Workbook

Sheet Test Plan
A1: Section | B1: Details
A2: Project name | B2: Guru99 Banking project
A3: Document | B3: Test plan
A4: SRS version | B4: 2
A5: Testing type | B5: Manual functional testing
A6: Objective | B6: Verify that Guru99 Bank meets the specified functional requirements
A7: Scope | B7: Functional testing and external interfaces
A8: Out of scope | B8: Automation testing and performance/stress testing
A9: Roles | B9: Manager and customer
A10: Test environment | B10: Browser, OS
A11: Test data | B11: Customer, account, login and transaction data
A12: Entry criteria | B12: Requirements available and test environment accessible
A13: Exit criteria | B13: Planned test cases executed and defects documented
A14: Deliverables | B14: Test cases, bug report, RTM, test execution, summary report
A15: Test approach | B15: Black-box manual testing using requirement-based testing, equivalence partitioning, boundary value analysis, positive and negative testing and error guessing
A16: Test levels | B16: System testing of each module through the web interface
... A23: Risks and assumptions | B23: The application is a shared public demo site that may change, show errors or lose data; results depend on its behavior at the time of execution

Sheet Test Scenarios
A1: Scenario ID | B1: Scenario | C1: Req | D1: Test Cases
A2: SC_LG_01 | B2: Successful login as Manager | C2: 3.1.1 | D2: TC_LG_001
A3: SC_LG_02 | B3: Successful login as Customer | C3: 3.1.1 | D3: -
A4: SC_LG_03 | B4: Empty fields (User ID / Password / both) | C4: L1, L2 | D4: TC_LG_002 - TC_LG_004
A5: SC_LG_04 | B5: Invalid credentials (User ID or Password) | C5: L3 | D5: TC_LG_005 - TC_LG_006
A6: SC_LG_05 | B6: Case sensitivity of the credentials | C6: 3.1.1 | D6: TC_LG_007 - TC_LG_008
A7: SC_LG_06 | B7: Account lockout after 3 failed attempts | C7: L4, L5 | D7: TC_LG_009
A8: SC_LG_07 | B8: Login blocked for a locked account, even with valid credentials | C8: L4 | D8: TC_LG_010
A9: SC_LG_08 | B9: Reset button behavior | C9: 3.1.1 | D9: TC_LG_011
A10: SC_LG_09 | B10: Field properties (password masking, 30-character limit, spaces, special characters) | C10: 3.1.1 | D10: TC_LG_012 - TC_LG_013, TC_LG_015
A11: SC_LG_10 | B11: Logout and session termination | C11: 2.0 | D11: TC_LG_016 - TC_LG_017
A12: SC_LG_11 | B12: Session timeout after 15 minutes of inactivity | C12: 2.1.4 / E54 | D12: -
... A111: SC_CP_08 | B111: Security input (SQL injection) | C111: General | D111: TC_CP_023

Sheet Test Cases
A1: ID | B1: Title | C1: Description | D1: Pre-Condition | E1: Test steps | F1: Test data | G1: Priority | H1: Expected Result | I1: Actual result | J1: Status | K1: Designer | L1: Executer
A2: TC_LG_001 | B2: Successful login as Manager | C2: Verify that a Manager can log in with valid credentials | D2: Manager account exists and is active; Login page is open in Chrome | E2: 1. Enter User ID 2. Enter Password 3. Click Submit | F2: User ID: mngr668217 Password: rUqyzUv | G2: High | H2: User is redirected to the Manager Dashboard, and all Manager modules are displayed | I2: The manager was redirected to the Manager dashboard. | J2: Pass | K2: Amjad | L2: Amjad
A3: TC_LG_002 | B3: Empty User ID | C3: Verify that login is blocked when User ID is empty | D3: Login page is open | E3: 1. Leave User ID empty 2. Enter Password 3. Click Submit | F3: User ID: Password: rUqyzUv | G3: High | H3: E1: "User ID must not be blank" is displayed; login is not allowed | I3: The error message "User ID must not be blank" was displayed. | J3: Pass | K3: Amjad | L3: Amjad
A4: TC_LG_003 | B4: Empty Password | C4: Verify that login is blocked when Password is empty | D4: Login page is open | E4: 1. Enter User ID 2. Leave Password empty 3. Click Submit | F4: User ID: mngr668217 Password: | G4: High | H4: E2: "Password must not be blank" is displayed; login is not allowed | I4: The error message "Password must not be blank" was displayed. | J4: Pass | K4: Amjad | L4: Amjad
A5: TC_LG_004 | B5: Both fields empty | C5: Verify validation messages when both fields are empty | D5: Login page is open | E5: 1. Leave both fields empty 2. Click Submit | F5: User ID: Password: | G5: High | H5: E1 and E2 are displayed; login is not allowed | I5: The error messages "User ID must not be blank" and "Password must not be blank" were displayed. | J5: Pass | K5: Amjad | L5: Amjad
A6: TC_LG_005 | B6: Non-existent User ID | C6: Verify that an unregistered User ID is rejected | D6: Login page is open; the User ID does not exist in the system | E6: 1. Enter an unregistered User ID 2. Enter any Password 3. Click Submit | F6: User ID: ghost999 Password: Pass@123 | G6: High | H6: E3: "User ID and Password do not match" is displayed | I6: The alert "User is not valid" was displayed instead of the message required by the SRS (E3: "User ID and Password do not match"). The login was rejected. | J6: Fail | K6: Amjad | L6: Amjad
A7: TC_LG_006 | B7: Incorrect Password | C7: Verify that a valid User ID with a wrong Password is rejected | D7: Manager account exists and is active | E7: 1. Enter a valid User ID 2. Enter an incorrect Password 3. Click Submit | F7: User ID: mngr668217 Password: wrongpas | G7: High | H7: E3 is displayed; login is not allowed | I7: The alert "User is not valid" was displayed instead of the message required by the SRS (E3: "User ID and Password do not match"). The login was rejected. | J7: Fail | K7: Amjad | L7: Amjad
A8: TC_LG_007 | B8: Case sensitivity: User ID | C8: Verify that the User ID is case-sensitive | D8: Manager account "mngr668217" exists | E8: 1. Enter the User ID in uppercase 2. Enter the correct Password 3. Click Submit | F8: User ID: MNGR668217 Password: rUqyzUv | G8: Medium | H8: E3 is displayed (login rejected) | I8: The system accepted the User ID in uppercase and redirected the manager to the dashboard (the User ID is not case-sensitive). | J8: Fail | K8: Amjad | L8: Amjad
A9: TC_LG_008 | B9: Case sensitivity: Password | C9: Verify that the Password is case-sensitive | D9: Manager account "mngr668217" exists with password "rUqyzUv" | E9: 1. Enter the correct User ID 2. Enter the Password with different casing 3. Click Submit | F9: User ID: mngr668217 Password: RUQYZUV | G9: Medium | H9: E3 is displayed (login rejected) | I9: The system accepted the Password with different letter casing and redirected the manager to the dashboard (the Password is not case-sensitive). | J9: Fail | K9: Amjad | L9: Amjad
A10: TC_LG_009 | B10: Lockout after 3 failed attempts | C10: Verify that the account is locked after 3 consecutive failed login attempts | D10: Manager account is active and not locked; failed-attempt counter is 0 | E10: 1. Enter valid User ID and wrong Password, click Submit 2. Repeat step 1 (2nd attempt) 3. Repeat step 1 (3rd attempt) | F10: User ID: mngr668217 Password: wrongpas (wrong password, 3 consecutive attempts) | G10: High | H10: Attempts 1 and 2: E3 is displayed. Attempt 3: the account is locked and E55 is displayed (SRS is unclear about the 3rd-attempt message) | I10: The account was not locked after the 3 failed attempts and no error message was displayed. | J10: Fail | K10: Amjad | L10: Amjad
A11: TC_LG_010 | B11: Locked account with valid credentials | C11: Verify that a locked account cannot log in even with correct credentials | D11: Account is locked (after TC_LG_009) | E11: 1. Enter valid User ID 2. Enter correct Password 3. Click Submit | F11: User ID: mngr668217 Password: rUqyzUv (valid password) | G11: High | H11: Login is rejected with the lockout message (E55) | I11: The account was not locked, so the lockout message (E55) was not displayed. | J11: Fail | K11: Amjad | L11: Amjad
A12: TC_LG_011 | B12: Reset button | C12: Verify that the Reset button clears the form | D12: Login page is open | E12: 1. Enter data in both fields 2. Click Reset | F12: User ID: mngr668217 Password: rUqyzUv | G12: Medium | H12: Both fields are cleared, and no error messages are displayed | I12: Both fields were cleared and no error message was displayed. | J12: Pass | K12: Amjad | L12: Amjad
... A19: TC_LG_018 | B19: Access without login | C19: Verify that protected pages require authentication | D19: User is not logged in; a valid internal page URL is available | E19: 1. Open an internal page URL directly in the browser | F19: Direct URL of an internal page | G19: High | H19: User is redirected to the Login page | I19: The system opened the protected page directly without any authentication. | J19: Fail | K19: Amjad | L19: Amjad
B20: New Customer
A21: TC_NC_001 | B21: Create customer with valid data | C21: Verify a customer is created with all valid fields | D21: 1. Logged in as Manager 2. New Customer page is open | E21: 1. Enter the values from Test data 2. Click Submit | F21: Customer Name: John Smith Gender: Male Date of Birth: 1990-05-15 Address: 12 Main Street City: Alexandria State: Alexandria PIN Code: 123456 Mobile Number: 5551234567 Email: john.smith01@test.com Password: Pass@123 | G21: High | H21: Customer is created; a unique Customer ID is generated and a confirmation is displayed | I21: The customer was created successfully. Generated Customer ID: 4073. | J21: Pass | K21: Amjad | L21: Amjad
A22: TC_NC_002 | B22: Form fields and buttons | C22: Verify all fields in SRS 3.1.2 exist | D22: 1. Logged in as Manager 2. New Customer page is open | E22: 1. Open the New Customer page 2. Review the form | F22: – | G22: Medium | H22: Customer Name, Gender (Male/Female radio), Date of Birth (date picker), Address (textarea), City, State, PIN Code, Mobile Number, Email, Password, Submit and Reset are present | I22: Customer Name, Gender (Male/Female radio), Date of Birth (date picker), Address (textarea), City, State, PIN Code, Mobile Number, Email, Password, Submit and Reset are present | J22: Pass | K22: Amjad | L22: Amjad
A23: TC_NC_003 | B23: Reset button | C23: Verify Reset clears the form | D23: 1. Logged in as Manager 2. New Customer page is open | E23: 1. Enter the values from Test data 2. Click Reset | F23: Customer Name: John Smith Gender: Male Date of Birth: 1990-05-15 Address: 12 Main Street City: Alexandria State: Alexandria PIN Code: 123456 Mobile Number: 5551234567 Email: john.smith03@test.com Password: Pass@123 | G23: Medium | H23: All fields are cleared, Gender is deselected, and no error is displayed | I23: All fields are cleared, Gender is deselected, and no error is displayed | J23: Pass | K23: Amjad | L23: Amjad
A24: TC_NC_004 | B24: Unique Customer ID | C24: Verify each new customer gets a different ID | D24: 1. Logged in as Manager 2. New Customer page is open | E24: 1. Create customer A using the Customer A values 2. Create customer B using the Customer B values | F24: Customer Name: John Smith Gender: Male Date of Birth: 1990-05-15 Address: 12 Main Street City: Alexandria State: Alexandria PIN Code: 123456 Mobile Number: 5551234567 Email: Customer A: john.smith04a@test.com Customer B: john.smith04b@test.com ◄ Password: Pass@123 | G24: High | H24: Two different Customer IDs are generated | I24: Both customers were created successfully. Generated Customer IDs: 4620 (customer A) and 78692 (customer B). | J24: Pass | K24: Amjad | L24: Amjad
A25: TC_NC_005 | B25: Created customer data is saved correctly | C25: Verify saved details via Edit Customer | D25: 1. Logged in as Manager 2. Customer created in TC_NC_001 (Customer ID 4073) | E25: 1. Open the Edit Customer page 2. Enter the generated Customer ID 3. Submit | F25: Customer ID: 4073 Values to compare (from TC_NC_001): Customer Name: John Smith Gender: Male Date of Birth: 1990-05-15 Address: 12 Main Street City: Alexandria State: Alexandria PIN Code: 123456 Mobile Number: 5551234567 Email: john.smith01@test.com Password: Pass@123 | G25: High | H25: All entered details (name, gender, DOB, address, city, state, PIN, mobile, email) match what was entered | I25: All entered details (name, gender, DOB, address, city, state, PIN, mobile, email) match what was entered | J25: Pass | K25: Amjad | L25: Amjad
A26: TC_NC_006 | B26: Name: blank (NC1) | C26: Verify blank name is rejected | D26: 1. Logged in as Manager 2. New Customer page is open | E26: 1. Leave Customer Name empty and enter the rest from Test data 2. Click Submit | F26: Customer Name: (empty) ◄ Gender: Male Date of Birth: 1990-05-15 Address: 12 Main Street City: Alexandria State: Alexandria PIN Code: 123456 Mobile Number: 5551234567 Email: john.smith06@test.com Password: Pass@123 | G26: High | H26: E4: "Customer Name must not be blank"; no customer created | I26: E4: "Customer Name must not be blank"; no customer created | J26: Pass | K26: Amjad | L26: Amjad
A27: TC_NC_007 | B27: Name: numbers (NC2) | C27: Verify numbers are rejected | D27: 1. Logged in as Manager 2. New Customer page is open | E27: 1. Enter the values from Test data 2. Click Submit | F27: Customer Name: John123 ◄ Gender: Male Date of Birth: 1990-05-15 Address: 12 Main Street City: Alexandria State: Alexandria PIN Code: 123456 Mobile Number: 5551234567 Email: john.smith07@test.com Password: Pass@123 | G27: High | H27: E48: "Numbers are not allowed" | I27: E48: "Numbers are not allowed" | J27: Pass | K27: Amjad | L27: Amjad
A28: TC_NC_008 | B28: Name: special characters (NC3) | C28: Verify special characters are rejected | D28: 1. Logged in as Manager 2. New Customer page is open | E28: 1. Enter the values from Test data 2. Click Submit | F28: Customer Name: John@#$ ◄ Gender: Male Date of Birth: 1990-05-15 Address: 12 Main Street City: Alexandria State: Alexandria PIN Code: 123456 Mobile Number: 5551234567 Email: john.smith08@test.com Password: Pass@123 | G28: High | H28: E46: "Special characters are not allowed" | I28: E46: "Special characters are not allowed" | J28: Pass | K28: Amjad | L28: Amjad
A29: TC_NC_009 | B29: Name: leading space (NC4) | C29: Verify a leading space is rejected | D29: 1. Logged in as Manager 2. New Customer page is open | E29: 1. Enter the values from Test data 2. Click Submit | F29: Customer Name: " John" (a space, then John) ◄ Gender: Male Date of Birth: 1990-05-15 Address: 12 Main Street City: Alexandria State: Alexandria PIN Code: 123456 Mobile Number: 5551234567 Email: john.smith09@test.com Password: Pass@123 | G29: Medium | H29: E47: "First character cannot be space" | I29: E47: "First character cannot be space" | J29: Pass | K29: Amjad | L29: Amjad
A30: TC_NC_010 | B30: Name: spaces between words | C30: Verify a valid multi-word name is accepted | D30: 1. Logged in as Manager 2. New Customer page is open | E30: 1. Enter the values from Test data 2. Click Submit | F30: Customer Name: Mary Ann Lee ◄ Gender: Male Date of Birth: 1990-05-15 Address: 12 Main Street City: Alexandria State: Alexandria PIN Code: 123456 Mobile Number: 5551234567 Email: john.smith10@test.com Password: Pass@123 | G30: Medium | H30: Customer is created successfully | I30: Customer is created successfully | J30: Pass | K30: Amjad | L30: Amjad
A31: TC_NC_011 | B31: Name: max length 50 (BVA) | C31: Verify the 50-character limit | D31: 1. Logged in as Manager 2. New Customer page is open | E31: 1. Enter the values of Attempt 1 from Test data, click Submit 2. Reopen the New Customer page, enter the values of Attempt 2, click Submit | F31: Customer Name: [Attempt 1] AbcdefghijAbcdefghijAbcdefghijAbcdefghijAbcdefghij (50 letters) [Attempt 2] AbcdefghijAbcdefghijAbcdefghijAbcdefghijAbcdefghijk (51 letters) ◄ Gender: Male Date of Birth: 1990-05-15 Address: 12 Main Street City: Alexandria State: Alexandria PIN Code: 123456 Mobile Number: 5551234567 Email: [Attempt 1] john.smith11a@test.com [Attempt 2] john.smith11b@test.com Password: Pass@123 | G31: Medium | H31: 50 characters are accepted; the 51st is rejected or truncated | I31: The Customer Name field accepts a maximum of 25 characters. | J31: Fail | K31: Amjad | L31: Amjad
A32: TC_NC_012 | B32: Gender: not selected (NC20) | C32: Verify Gender is mandatory | D32: 1. Logged in as Manager 2. New Customer page is open | E32: 1. Leave Gender unselected and enter the rest from Test data 2. Click Submit | F32: Customer Name: John Smith Gender: (none selected) ◄ Date of Birth: 1990-05-15 Address: 12 Main Street City: Alexandria State: Alexandria PIN Code: 123456 Mobile Number: 5551234567 Email: john.smith12@test.com Password: Pass@123 | G32: High | H32: An error is displayed and no customer is created (message not defined in SRS) | I32: A gender was selected by default, so the Gender field cannot be left unselected. | J32: Fail | K32: Amjad | L32: Amjad
... A72: TC_NC_052 | B72: Double submission | C72: Verify no duplicate customer is created | D72: 1. Logged in as Manager 2. New Customer page is open | E72: 1. Enter the values from Test data 2. Double-click Submit quickly | F72: Customer Name: John Smith Gender: Male Date of Birth: 1990-05-15 Address: 12 Main Street City: Alexandria State: Alexandria PIN Code: 123456 Mobile Number: 5551234567 Email: john.smith52@test.com Password: Pass@123 | G72: Medium | H72: Only one customer is created; the duplicate attempt is ignored or rejected (E49) | I72: Only one customer is created; the duplicate attempt is ignored or rejected (E49) | J72: Pass | K72: Amjad | L72: Amjad
B73: Edit Customer
A74: TC_EC_001 | B74: Retrieve customer with valid ID | C74: Verify customer details are displayed for a valid Customer ID | D74: 1. Logged in as Manager 2. Customer 4073 exists and is associated with this Manager (created in TC_NC_001 and not yet edited) 3. Edit Customer page is open | E74: 1. Enter the Customer ID from Test data 2. Click Submit | F74: Customer ID: 4073 Values entered in TC_NC_001: Customer Name: John Smith Gender: Male Date of Birth: 1990-05-15 Address: 12 Main Street City: Alexandria State: Alexandria PIN Code: 123456 Mobile Number: 5551234567 Email: john.smith01@test.com | G74: High | H74: Customer details are displayed in an editable form and match the values entered at creation | I74: Customer details are displayed in an editable form and match the values entered at creation | J74: Pass | K74: Amjad | L74: Amjad
A75: TC_EC_002 | B75: Non-editable fields are disabled | C75: Verify Customer ID, Customer Name, Gender and Date of Birth cannot be edited | D75: 1. Logged in as Manager 2. Customer 4073 exists and is associated with this Manager (created in TC_NC_001) 3. Edit Customer page is open | E75: 1. Load customer 4073 2. Try to type in / change Customer ID, Customer Name, Gender and Date of Birth | F75: Customer ID: 4073 | G75: High | H75: Customer ID, Customer Name, Gender and Date of Birth are disabled and cannot be changed | I75: Customer ID, Customer Name, Gender and Date of Birth are disabled and cannot be changed | J75: Pass | K75: Amjad | L75: Amjad
A76: TC_EC_003 | B76: Editable fields are enabled | C76: Verify Address, City, State, PIN, Mobile and Email can be edited | D76: 1. Logged in as Manager 2. Customer 4073 exists and is associated with this Manager (created in TC_NC_001) 3. Edit Customer page is open | E76: 1. Load customer 4073 2. Click into each of the six fields and type | F76: Customer ID: 4073 | G76: High | H76: Address, City, State, PIN Code, Mobile Number and Email accept input | I76: Address, City, State, PIN Code, Mobile Number and Email accept input | J76: Pass | K76: Amjad | L76: Amjad
A77: TC_EC_004 | B77: Customer ID: blank (EC1) | C77: Verify blank Customer ID is rejected | D77: 1. Logged in as Manager 2. Edit Customer page is open | E77: 1. Leave Customer ID empty 2. Click Submit | F77: Customer ID: (empty) ◄ | G77: High | H77: E15: "Customer ID must not be blank" | I77: E15: "Customer ID must not be blank" | J77: Pass | K77: Amjad | L77: Amjad
A78: TC_EC_005 | B78: Customer ID: non-numeric (EC2) | C78: Verify letters and symbols are rejected | D78: 1. Logged in as Manager 2. Edit Customer page is open | E78: 1. Enter the Attempt 1 value, click Submit 2. Repeat for the Attempt 2 value | F78: Customer ID: [Attempt 1] ABC123 [Attempt 2] 12@#45 ◄ | G78: High | H78: E16: "Customer ID must be numeric" for each attempt | I78: E16: "Customer ID must be numeric" for each attempt | J78: Pass | K78: Amjad | L78: Amjad
A79: TC_EC_006 | B79: Customer ID: unusual numeric values | C79: Verify zero, negative and decimal values are handled | D79: 1. Logged in as Manager 2. Edit Customer page is open | E79: 1. Enter the Attempt 1 value, click Submit 2. Repeat for each remaining attempt | F79: Customer ID: [Attempt 1] 0 [Attempt 2] -5 [Attempt 3] 12.5 ◄ | G79: Low | H79: Each value is rejected with E16 or the "Customer ID does not exist" error; no customer is loaded | I79: Each value is rejected with E16 or the "Customer ID does not exist" error; no customer is loaded | J79: Pass | K79: Amjad | L79: Amjad
A80: TC_EC_007 | B80: Customer ID: does not exist (EC3) | C80: Verify an unknown Customer ID is rejected | D80: 1. Logged in as Manager 2. Edit Customer page is open | E80: 1. Enter a non-existent ID 2. Click Submit | F80: Customer ID: 999999999 ◄ | G80: High | H80: E51: "Customer ID does not exist" | I80: E51: "Customer ID does not exist" | J80: Pass | K80: Amjad | L80: Amjad
A81: TC_EC_008 | B81: Customer of another Manager (EC4) | C81: Verify a Manager cannot edit a customer associated with another Manager | D81: 1. A second Manager account exists 2. Customer 4073 is associated with Manager 1 only 3. Logged in as Manager 2 | E81: 1. Log in as Manager 2 2. Open Edit Customer 3. Enter the Customer ID of customer 4073, click Submit | F81: Customer ID: 4073 ◄ Logged in as: Manager 2 (a different Manager) | G81: High | H81: E44 is displayed; the customer details are not loaded | I81: E44 is displayed; the customer details are not loaded | J81: Pass | K81: Amjad | L81: Amjad
A82: TC_EC_009 | B82: Customer ID: SQL injection | C82: Verify basic SQL input is handled safely | D82: 1. Logged in as Manager 2. Edit Customer page is open | E82: 1. Enter the value from Test data 2. Click Submit | F82: Customer ID: 1 OR 1=1 ◄ | G82: Medium | H82: Input is rejected (E16); no customer data is returned and no database error is displayed | I82: Input is rejected (E16); no customer data is returned and no database error is displayed | J82: Pass | K82: Amjad | L82: Amjad
A83: TC_EC_010 | B83: Update all editable fields with valid data | C83: Verify all six editable fields can be updated together | D83: 1. Logged in as Manager 2. Customer 4073 exists and is associated with this Manager (created in TC_NC_001) 3. Edit Customer page is open | E83: 1. Enter the Customer ID from Test data and click Submit 2. Change the field(s) marked ◄ to the values in Test data 3. Click Submit | F83: Customer ID: 4073 Address: 45 Park Avenue ◄ City: Cairo ◄ State: Cairo ◄ PIN Code: 654321 ◄ Mobile Number: 5559876543 ◄ Email: john.edit10@test.com ◄ | G83: High | H83: Customer is updated successfully and a confirmation is displayed (message not defined in SRS) | I83: The customer data was updated, but no success message was displayed and the system redirected the manager to an empty white page. | J83: Fail | K83: Amjad | L83: Amjad
A84: TC_EC_011 | B84: Updated data is persisted | C84: Verify the update is saved by reloading the customer | D84: 1. Logged in as Manager 2. Customer 4073 exists and is associated with this Manager (updated in TC_EC_010) 3. Edit Customer page is open | E84: 1. Enter the Customer ID, click Submit 2. Compare the loaded values with the Test data | F84: Customer ID: 4073 Expected values (from TC_EC_010): Address: 45 Park Avenue City: Cairo State: Cairo PIN Code: 654321 Mobile Number: 5559876543 Email: john.edit10@test.com Customer Name, Gender and Date of Birth: unchanged (see TC_NC_001) | G84: High | H84: All six fields show the updated values; Name, Gender and DOB are unchanged | I84: All six fields show the updated values; Name, Gender and DOB are unchanged | J84: Pass | K84: Amjad | L84: Amjad
A85: TC_EC_012 | B85: Update a single field only | C85: Verify updating one field leaves the others unchanged | D85: 1. Logged in as Manager 2. Customer 4073 exists and is associated with this Manager (created in TC_NC_001) 3. Edit Customer page is open | E85: 1. Enter the Customer ID from Test data and click Submit 2. Change the field(s) marked ◄ to the values in Test data 3. Click Submit | F85: Customer ID: 4073 Address: 78 River Road ◄ City: (leave as loaded) State: (leave as loaded) PIN Code: (leave as loaded) Mobile Number: (leave as loaded) Email: (leave as loaded) | G85: Medium | H85: Address is updated; City, State, PIN, Mobile and Email keep their previous values | I85: The address was updated and the other fields kept their previous values; no success message was displayed. | J85: Pass | K85: Amjad | L85: Amjad
... A113: TC_EC_040 | B113: XSS input | C113: Verify script input is not executed | D113: 1. Logged in as Manager 2. Customer 4073 exists and is associated with this Manager (created in TC_NC_001) 3. Edit Customer page is open | E113: 1. Enter the Customer ID from Test data and click Submit 2. Change the field(s) marked ◄ to the values in Test data 3. Click Submit | F113: Customer ID: 4073 Address: <script>alert('x')</script> ◄ City: (leave as loaded) State: (leave as loaded) PIN Code: (leave as loaded) Mobile Number: (leave as loaded) Email: (leave as loaded) | G113: High | H113: Input is rejected and no script is executed | I113: The input was rejected and no script was executed. | J113: Pass | K113: Amjad | L113: Amjad
B114: Delete customer
A115: TC_DC_001 | B115: Delete customer without accounts | C115: Verify a customer with no accounts can be deleted after confirmation | D115: 1. Logged in as Manager 2. Customer 4073 exists, has no accounts and is associated with this Manager 3. Delete Customer page is open | E115: 1. Enter the Customer ID from Test data 2. Click Delete 3. Confirm in the dialog | F115: Customer ID: 4073 ◄ | G115: High | H115: A confirmation dialog appears; after confirming, the customer is deleted and a success message is displayed (message not defined in SRS) | I115: The customer was deleted, but the system redirected the manager to a "This page isn't working" error page; no success or error message was displayed. | J115: Fail | K115: Amjad | L115: Amjad
A116: TC_DC_002 | B116: Confirmation dialog before deletion | C116: Verify deletion is not executed until the Manager confirms | D116: 1. Logged in as Manager 2. Customer 4073 exists with no accounts 3. Delete Customer page is open | E116: 1. Enter the Customer ID 2. Click Delete 3. Observe the dialog without confirming | F116: Customer ID: 4073 ◄ | G116: High | H116: A confirmation dialog is displayed after clicking Delete; the customer still exists until the dialog is confirmed | I116: The system redirected the manager to a "This page isn't working" error page and deleted the customer without any success or error message. | J116: Pass | K116: Amjad | L116: Amjad
A117: TC_DC_003 | B117: Cancel the confirmation dialog | C117: Verify cancelling keeps the customer | D117: 1. Logged in as Manager 2. Customer 4073 exists with no accounts 3. Delete Customer page is open | E117: 1. Enter the Customer ID 2. Click Delete 3. Click Cancel in the dialog 4. Open Edit Customer and load the same ID | F117: Customer ID: 4073 ◄ | G117: High | H117: The customer is not deleted; loading the ID in Edit Customer still shows the customer details | I117: The customer was not deleted; loading the ID in Edit Customer still shows the customer details. | J117: Pass | K117: Amjad | L117: Amjad
A118: TC_DC_004 | B118: Deleted customer cannot be retrieved | C118: Verify the deleted customer no longer exists | D118: 1. Logged in as Manager 2. Customer 4073 was deleted in TC_DC_001 | E118: 1. Open Edit Customer 2. Enter the deleted Customer ID 3. Click Submit | F118: Customer ID: 4073 (deleted in TC_DC_001) ◄ | G118: High | H118: E51: "Customer ID does not exist" | I118: The error message E51 "Customer ID does not exist" was displayed, but the system also redirected the manager to a "This page isn't working" error page. | J118: Pass | K118: Amjad | L118: Amjad
A119: TC_DC_005 | B119: Delete an already deleted customer | C119: Verify deleting the same ID twice is handled (DC3) | D119: 1. Logged in as Manager 2. Customer 4073 was deleted in TC_DC_001 3. Delete Customer page is open | E119: 1. Enter the Customer ID from Test data 2. Click Delete | F119: Customer ID: 4073 (already deleted) ◄ | G119: Medium | H119: E51: "Customer ID does not exist" | I119: The error message E51 "Customer ID does not exist" was displayed, but the system also redirected the manager to a "This page isn't working" error page. | J119: Pass | K119: Amjad | L119: Amjad
A120: TC_DC_006 | B120: Customer ID: blank (DC1) | C120: Verify blank Customer ID is rejected | D120: 1. Logged in as Manager 2. Delete Customer page is open | E120: 1. Enter the Customer ID from Test data 2. Click Delete | F120: Customer ID: (empty) ◄ | G120: High | H120: E15: "Customer ID must not be blank" | I120: E15: "Customer ID must not be blank" | J120: Pass | K120: Amjad | L120: Amjad
A121: TC_DC_007 | B121: Customer ID: non-numeric (DC2) | C121: Verify letters and symbols are rejected | D121: 1. Logged in as Manager 2. Delete Customer page is open | E121: 1. Enter the Attempt 1 value (other fields valid), click Delete 2. Repeat for each remaining attempt | F121: Customer ID: [Attempt 1] ABC123 [Attempt 2] 12@#45 ◄ | G121: High | H121: E16: "Customer ID must be numeric" for each attempt | I121: E16: "Customer ID must be numeric" for each attempt | J121: Pass | K121: Amjad | L121: Amjad
A122: TC_DC_008 | B122: Customer ID: zero, negative, decimal | C122: Verify unusual numeric values are handled | D122: 1. Logged in as Manager 2. Delete Customer page is open | E122: 1. Enter the Attempt 1 value (other fields valid), click Delete 2. Repeat for each remaining attempt | F122: Customer ID: [Attempt 1] 0 [Attempt 2] -5 [Attempt 3] 12.5 ◄ | G122: Low | H122: Each value is rejected with E16 or E51; nothing is deleted | I122: Each value is rejected with E16 or E51; nothing is deleted | J122: Pass | K122: Amjad | L122: Amjad
A123: TC_DC_009 | B123: Customer ID: does not exist (DC3) | C123: Verify an unknown ID is rejected | D123: 1. Logged in as Manager 2. Delete Customer page is open | E123: 1. Enter the Customer ID from Test data 2. Click Delete | F123: Customer ID: 999999999 ◄ | G123: High | H123: E51: "Customer ID does not exist" | I123: E51: "Customer ID does not exist" | J123: Pass | K123: Amjad | L123: Amjad
A124: TC_DC_010 | B124: Customer with active accounts (DC4) | C124: Verify a customer with accounts cannot be deleted | D124: 1. Logged in as Manager 2. Customer 38892 has active accounts 185657 and 185658 3. Delete Customer page is open | E124: 1. Enter the Customer ID 2. Click Delete 3. Confirm in the dialog (if shown) | F124: Customer ID: 38892 ◄ (owner of accounts 185657 and 185658) | G124: High | H124: E52: "Customer has active accounts and cannot be deleted"; the customer and accounts remain | I124: E52: "Customer has active accounts and cannot be deleted"; the customer and accounts remain | J124: Pass | K124: Amjad | L124: Amjad
A125: TC_DC_011 | B125: Customer of another Manager (DC5) | C125: Verify a Manager cannot delete another Manager's customer | D125: 1. A second Manager account exists (Manager 2) and owns customer/account that are NOT associated with Manager 1 2. Logged in as Manager 1 3. Delete Customer page is open | E125: 1. Enter the Customer ID from Test data 2. Click Delete | F125: Customer ID: a Manager 2 customer (ID not recorded) ◄ Logged in as: Manager 1 | G125: High | H125: E44 is displayed; the customer is not deleted | I125: E44 is displayed; the customer is not deleted | J125: Pass | K125: Amjad | L125: Amjad
A126: TC_DC_012 | B126: Reset button | C126: Verify Reset clears the form | D126: 1. Logged in as Manager 2. Delete Customer page is open | E126: 1. Type the Customer ID 2. Click Reset | F126: Customer ID: 12345 (typed, then Reset) | G126: Low | H126: The Customer ID field is cleared and no error is displayed | I126: The Customer ID field is cleared and no error is displayed | J126: Pass | K126: Amjad | L126: Amjad
... A128: TC_DC_014 | B128: Browser refresh after deletion | C128: Verify refreshing after a deletion does not crash | D128: 1. Logged in as Manager 2. Delete Customer page is open | E128: 1. After a successful deletion press F5 and confirm the resubmission prompt (if any) | F128: Customer ID: 4073 (deleted in TC_DC_001) | G128: Low | H128: No server error is shown; the page shows E51 or reloads the empty form | I128: The system redirected the manager to a "This page isn't working" error page; no success or error message was displayed. | J128: Fail | K128: Amjad | L128: Amjad
B129: New Account
A130: TC_NA_001 | B130: Create Savings account with valid data | C130: Verify a Savings account is created (account 185657) | D130: 1. Logged in as Manager 2. Customer 38892 exists and is associated with this Manager 3. New Account page is open | E130: 1. Enter the values from Test data 2. Click Submit | F130: Customer ID: 38892 Account Type: Savings Initial Deposit: 1000 | G130: High | H130: A unique Account Number is generated and a confirmation is displayed with the account details | I130: The account was created successfully. Generated Account ID: 185657. | J130: Pass | K130: Amjad | L130: Amjad
A131: TC_NA_002 | B131: Create Current account with valid data | C131: Verify a Current account is created (account 185658) | D131: 1. Logged in as Manager 2. Customer 38892 exists and is associated with this Manager 3. New Account page is open | E131: 1. Enter the values from Test data 2. Click Submit | F131: Customer ID: 38892 Account Type: Current ◄ Initial Deposit: 5000 ◄ | G131: High | H131: A unique Account Number is generated and a confirmation is displayed | I131: The account was created successfully. Generated Account ID: 185658. | J131: Pass | K131: Amjad | L131: Amjad
A132: TC_NA_003 | B132: Form fields and buttons | C132: Verify fields in SRS 3.1.5 exist | D132: 1. Logged in as Manager 2. Customer 38892 exists and is associated with this Manager 3. New Account page is open | E132: 1. Open the New Account page 2. Review the form and open the Account Type dropdown | F132: – | G132: Medium | H132: Customer ID, Account Type (dropdown with only Savings and Current), Initial Deposit, Submit and Reset are present | I132: Customer ID, Account Type (dropdown with only Savings and Current), Initial Deposit, Submit and Reset are present | J132: Pass | K132: Amjad | L132: Amjad
A133: TC_NA_004 | B133: Unique account numbers | C133: Verify every account gets a different number | D133: 1. Logged in as Manager 2. Customer 38892 exists and is associated with this Manager 3. New Account page is open | E133: 1. Compare the Account Numbers generated in TC_NA_001 and TC_NA_002 | F133: Account 185657 (created in TC_NA_001) and account 185658 (created in TC_NA_002) | G133: High | H133: The Account Numbers generated for 185657 and 185658 are different | I133: The Account Numbers 185657 and 185658 are different. | J133: Pass | K133: Amjad | L133: Amjad
A134: TC_NA_005 | B134: Reset button | C134: Verify Reset clears the form | D134: 1. Logged in as Manager 2. Customer 38892 exists and is associated with this Manager 3. New Account page is open | E134: 1. Enter the values from Test data 2. Click Reset | F134: Customer ID: 38892 Account Type: Savings Initial Deposit: 1000 | G134: Medium | H134: All fields are cleared and the dropdown returns to its default; no error is displayed | I134: All fields are cleared and the dropdown returns to its default; no error is displayed | J134: Pass | K134: Amjad | L134: Amjad
A135: TC_NA_006 | B135: Several accounts for one customer | C135: Verify one customer can own more than one account of the same type | D135: 1. Logged in as Manager 2. Customer 38892 exists and is associated with this Manager 3. New Account page is open | E135: 1. Enter the values from Test data 2. Click Submit | F135: Customer ID: 38892 Account Type: Savings Initial Deposit: 1500 ◄ | G135: Medium | H135: A second Savings account is created for customer 38892 with a new Account Number | I135: The account was created successfully. Generated Account ID: 185659. | J135: Pass | K135: Amjad | L135: Amjad
A136: TC_NA_007 | B136: Opening balance equals initial deposit | C136: Verify the new account balance | D136: 1. Logged in as Manager 2. Account 185657 was created in TC_NA_001 and no other transaction was made on it | E136: 1. Open Balance Enquiry 2. Enter the Account Number of 185657 3. Click Submit | F136: Account Number: 185657 Expected balance: 1000.00 | G136: High | H136: Balance Enquiry for 185657 shows a balance equal to the Initial Deposit | I136: The system redirected the manager to a "This page isn't working" error page, so the balance could not be verified. | J136: Fail | K136: Amjad | L136: Amjad
A137: TC_NA_008 | B137: Customer ID: blank (NA1) | C137: Verify blank Customer ID is rejected | D137: 1. Logged in as Manager 2. Customer 38892 exists and is associated with this Manager 3. New Account page is open | E137: 1. Enter the values from Test data 2. Click Submit | F137: Customer ID: (empty) ◄ Account Type: Savings Initial Deposit: 1000 | G137: High | H137: E15: "Customer ID must not be blank" | I137: E15: "Customer ID must not be blank" | J137: Pass | K137: Amjad | L137: Amjad
A138: TC_NA_009 | B138: Customer ID: non-numeric (NA2) | C138: Verify letters and symbols are rejected | D138: 1. Logged in as Manager 2. Customer 38892 exists and is associated with this Manager 3. New Account page is open | E138: 1. Enter the Attempt 1 value (other fields valid), click Submit 2. Repeat for each remaining attempt | F138: Customer ID: [Attempt 1] ABC123 [Attempt 2] 12@#45 ◄ Account Type: Savings Initial Deposit: 1000 | G138: High | H138: E16: "Customer ID must be numeric" for each attempt | I138: E16: "Customer ID must be numeric" for each attempt | J138: Pass | K138: Amjad | L138: Amjad
A139: TC_NA_010 | B139: Customer ID: zero, negative, decimal | C139: Verify unusual numeric values are handled | D139: 1. Logged in as Manager 2. Customer 38892 exists and is associated with this Manager 3. New Account page is open | E139: 1. Enter the Attempt 1 value (other fields valid), click Submit 2. Repeat for each remaining attempt | F139: Customer ID: [Attempt 1] 0 [Attempt 2] -5 [Attempt 3] 12.5 ◄ Account Type: Savings Initial Deposit: 1000 | G139: Low | H139: Each value is rejected with E16 or E51; no account is created | I139: Each value is rejected with E16 or E51; no account is created | J139: Pass | K139: Amjad | L139: Amjad
A140: TC_NA_011 | B140: Customer ID: does not exist (NA3) | C140: Verify an unknown Customer ID is rejected | D140: 1. Logged in as Manager 2. Customer 38892 exists and is associated with this Manager 3. New Account page is open | E140: 1. Enter the values from Test data 2. Click Submit | F140: Customer ID: 999999999 ◄ Account Type: Savings Initial Deposit: 1000 | G140: High | H140: E51: "Customer ID does not exist" | I140: E51: "Customer ID does not exist" | J140: Pass | K140: Amjad | L140: Amjad
A141: TC_NA_012 | B141: Customer of another Manager (NA4) | C141: Verify a Manager cannot open an account for another Manager's customer | D141: 1. A second Manager account exists (Manager 2) and owns customer/account that are NOT associated with Manager 1 2. Logged in as Manager 1 3. New Account page is open | E141: 1. Enter the values from Test data 2. Click Submit | F141: Customer ID: a Manager 2 customer (ID not recorded) ◄ Account Type: Savings Initial Deposit: 1000 | G141: High | H141: E44 is displayed; no account is created | I141: The message "You are not authorized to Add Account for this Customer" was displayed. | J141: Blocked | K141: Amjad | L141: Amjad
... A158: TC_NA_029 | B158: Double submission | C158: Verify no duplicate account is created | D158: 1. Logged in as Manager 2. Customer 38892 exists and is associated with this Manager 3. New Account page is open | E158: 1. Enter the values from Test data 2. Double-click Submit quickly | F158: Customer ID: 38892 Account Type: Savings Initial Deposit: 1000 | G158: Medium | H158: Only one account is created for the double-click | I158: The account was created successfully. Generated Account ID: 185664. | J158: Pass | K158: Amjad | L158: Amjad
B159: Edit Account
A160: TC_EA_001 | B160: Retrieve account with valid number | C160: Verify account details are displayed | D160: 1. Logged in as Manager 2. Account 185657 (Savings) exists and is associated with this Manager 3. Edit Account page is open | E160: 1. Enter the Account Number 2. Click Submit | F160: Account Number: 185657 ◄ | G160: High | H160: Account details are displayed in a form (Account Number, Customer ID, Account Type, Balance) | I160: After submitting the Account Number, the system redirected the manager to a "This page isn't working" error page. | J160: Fail | K160: Amjad | L160: Amjad
A161: TC_EA_002 | B161: Non-editable fields are disabled | C161: Verify Account Number, Customer ID and Balance cannot be edited | D161: 1. Logged in as Manager 2. Account 185657 (Savings) exists and is associated with this Manager 3. Edit Account page is open | E161: 1. Load 185657 2. Try to type in each of the three fields | F161: Account Number: 185657 | G161: High | H161: Account Number, Customer ID and Balance are disabled and cannot be changed | I161: The system redirected the manager to a "This page isn't working" error page. The test could not be completed. | J161: Blocked | K161: Amjad | L161: Amjad
A162: TC_EA_003 | B162: Account Type dropdown options | C162: Verify only Savings and Current are offered | D162: 1. Logged in as Manager 2. Account 185657 (Savings) exists and is associated with this Manager 3. Edit Account page is open | E162: 1. Load 185657 2. Open the Account Type dropdown | F162: Account Number: 185657 | G162: Medium | H162: The dropdown offers Savings and Current only; Account Type is editable | I162: The system redirected the manager to a "This page isn't working" error page. The test could not be completed. | J162: Blocked | K162: Amjad | L162: Amjad
A163: TC_EA_004 | B163: Change Savings to Current | C163: Verify the account type can be changed and is saved | D163: 1. Logged in as Manager 2. Account 185657 (Savings) exists and is associated with this Manager 3. Edit Account page is open | E163: 1. Enter the Account Number from Test data and click Submit 2. Change Account Type as shown in Test data 3. Click Submit 4. Reload 185657 and check Account Type | F163: Account Number: 185657 Account Type: Current ◄ | G163: High | H163: Account Type is updated and a confirmation is displayed; reloading 185657 shows Current | I163: The system redirected the manager to a "This page isn't working" error page. The test could not be completed. | J163: Blocked | K163: Amjad | L163: Amjad
A164: TC_EA_005 | B164: Change Current to Savings | C164: Verify the reverse change | D164: 1. Logged in as Manager 2. Account 185658 (Current) exists and is associated with this Manager 3. Edit Account page is open | E164: 1. Enter the Account Number from Test data and click Submit 2. Change Account Type as shown in Test data 3. Click Submit | F164: Account Number: 185658 Account Type: Savings ◄ | G164: Medium | H164: Account Type is updated; reloading 185658 shows Savings | I164: The system redirected the manager to a "This page isn't working" error page. The test could not be completed. | J164: Blocked | K164: Amjad | L164: Amjad
A165: TC_EA_006 | B165: Submit without changes | C165: Verify submitting an unchanged form is handled | D165: 1. Logged in as Manager 2. Account 185657 (Savings) exists and is associated with this Manager 3. Edit Account page is open | E165: 1. Enter the Account Number from Test data and click Submit 2. Change Account Type as shown in Test data 3. Click Submit | F165: Account Number: 185657 Account Type: (leave as loaded) | G165: Low | H165: No error occurs and the data remains unchanged (behavior not defined in SRS) | I165: The system redirected the manager to a "This page isn't working" error page. The test could not be completed. | J165: Blocked | K165: Amjad | L165: Amjad
A166: TC_EA_007 | B166: Balance unchanged after type change | C166: Verify editing does not affect the balance | D166: 1. Logged in as Manager 2. Account 185657 (Savings) exists and is associated with this Manager 3. Edit Account page is open | E166: 1. Note the balance in Balance Enquiry 2. Change Account Type (TC_EA_004) 3. Check the balance again | F166: Account Number: 185657 Balance before and after: compare | G166: High | H166: Balance Enquiry shows the same balance before and after the change | I166: The system redirected the manager to a "This page isn't working" error page. The test could not be completed. | J166: Blocked | K166: Amjad | L166: Amjad
A167: TC_EA_008 | B167: Account Type: not selected (EA5) | C167: Verify Account Type cannot be blank | D167: 1. Logged in as Manager 2. Account 185657 (Savings) exists and is associated with this Manager 3. Edit Account page is open | E167: 1. Enter the Account Number from Test data and click Submit 2. Change Account Type as shown in Test data 3. Click Submit | F167: Account Number: 185657 Account Type: (not selected) ◄ | G167: Medium | H167: E17: "Account Type must not be blank" (applies only if the dropdown allows an empty option) | I167: The system redirected the manager to a "This page isn't working" error page. The test could not be completed. | J167: Blocked | K167: Amjad | L167: Amjad
A168: TC_EA_009 | B168: Account Number: blank (EA1) | C168: Verify blank account number is rejected | D168: 1. Logged in as Manager 2. Account 185657 (Savings) exists and is associated with this Manager 3. Edit Account page is open | E168: 1. Leave Account Number empty 2. Click Submit | F168: Account Number: (empty) ◄ | G168: High | H168: E21: "Account Number must not be blank" | I168: E21: "Account Number must not be blank" | J168: Pass | K168: Amjad | L168: Amjad
A169: TC_EA_010 | B169: Account Number: non-numeric (EA2) | C169: Verify letters and symbols are rejected | D169: 1. Logged in as Manager 2. Account 185657 (Savings) exists and is associated with this Manager 3. Edit Account page is open | E169: 1. Enter the Attempt 1 value (other fields valid), click Submit 2. Repeat for each remaining attempt | F169: Account Number: [Attempt 1] ABC123 [Attempt 2] 12@#45 ◄ | G169: High | H169: E22: "Account Number must be numeric" (or E23 "Characters are not allowed in Account Number"; SRS overlaps) | I169: The system redirected the manager to a "This page isn't working" error page. The test could not be completed. | J169: Blocked | K169: Amjad | L169: Amjad
A170: TC_EA_011 | B170: Account Number: zero, negative, decimal | C170: Verify unusual numeric values are handled | D170: 1. Logged in as Manager 2. Account 185657 (Savings) exists and is associated with this Manager 3. Edit Account page is open | E170: 1. Enter the Attempt 1 value (other fields valid), click Submit 2. Repeat for each remaining attempt | F170: Account Number: [Attempt 1] 0 [Attempt 2] -5 [Attempt 3] 12.5 ◄ | G170: Low | H170: Each value is rejected with E22 or E24; no account is loaded | I170: The system redirected the manager to a "This page isn't working" error page. The test could not be completed. | J170: Blocked | K170: Amjad | L170: Amjad
A171: TC_EA_012 | B171: Account Number: does not exist (EA3) | C171: Verify an unknown account is rejected | D171: 1. Logged in as Manager 2. Account 185657 (Savings) exists and is associated with this Manager 3. Edit Account page is open | E171: 1. Enter the Account Number 2. Click Submit | F171: Account Number: 999999999999999 ◄ | G171: High | H171: E24: "Account Number not found" | I171: The system redirected the manager to a "This page isn't working" error page. The test could not be completed. | J171: Blocked | K171: Amjad | L171: Amjad
... A174: TC_EA_015 | B174: SQL injection in Account Number | C174: Verify basic SQL input is handled safely | D174: 1. Logged in as Manager 2. Account 185657 (Savings) exists and is associated with this Manager 3. Edit Account page is open | E174: 1. Enter the Account Number 2. Click Submit | F174: Account Number: 1 OR 1=1 ◄ | G174: Medium | H174: E22 is displayed; no account data is returned and no database error is shown | I174: The system redirected the manager to a "This page isn't working" error page. The test could not be completed. | J174: Blocked | K174: Amjad | L174: Amjad
B175: Delete account
A176: TC_DA_001 | B176: Delete account with zero balance | C176: Verify an account with zero balance can be deleted after confirmation | D176: 1. Logged in as Manager 2. An account with balance 0.00 exists and is associated with this Manager (not available, see Test Data Setup) 3. Delete Account page is open | E176: 1. Enter the Account Number 2. Click Delete 3. Confirm in the dialog | F176: Account Number: an account with balance 0.00 (not available, see Test Data Setup) ◄ | G176: High | H176: A confirmation dialog appears; after confirming, the account is deleted and a success message is displayed (see SRS gap: accounts with transactions) | I176: The test could not be executed: an account with a zero balance cannot be created (the minimum initial deposit is 500). | J176: Blocked | K176: Amjad | L176: Amjad
A177: TC_DA_002 | B177: Confirmation dialog before deletion | C177: Verify deletion is not executed until confirmed | D177: 1. Logged in as Manager 2. An account with balance 0.00 exists (not available, see Test Data Setup) | E177: 1. Enter the Account Number 2. Click Delete 3. Observe the dialog without confirming | F177: Account Number: an account with balance 0.00 (not available, see Test Data Setup) ◄ | G177: High | H177: A confirmation dialog is displayed; the account still exists until confirmed | I177: The test could not be executed: an account with a zero balance cannot be created (the minimum initial deposit is 500). | J177: Blocked | K177: Amjad | L177: Amjad
A178: TC_DA_003 | B178: Cancel the confirmation dialog | C178: Verify cancelling keeps the account | D178: 1. Logged in as Manager 2. An account with balance 0.00 exists (not available, see Test Data Setup) | E178: 1. Enter the Account Number 2. Click Delete 3. Click Cancel 4. Check the account in Balance Enquiry | F178: Account Number: an account with balance 0.00 (not available, see Test Data Setup) ◄ | G178: High | H178: The account is not deleted; Balance Enquiry still returns it | I178: The test could not be executed: an account with a zero balance cannot be created (the minimum initial deposit is 500). | J178: Blocked | K178: Amjad | L178: Amjad
A179: TC_DA_004 | B179: Deleted account cannot be retrieved | C179: Verify the deleted account no longer exists | D179: 1. Logged in as Manager 2. The account was deleted in TC_DA_001 | E179: 1. Open Balance Enquiry 2. Enter the deleted Account Number 3. Click Submit | F179: Account Number: an account with balance 0.00 (not available, see Test Data Setup) ◄ | G179: High | H179: E24: "Account Number not found" | I179: The system redirected the manager to a "This page isn't working" error page. | J179: Fail | K179: Amjad | L179: Amjad
A180: TC_DA_005 | B180: Delete an already deleted account | C180: Verify deleting the same account twice is handled | D180: 1. Logged in as Manager 2. The account was deleted in TC_DA_001 3. Delete Account page is open | E180: 1. Enter the Account Number from Test data 2. Click Delete | F180: Account Number: an account with balance 0.00 (not available, see Test Data Setup) ◄ | G180: Medium | H180: E24: "Account Number not found" | I180: The system redirected the manager to a "This page isn't working" error page. | J180: Fail | K180: Amjad | L180: Amjad
A181: TC_DA_006 | B181: Account Number: blank (DA1) | C181: Verify blank account number is rejected | D181: 1. Logged in as Manager 2. Delete Account page is open | E181: 1. Enter the Account Number from Test data 2. Click Delete | F181: Account Number: (empty) ◄ | G181: High | H181: E21: "Account Number must not be blank" | I181: E21: "Account Number must not be blank" | J181: Pass | K181: Amjad | L181: Amjad
A182: TC_DA_007 | B182: Account Number: non-numeric (DA2) | C182: Verify letters and symbols are rejected | D182: 1. Logged in as Manager 2. Delete Account page is open | E182: 1. Enter the Attempt 1 value (other fields valid), click Delete 2. Repeat for each remaining attempt | F182: Account Number: [Attempt 1] ABC123 [Attempt 2] 12@#45 ◄ | G182: High | H182: E22: "Account Number must be numeric" for each attempt | I182: E22: "Account Number must be numeric" for each attempt | J182: Pass | K182: Amjad | L182: Amjad
A183: TC_DA_008 | B183: Account Number: zero, negative, decimal | C183: Verify unusual numeric values are handled | D183: 1. Logged in as Manager 2. Delete Account page is open | E183: 1. Enter the Attempt 1 value (other fields valid), click Delete 2. Repeat for each remaining attempt | F183: Account Number: [Attempt 1] 0 [Attempt 2] -5 [Attempt 3] 12.5 ◄ | G183: Low | H183: Each value is rejected with E22 or E24; nothing is deleted | I183: Each value is rejected with E22 or E24; nothing is deleted | J183: Pass | K183: Amjad | L183: Amjad
A184: TC_DA_009 | B184: Account Number: does not exist (DA3) | C184: Verify an unknown account is rejected | D184: 1. Logged in as Manager 2. Delete Account page is open | E184: 1. Enter the Account Number from Test data 2. Click Delete | F184: Account Number: 999999999999999 ◄ | G184: High | H184: E24: "Account Number not found" | I184: E24: "Account Number not found" | J184: Pass | K184: Amjad | L184: Amjad
A185: TC_DA_010 | B185: Account of another Manager (DA4) | C185: Verify a Manager cannot delete another Manager's account | D185: 1. A second Manager account exists (Manager 2) and owns customer/account that are NOT associated with Manager 1 2. Logged in as Manager 1 3. Delete Account page is open | E185: 1. Enter the Account Number from Test data 2. Click Delete | F185: Account Number: an account of a Manager 2 customer (number not recorded) ◄ | G185: High | H185: E44 is displayed; the account is not deleted | I185: The system redirected the manager to a "This page isn't working" error page. | J185: Fail | K185: Amjad | L185: Amjad
A186: TC_DA_011 | B186: Account with positive balance (DA5) | C186: Verify an account with money cannot be deleted | D186: 1. Logged in as Manager 2. Account 185657 has a balance greater than 0 3. Delete Account page is open | E186: 1. Enter the Account Number 2. Click Delete 3. Confirm (if shown) | F186: Account Number: 185657 (balance 1000.00) ◄ | G186: High | H186: E53: "Account balance must be zero to delete"; the account remains | I186: The system redirected the manager to a "This page isn't working" error page. | J186: Fail | K186: Amjad | L186: Amjad
A187: TC_DA_012 | B187: Account with balance 0.01 (BVA) | C187: Verify the smallest positive balance blocks deletion | D187: 1. Logged in as Manager 2. An account with balance 0.01 exists (set up with deposits/withdrawals) 3. Delete Account page is open | E187: 1. Enter the Account Number from Test data 2. Click Delete | F187: Account Number: an account with balance 0.01 (not available, see Test Data Setup) ◄ | G187: Medium | H187: E53 is displayed; the account remains | I187: The system redirected the manager to a "This page isn't working" error page. The test could not be completed. | J187: Blocked | K187: Amjad | L187: Amjad
A188: TC_DA_013 | B188: Zero balance but existing transactions | C188: Verify the conflict between DA5 and RESTRICT DELETE (SRS 3.8.3) | D188: 1. Logged in as Manager 2. An account with transactions and balance 0.00 exists (not available, see Test Data Setup) 3. Delete Account page is open | E188: 1. Enter the Account Number from Test data 2. Click Delete | F188: Account Number: an account with balance 0.00 (not available, see Test Data Setup) ◄ | G188: High | H188: Document the actual behavior: DA5 allows deletion at zero balance, while 3.8.3 forbids deleting an account with transactions | I188: The system redirected the manager to a "This page isn't working" error page. The test could not be completed. | J188: Blocked | K188: Amjad | L188: Amjad
B189: Deposit
A190: TC_DP_001 | B190: Deposit with valid data | C190: Verify a deposit is processed | D190: 1. Logged in as Manager 2. Account 185657 exists with a known balance B and is associated with this Manager 3. Deposit page is open | E190: 1. Enter the values from Test data 2. Click Submit | F190: Account Number: 185657 Amount: 500 Description: Salary deposit | G190: High | H190: Deposit succeeds; the updated balance (B + 500) and a Transaction ID are displayed | I190: After clicking Submit, the system redirected the manager to a "This page isn't working" error page. | J190: Fail | K190: Amjad | L190: Amjad
A191: TC_DP_002 | B191: Balance after deposit | C191: Verify the balance in Balance Enquiry | D191: 1. Logged in as Manager 2. Account 185657 exists with a known balance B and is associated with this Manager 3. Deposit page is open | E191: 1. Complete TC_DP_001 2. Open Balance Enquiry and enter 185657 | F191: Account Number: 185657 Expected balance: B + 500 | G191: High | H191: Balance Enquiry shows B + 500 | I191: The system redirected the manager to a "This page isn't working" error page. The test could not be completed. | J191: Blocked | K191: Amjad | L191: Amjad
...

Sheet RTM
A1: Req ID | B1: SRS section | C1: Module | D1: Requirement | E1: Error | F1: Test cases | G1: No. of TCs | H1: Pass | I1: Fail | J1: Blocked | K1: Coverage status | L1: Linked defects
A2: L1 | B2: 3.3.1 | C2: Login | D2: User ID must not be blank | E2: Display error E1 | F2: TC_LG_002, TC_LG_004 | G2: =SUMPRODUCT(COUNTIF('Test Cases'!$A$2:$A$1513,{"TC_LG_002","TC_LG_004"})) -> 2 | H2: =SUMPRODUCT(COUNTIFS('Test Cases'!$A$2:$A$1513,{"TC_LG_002","TC_LG_004"},'Test Cases'!$J$2:$J$1513,"Pass")) -> 2 | I2: =SUMPRODUCT(COUNTIFS('Test Cases'!$A$2:$A$1513,{"TC_LG_002","TC_LG_004"},'Test Cases'!$J$2:$J$1513,"Fail")) -> 0 | J2: =SUMPRODUCT(COUNTIFS('Test Cases'!$A$2:$A$1513,{"TC_LG_002","TC_LG_004"},'Test Cases'!$J$2:$J$1513,"Blocked")) -> 0 | K2: =IF(G2=0,"Not covered",IF(I2>0,"Fail",IF(J2>0,"Blocked",IF(H2=G2,"Pass","Partially executed")))) -> Pass | L2: -
A3: L2 | B3: 3.3.1 | C3: Login | D3: Password must not be blank | E3: Display error E2 | F3: TC_LG_003 - TC_LG_004 | G3: =SUMPRODUCT(COUNTIF('Test Cases'!$A$2:$A$1513,{"TC_LG_003","TC_LG_004"})) -> 2 | H3: =SUMPRODUCT(COUNTIFS('Test Cases'!$A$2:$A$1513,{"TC_LG_003","TC_LG_004"},'Test Cases'!$J$2:$J$1513,"Pass")) -> 2 | I3: =SUMPRODUCT(COUNTIFS('Test Cases'!$A$2:$A$1513,{"TC_LG_003","TC_LG_004"},'Test Cases'!$J$2:$J$1513,"Fail")) -> 0 | J3: =SUMPRODUCT(COUNTIFS('Test Cases'!$A$2:$A$1513,{"TC_LG_003","TC_LG_004"},'Test Cases'!$J$2:$J$1513,"Blocked")) -> 0 | K3: =IF(G3=0,"Not covered",IF(I3>0,"Fail",IF(J3>0,"Blocked",IF(H3=G3,"Pass","Partially executed")))) -> Pass | L3: -
A4: L3 | B4: 3.3.1 | C4: Login | D4: User ID and Password combination must exist in database | E4: Display error E3 | F4: TC_LG_005 - TC_LG_006 | G4: =SUMPRODUCT(COUNTIF('Test Cases'!$A$2:$A$1513,{"TC_LG_005","TC_LG_006"})) -> 2 | H4: =SUMPRODUCT(COUNTIFS('Test Cases'!$A$2:$A$1513,{"TC_LG_005","TC_LG_006"},'Test Cases'!$J$2:$J$1513,"Pass")) -> 0 | I4: =SUMPRODUCT(COUNTIFS('Test Cases'!$A$2:$A$1513,{"TC_LG_005","TC_LG_006"},'Test Cases'!$J$2:$J$1513,"Fail")) -> 2 | J4: =SUMPRODUCT(COUNTIFS('Test Cases'!$A$2:$A$1513,{"TC_LG_005","TC_LG_006"},'Test Cases'!$J$2:$J$1513,"Blocked")) -> 0 | K4: =IF(G4=0,"Not covered",IF(I4>0,"Fail",IF(J4>0,"Blocked",IF(H4=G4,"Pass","Partially executed")))) -> Fail | L4: BUG_006
A5: L4 | B5: 3.3.1 | C5: Login | D5: Account must not be locked | E5: Display lockout message | F5: TC_LG_010 | G5: =SUMPRODUCT(COUNTIF('Test Cases'!$A$2:$A$1513,{"TC_LG_010"})) -> 1 | H5: =SUMPRODUCT(COUNTIFS('Test Cases'!$A$2:$A$1513,{"TC_LG_010"},'Test Cases'!$J$2:$J$1513,"Pass")) -> 0 | I5: =SUMPRODUCT(COUNTIFS('Test Cases'!$A$2:$A$1513,{"TC_LG_010"},'Test Cases'!$J$2:$J$1513,"Fail")) -> 1 | J5: =SUMPRODUCT(COUNTIFS('Test Cases'!$A$2:$A$1513,{"TC_LG_010"},'Test Cases'!$J$2:$J$1513,"Blocked")) -> 0 | K5: =IF(G5=0,"Not covered",IF(I5>0,"Fail",IF(J5>0,"Blocked",IF(H5=G5,"Pass","Partially executed")))) -> Fail | L5: BUG_003
A6: L5 | B6: 3.3.1 | C6: Login | D6: Maximum 3 failed attempts allowed | E6: Lock account after 3 failures | F6: TC_LG_009 | G6: =SUMPRODUCT(COUNTIF('Test Cases'!$A$2:$A$1513,{"TC_LG_009"})) -> 1 | H6: =SUMPRODUCT(COUNTIFS('Test Cases'!$A$2:$A$1513,{"TC_LG_009"},'Test Cases'!$J$2:$J$1513,"Pass")) -> 0 | I6: =SUMPRODUCT(COUNTIFS('Test Cases'!$A$2:$A$1513,{"TC_LG_009"},'Test Cases'!$J$2:$J$1513,"Fail")) -> 1 | J6: =SUMPRODUCT(COUNTIFS('Test Cases'!$A$2:$A$1513,{"TC_LG_009"},'Test Cases'!$J$2:$J$1513,"Blocked")) -> 0 | K6: =IF(G6=0,"Not covered",IF(I6>0,"Fail",IF(J6>0,"Blocked",IF(H6=G6,"Pass","Partially executed")))) -> Fail | L6: BUG_003
A7: NC1 | B7: 3.3.2 | C7: New Customer | D7: Customer Name: Must not be blank | E7: E4 | F7: TC_NC_006 | G7: =SUMPRODUCT(COUNTIF('Test Cases'!$A$2:$A$1513,{"TC_NC_006"})) -> 1 | H7: =SUMPRODUCT(COUNTIFS('Test Cases'!$A$2:$A$1513,{"TC_NC_006"},'Test Cases'!$J$2:$J$1513,"Pass")) -> 1 | I7: =SUMPRODUCT(COUNTIFS('Test Cases'!$A$2:$A$1513,{"TC_NC_006"},'Test Cases'!$J$2:$J$1513,"Fail")) -> 0 | J7: =SUMPRODUCT(COUNTIFS('Test Cases'!$A$2:$A$1513,{"TC_NC_006"},'Test Cases'!$J$2:$J$1513,"Blocked")) -> 0 | K7: =IF(G7=0,"Not covered",IF(I7>0,"Fail",IF(J7>0,"Blocked",IF(H7=G7,"Pass","Partially executed")))) -> Pass | L7: -
A8: NC2 | B8: 3.3.2 | C8: New Customer | D8: Customer Name: Must not contain numbers | E8: E48 | F8: TC_NC_007 | G8: =SUMPRODUCT(COUNTIF('Test Cases'!$A$2:$A$1513,{"TC_NC_007"})) -> 1 | H8: =SUMPRODUCT(COUNTIFS('Test Cases'!$A$2:$A$1513,{"TC_NC_007"},'Test Cases'!$J$2:$J$1513,"Pass")) -> 1 | I8: =SUMPRODUCT(COUNTIFS('Test Cases'!$A$2:$A$1513,{"TC_NC_007"},'Test Cases'!$J$2:$J$1513,"Fail")) -> 0 | J8: =SUMPRODUCT(COUNTIFS('Test Cases'!$A$2:$A$1513,{"TC_NC_007"},'Test Cases'!$J$2:$J$1513,"Blocked")) -> 0 | K8: =IF(G8=0,"Not covered",IF(I8>0,"Fail",IF(J8>0,"Blocked",IF(H8=G8,"Pass","Partially executed")))) -> Pass | L8: -
A9: NC3 | B9: 3.3.2 | C9: New Customer | D9: Customer Name: Must not contain special characters | E9: E46 | F9: TC_NC_008 | G9: =SUMPRODUCT(COUNTIF('Test Cases'!$A$2:$A$1513,{"TC_NC_008"})) -> 1 | H9: =SUMPRODUCT(COUNTIFS('Test Cases'!$A$2:$A$1513,{"TC_NC_008"},'Test Cases'!$J$2:$J$1513,"Pass")) -> 1 | I9: =SUMPRODUCT(COUNTIFS('Test Cases'!$A$2:$A$1513,{"TC_NC_008"},'Test Cases'!$J$2:$J$1513,"Fail")) -> 0 | J9: =SUMPRODUCT(COUNTIFS('Test Cases'!$A$2:$A$1513,{"TC_NC_008"},'Test Cases'!$J$2:$J$1513,"Blocked")) -> 0 | K9: =IF(G9=0,"Not covered",IF(I9>0,"Fail",IF(J9>0,"Blocked",IF(H9=G9,"Pass","Partially executed")))) -> Pass | L9: -
A10: NC4 | B10: 3.3.2 | C10: New Customer | D10: Customer Name: First character cannot be space | E10: E47 | F10: TC_NC_009 | G10: =SUMPRODUCT(COUNTIF('Test Cases'!$A$2:$A$1513,{"TC_NC_009"})) -> 1 | H10: =SUMPRODUCT(COUNTIFS('Test Cases'!$A$2:$A$1513,{"TC_NC_009"},'Test Cases'!$J$2:$J$1513,"Pass")) -> 1 | I10: =SUMPRODUCT(COUNTIFS('Test Cases'!$A$2:$A$1513,{"TC_NC_009"},'Test Cases'!$J$2:$J$1513,"Fail")) -> 0 | J10: =SUMPRODUCT(COUNTIFS('Test Cases'!$A$2:$A$1513,{"TC_NC_009"},'Test Cases'!$J$2:$J$1513,"Blocked")) -> 0 | K10: =IF(G10=0,"Not covered",IF(I10>0,"Fail",IF(J10>0,"Blocked",IF(H10=G10,"Pass","Partially executed")))) -> Pass | L10: -
A11: NC5 | B11: 3.3.2 | C11: New Customer | D11: Address: Must not be blank | E11: E5 | F11: TC_NC_020 | G11: =SUMPRODUCT(COUNTIF('Test Cases'!$A$2:$A$1513,{"TC_NC_020"})) -> 1 | H11: =SUMPRODUCT(COUNTIFS('Test Cases'!$A$2:$A$1513,{"TC_NC_020"},'Test Cases'!$J$2:$J$1513,"Pass")) -> 1 | I11: =SUMPRODUCT(COUNTIFS('Test Cases'!$A$2:$A$1513,{"TC_NC_020"},'Test Cases'!$J$2:$J$1513,"Fail")) -> 0 | J11: =SUMPRODUCT(COUNTIFS('Test Cases'!$A$2:$A$1513,{"TC_NC_020"},'Test Cases'!$J$2:$J$1513,"Blocked")) -> 0 | K11: =IF(G11=0,"Not covered",IF(I11>0,"Fail",IF(J11>0,"Blocked",IF(H11=G11,"Pass","Partially executed")))) -> Pass | L11: -
A12: NC6 | B12: 3.3.2 | C12: New Customer | D12: City: Must not be blank | E12: E6 | F12: TC_NC_024 | G12: =SUMPRODUCT(COUNTIF('Test Cases'!$A$2:$A$1513,{"TC_NC_024"})) -> 1 | H12: =SUMPRODUCT(COUNTIFS('Test Cases'!$A$2:$A$1513,{"TC_NC_024"},'Test Cases'!$J$2:$J$1513,"Pass")) -> 1 | I12: =SUMPRODUCT(COUNTIFS('Test Cases'!$A$2:$A$1513,{"TC_NC_024"},'Test Cases'!$J$2:$J$1513,"Fail")) -> 0 | J12: =SUMPRODUCT(COUNTIFS('Test Cases'!$A$2:$A$1513,{"TC_NC_024"},'Test Cases'!$J$2:$J$1513,"Blocked")) -> 0 | K12: =IF(G12=0,"Not covered",IF(I12>0,"Fail",IF(J12>0,"Blocked",IF(H12=G12,"Pass","Partially executed")))) -> Pass | L12: -
A13: NC7 | B13: 3.3.2 | C13: New Customer | D13: City: Must not contain numbers | E13: E48 | F13: TC_NC_025 | G13: =SUMPRODUCT(COUNTIF('Test Cases'!$A$2:$A$1513,{"TC_NC_025"})) -> 1 | H13: =SUMPRODUCT(COUNTIFS('Test Cases'!$A$2:$A$1513,{"TC_NC_025"},'Test Cases'!$J$2:$J$1513,"Pass")) -> 1 | I13: =SUMPRODUCT(COUNTIFS('Test Cases'!$A$2:$A$1513,{"TC_NC_025"},'Test Cases'!$J$2:$J$1513,"Fail")) -> 0 | J13: =SUMPRODUCT(COUNTIFS('Test Cases'!$A$2:$A$1513,{"TC_NC_025"},'Test Cases'!$J$2:$J$1513,"Blocked")) -> 0 | K13: =IF(G13=0,"Not covered",IF(I13>0,"Fail",IF(J13>0,"Blocked",IF(H13=G13,"Pass","Partially executed")))) -> Pass | L13: -
A14: NC8 | B14: 3.3.2 | C14: New Customer | D14: State: Must not be blank | E14: E7 | F14: TC_NC_027 | G14: =SUMPRODUCT(COUNTIF('Test Cases'!$A$2:$A$1513,{"TC_NC_027"})) -> 1 | H14: =SUMPRODUCT(COUNTIFS('Test Cases'!$A$2:$A$1513,{"TC_NC_027"},'Test Cases'!$J$2:$J$1513,"Pass")) -> 1 | I14: =SUMPRODUCT(COUNTIFS('Test Cases'!$A$2:$A$1513,{"TC_NC_027"},'Test Cases'!$J$2:$J$1513,"Fail")) -> 0 | J14: =SUMPRODUCT(COUNTIFS('Test Cases'!$A$2:$A$1513,{"TC_NC_027"},'Test Cases'!$J$2:$J$1513,"Blocked")) -> 0 | K14: =IF(G14=0,"Not covered",IF(I14>0,"Fail",IF(J14>0,"Blocked",IF(H14=G14,"Pass","Partially executed")))) -> Pass | L14: -
A15: NC9 | B15: 3.3.2 | C15: New Customer | D15: State: Must not contain numbers | E15: E48 | F15: TC_NC_028 | G15: =SUMPRODUCT(COUNTIF('Test Cases'!$A$2:$A$1513,{"TC_NC_028"})) -> 1 | H15: =SUMPRODUCT(COUNTIFS('Test Cases'!$A$2:$A$1513,{"TC_NC_028"},'Test Cases'!$J$2:$J$1513,"Pass")) -> 1 | I15: =SUMPRODUCT(COUNTIFS('Test Cases'!$A$2:$A$1513,{"TC_NC_028"},'Test Cases'!$J$2:$J$1513,"Fail")) -> 0 | J15: =SUMPRODUCT(COUNTIFS('Test Cases'!$A$2:$A$1513,{"TC_NC_028"},'Test Cases'!$J$2:$J$1513,"Blocked")) -> 0 | K15: =IF(G15=0,"Not covered",IF(I15>0,"Fail",IF(J15>0,"Blocked",IF(H15=G15,"Pass","Partially executed")))) -> Pass | L15: -
A16: NC10 | B16: 3.3.2 | C16: New Customer | D16: PIN Code: Must not be blank | E16: E8 | F16: TC_NC_030 | G16: =SUMPRODUCT(COUNTIF('Test Cases'!$A$2:$A$1513,{"TC_NC_030"})) -> 1 | H16: =SUMPRODUCT(COUNTIFS('Test Cases'!$A$2:$A$1513,{"TC_NC_030"},'Test Cases'!$J$2:$J$1513,"Pass")) -> 1 | I16: =SUMPRODUCT(COUNTIFS('Test Cases'!$A$2:$A$1513,{"TC_NC_030"},'Test Cases'!$J$2:$J$1513,"Fail")) -> 0 | J16: =SUMPRODUCT(COUNTIFS('Test Cases'!$A$2:$A$1513,{"TC_NC_030"},'Test Cases'!$J$2:$J$1513,"Blocked")) -> 0 | K16: =IF(G16=0,"Not covered",IF(I16>0,"Fail",IF(J16>0,"Blocked",IF(H16=G16,"Pass","Partially executed")))) -> Pass | L16: -
A17: NC11 | B17: 3.3.2 | C17: New Customer | D17: PIN Code: Must be numeric | E17: E9 | F17: TC_NC_031 | G17: =SUMPRODUCT(COUNTIF('Test Cases'!$A$2:$A$1513,{"TC_NC_031"})) -> 1 | H17: =SUMPRODUCT(COUNTIFS('Test Cases'!$A$2:$A$1513,{"TC_NC_031"},'Test Cases'!$J$2:$J$1513,"Pass")) -> 1 | I17: =SUMPRODUCT(COUNTIFS('Test Cases'!$A$2:$A$1513,{"TC_NC_031"},'Test Cases'!$J$2:$J$1513,"Fail")) -> 0 | J17: =SUMPRODUCT(COUNTIFS('Test Cases'!$A$2:$A$1513,{"TC_NC_031"},'Test Cases'!$J$2:$J$1513,"Blocked")) -> 0 | K17: =IF(G17=0,"Not covered",IF(I17>0,"Fail",IF(J17>0,"Blocked",IF(H17=G17,"Pass","Partially executed")))) -> Pass | L17: -
A18: NC12 | B18: 3.3.2 | C18: New Customer | D18: PIN Code: Must have exactly 6 digits | E18: E10 | F18: TC_NC_032 | G18: =SUMPRODUCT(COUNTIF('Test Cases'!$A$2:$A$1513,{"TC_NC_032"})) -> 1 | H18: =SUMPRODUCT(COUNTIFS('Test Cases'!$A$2:$A$1513,{"TC_NC_032"},'Test Cases'!$J$2:$J$1513,"Pass")) -> 1 | I18: =SUMPRODUCT(COUNTIFS('Test Cases'!$A$2:$A$1513,{"TC_NC_032"},'Test Cases'!$J$2:$J$1513,"Fail")) -> 0 | J18: =SUMPRODUCT(COUNTIFS('Test Cases'!$A$2:$A$1513,{"TC_NC_032"},'Test Cases'!$J$2:$J$1513,"Blocked")) -> 0 | K18: =IF(G18=0,"Not covered",IF(I18>0,"Fail",IF(J18>0,"Blocked",IF(H18=G18,"Pass","Partially executed")))) -> Pass | L18: -
A19: NC13 | B19: 3.3.2 | C19: New Customer | D19: Mobile Number: Must not be blank | E19: E11 | F19: TC_NC_034 | G19: =SUMPRODUCT(COUNTIF('Test Cases'!$A$2:$A$1513,{"TC_NC_034"})) -> 1 | H19: =SUMPRODUCT(COUNTIFS('Test Cases'!$A$2:$A$1513,{"TC_NC_034"},'Test Cases'!$J$2:$J$1513,"Pass")) -> 1 | I19: =SUMPRODUCT(COUNTIFS('Test Cases'!$A$2:$A$1513,{"TC_NC_034"},'Test Cases'!$J$2:$J$1513,"Fail")) -> 0 | J19: =SUMPRODUCT(COUNTIFS('Test Cases'!$A$2:$A$1513,{"TC_NC_034"},'Test Cases'!$J$2:$J$1513,"Blocked")) -> 0 | K19: =IF(G19=0,"Not covered",IF(I19>0,"Fail",IF(J19>0,"Blocked",IF(H19=G19,"Pass","Partially executed")))) -> Pass | L19: -
A20: NC14 | B20: 3.3.2 | C20: New Customer | D20: Mobile Number: Must be numeric | E20: E12 | F20: TC_NC_035 | G20: =SUMPRODUCT(COUNTIF('Test Cases'!$A$2:$A$1513,{"TC_NC_035"})) -> 1 | H20: =SUMPRODUCT(COUNTIFS('Test Cases'!$A$2:$A$1513,{"TC_NC_035"},'Test Cases'!$J$2:$J$1513,"Pass")) -> 1 | I20: =SUMPRODUCT(COUNTIFS('Test Cases'!$A$2:$A$1513,{"TC_NC_035"},'Test Cases'!$J$2:$J$1513,"Fail")) -> 0 | J20: =SUMPRODUCT(COUNTIFS('Test Cases'!$A$2:$A$1513,{"TC_NC_035"},'Test Cases'!$J$2:$J$1513,"Blocked")) -> 0 | K20: =IF(G20=0,"Not covered",IF(I20>0,"Fail",IF(J20>0,"Blocked",IF(H20=G20,"Pass","Partially executed")))) -> Pass | L20: -
A21: NC15 | B21: 3.3.2 | C21: New Customer | D21: Email: Must not be blank | E21: E13 | F21: TC_NC_038 | G21: =SUMPRODUCT(COUNTIF('Test Cases'!$A$2:$A$1513,{"TC_NC_038"})) -> 1 | H21: =SUMPRODUCT(COUNTIFS('Test Cases'!$A$2:$A$1513,{"TC_NC_038"},'Test Cases'!$J$2:$J$1513,"Pass")) -> 1 | I21: =SUMPRODUCT(COUNTIFS('Test Cases'!$A$2:$A$1513,{"TC_NC_038"},'Test Cases'!$J$2:$J$1513,"Fail")) -> 0 | J21: =SUMPRODUCT(COUNTIFS('Test Cases'!$A$2:$A$1513,{"TC_NC_038"},'Test Cases'!$J$2:$J$1513,"Blocked")) -> 0 | K21: =IF(G21=0,"Not covered",IF(I21>0,"Fail",IF(J21>0,"Blocked",IF(H21=G21,"Pass","Partially executed")))) -> Pass | L21: -
A22: NC16 | B22: 3.3.2 | C22: New Customer | D22: Email: Must be valid email format | E22: E14 | F22: TC_NC_039 | G22: =SUMPRODUCT(COUNTIF('Test Cases'!$A$2:$A$1513,{"TC_NC_039"})) -> 1 | H22: =SUMPRODUCT(COUNTIFS('Test Cases'!$A$2:$A$1513,{"TC_NC_039"},'Test Cases'!$J$2:$J$1513,"Pass")) -> 1 | I22: =SUMPRODUCT(COUNTIFS('Test Cases'!$A$2:$A$1513,{"TC_NC_039"},'Test Cases'!$J$2:$J$1513,"Fail")) -> 0 | J22: =SUMPRODUCT(COUNTIFS('Test Cases'!$A$2:$A$1513,{"TC_NC_039"},'Test Cases'!$J$2:$J$1513,"Blocked")) -> 0 | K22: =IF(G22=0,"Not covered",IF(I22>0,"Fail",IF(J22>0,"Blocked",IF(H22=G22,"Pass","Partially executed")))) -> Pass | L22: -
A23: NC17 | B23: 3.3.2 | C23: New Customer | D23: Email: Must be unique in system | E23: E49 | F23: TC_NC_040 | G23: =SUMPRODUCT(COUNTIF('Test Cases'!$A$2:$A$1513,{"TC_NC_040"})) -> 1 | H23: =SUMPRODUCT(COUNTIFS('Test Cases'!$A$2:$A$1513,{"TC_NC_040"},'Test Cases'!$J$2:$J$1513,"Pass")) -> 1 | I23: =SUMPRODUCT(COUNTIFS('Test Cases'!$A$2:$A$1513,{"TC_NC_040"},'Test Cases'!$J$2:$J$1513,"Fail")) -> 0 | J23: =SUMPRODUCT(COUNTIFS('Test Cases'!$A$2:$A$1513,{"TC_NC_040"},'Test Cases'!$J$2:$J$1513,"Blocked")) -> 0 | K23: =IF(G23=0,"Not covered",IF(I23>0,"Fail",IF(J23>0,"Blocked",IF(H23=G23,"Pass","Partially executed")))) -> Pass | L23: -
A24: NC18 | B24: 3.3.2 | C24: New Customer | D24: Date of Birth: Must not be blank | E24: E50 | F24: TC_NC_014 | G24: =SUMPRODUCT(COUNTIF('Test Cases'!$A$2:$A$1513,{"TC_NC_014"})) -> 1 | H24: =SUMPRODUCT(COUNTIFS('Test Cases'!$A$2:$A$1513,{"TC_NC_014"},'Test Cases'!$J$2:$J$1513,"Pass")) -> 1 | I24: =SUMPRODUCT(COUNTIFS('Test Cases'!$A$2:$A$1513,{"TC_NC_014"},'Test Cases'!$J$2:$J$1513,"Fail")) -> 0 | J24: =SUMPRODUCT(COUNTIFS('Test Cases'!$A$2:$A$1513,{"TC_NC_014"},'Test Cases'!$J$2:$J$1513,"Blocked")) -> 0 | K24: =IF(G24=0,"Not covered",IF(I24>0,"Fail",IF(J24>0,"Blocked",IF(H24=G24,"Pass","Partially executed")))) -> Pass | L24: -
A25: NC19 | B25: 3.3.2 | C25: New Customer | D25: Date of Birth: Age must be 18 or above | E25: Custom error | F25: TC_NC_017 | G25: =SUMPRODUCT(COUNTIF('Test Cases'!$A$2:$A$1513,{"TC_NC_017"})) -> 1 | H25: =SUMPRODUCT(COUNTIFS('Test Cases'!$A$2:$A$1513,{"TC_NC_017"},'Test Cases'!$J$2:$J$1513,"Pass")) -> 0 | I25: =SUMPRODUCT(COUNTIFS('Test Cases'!$A$2:$A$1513,{"TC_NC_017"},'Test Cases'!$J$2:$J$1513,"Fail")) -> 1 | J25: =SUMPRODUCT(COUNTIFS('Test Cases'!$A$2:$A$1513,{"TC_NC_017"},'Test Cases'!$J$2:$J$1513,"Blocked")) -> 0 | K25: =IF(G25=0,"Not covered",IF(I25>0,"Fail",IF(J25>0,"Blocked",IF(H25=G25,"Pass","Partially executed")))) -> Fail | L25: BUG_008
A26: NC20 | B26: 3.3.2 | C26: New Customer | D26: Gender: Must be selected | E26: Custom error | F26: TC_NC_012 | G26: =SUMPRODUCT(COUNTIF('Test Cases'!$A$2:$A$1513,{"TC_NC_012"})) -> 1 | H26: =SUMPRODUCT(COUNTIFS('Test Cases'!$A$2:$A$1513,{"TC_NC_012"},'Test Cases'!$J$2:$J$1513,"Pass")) -> 0 | I26: =SUMPRODUCT(COUNTIFS('Test Cases'!$A$2:$A$1513,{"TC_NC_012"},'Test Cases'!$J$2:$J$1513,"Fail")) -> 1 | J26: =SUMPRODUCT(COUNTIFS('Test Cases'!$A$2:$A$1513,{"TC_NC_012"},'Test Cases'!$J$2:$J$1513,"Blocked")) -> 0 | K26: =IF(G26=0,"Not covered",IF(I26>0,"Fail",IF(J26>0,"Blocked",IF(H26=G26,"Pass","Partially executed")))) -> Fail | L26: BUG_011
A27: EC1 | B27: 3.3.3 | C27: Edit Customer | D27: Customer ID must not be blank | E27: E15 | F27: TC_EC_004 | G27: =SUMPRODUCT(COUNTIF('Test Cases'!$A$2:$A$1513,{"TC_EC_004"})) -> 1 | H27: =SUMPRODUCT(COUNTIFS('Test Cases'!$A$2:$A$1513,{"TC_EC_004"},'Test Cases'!$J$2:$J$1513,"Pass")) -> 1 | I27: =SUMPRODUCT(COUNTIFS('Test Cases'!$A$2:$A$1513,{"TC_EC_004"},'Test Cases'!$J$2:$J$1513,"Fail")) -> 0 | J27: =SUMPRODUCT(COUNTIFS('Test Cases'!$A$2:$A$1513,{"TC_EC_004"},'Test Cases'!$J$2:$J$1513,"Blocked")) -> 0 | K27: =IF(G27=0,"Not covered",IF(I27>0,"Fail",IF(J27>0,"Blocked",IF(H27=G27,"Pass","Partially executed")))) -> Pass | L27: -
A28: EC2 | B28: 3.3.3 | C28: Edit Customer | D28: Customer ID must be numeric | E28: E16 | F28: TC_EC_005 | G28: =SUMPRODUCT(COUNTIF('Test Cases'!$A$2:$A$1513,{"TC_EC_005"})) -> 1 | H28: =SUMPRODUCT(COUNTIFS('Test Cases'!$A$2:$A$1513,{"TC_EC_005"},'Test Cases'!$J$2:$J$1513,"Pass")) -> 1 | I28: =SUMPRODUCT(COUNTIFS('Test Cases'!$A$2:$A$1513,{"TC_EC_005"},'Test Cases'!$J$2:$J$1513,"Fail")) -> 0 | J28: =SUMPRODUCT(COUNTIFS('Test Cases'!$A$2:$A$1513,{"TC_EC_005"},'Test Cases'!$J$2:$J$1513,"Blocked")) -> 0 | K28: =IF(G28=0,"Not covered",IF(I28>0,"Fail",IF(J28>0,"Blocked",IF(H28=G28,"Pass","Partially executed")))) -> Pass | L28: -
A29: EC3 | B29: 3.3.3 | C29: Edit Customer | D29: Customer ID must exist in database | E29: Custom error | F29: TC_EC_007 | G29: =SUMPRODUCT(COUNTIF('Test Cases'!$A$2:$A$1513,{"TC_EC_007"})) -> 1 | H29: =SUMPRODUCT(COUNTIFS('Test Cases'!$A$2:$A$1513,{"TC_EC_007"},'Test Cases'!$J$2:$J$1513,"Pass")) -> 1 | I29: =SUMPRODUCT(COUNTIFS('Test Cases'!$A$2:$A$1513,{"TC_EC_007"},'Test Cases'!$J$2:$J$1513,"Fail")) -> 0 | J29: =SUMPRODUCT(COUNTIFS('Test Cases'!$A$2:$A$1513,{"TC_EC_007"},'Test Cases'!$J$2:$J$1513,"Blocked")) -> 0 | K29: =IF(G29=0,"Not covered",IF(I29>0,"Fail",IF(J29>0,"Blocked",IF(H29=G29,"Pass","Partially executed")))) -> Pass | L29: -
A30: EC4 | B30: 3.3.3 | C30: Edit Customer | D30: Customer must be associated with current manager | E30: E44 | F30: TC_EC_008 | G30: =SUMPRODUCT(COUNTIF('Test Cases'!$A$2:$A$1513,{"TC_EC_008"})) -> 1 | H30: =SUMPRODUCT(COUNTIFS('Test Cases'!$A$2:$A$1513,{"TC_EC_008"},'Test Cases'!$J$2:$J$1513,"Pass")) -> 1 | I30: =SUMPRODUCT(COUNTIFS('Test Cases'!$A$2:$A$1513,{"TC_EC_008"},'Test Cases'!$J$2:$J$1513,"Fail")) -> 0 | J30: =SUMPRODUCT(COUNTIFS('Test Cases'!$A$2:$A$1513,{"TC_EC_008"},'Test Cases'!$J$2:$J$1513,"Blocked")) -> 0 | K30: =IF(G30=0,"Not covered",IF(I30>0,"Fail",IF(J30>0,"Blocked",IF(H30=G30,"Pass","Partially executed")))) -> Pass | L30: -
A31: EC5 | B31: 3.3.3 | C31: Edit Customer | D31: Email must be unique (if changed) | E31: E49 | F31: TC_EC_033 - TC_EC_036 | G31: =SUMPRODUCT(COUNTIF('Test Cases'!$A$2:$A$1513,{"TC_EC_033","TC_EC_034","TC_EC_035","TC_EC_036"})) -> 4 | H31: =SUMPRODUCT(COUNTIFS('Test Cases'!$A$2:$A$1513,{"TC_EC_033","TC_EC_034","TC_EC_035","TC_EC_036"},'Test Cases'!$J$2:$J$1513,"Pass")) -> 0 | I31: =SUMPRODUCT(COUNTIFS('Test Cases'!$A$2:$A$1513,{"TC_EC_033","TC_EC_034","TC_EC_035","TC_EC_036"},'Test Cases'!$J$2:$J$1513,"Fail")) -> 4 | J31: =SUMPRODUCT(COUNTIFS('Test Cases'!$A$2:$A$1513,{"TC_EC_033","TC_EC_034","TC_EC_035","TC_EC_036"},'Test Cases'!$J$2:$J$1513,"Blocked")) -> 0 | K31: =IF(G31=0,"Not covered",IF(I31>0,"Fail",IF(J31>0,"Blocked",IF(H31=G31,"Pass","Partially executed")))) -> Fail | L31: BUG_013, BUG_019
A32: EC6 | B32: 3.3.3 | C32: Edit Customer | D32: All field validations same as New Customer | E32: Various | F32: TC_EC_014 - TC_EC_015, TC_EC_017 - TC_EC_021, TC_EC_023 - TC_EC_025, TC_EC_027 - TC_EC_028, TC_EC_031 - TC_EC_032 | G32: =SUMPRODUCT(COUNTIF('Test Cases'!$A$2:$A$1513,{"TC_EC_014","TC_EC_015","TC_EC_017","TC_EC_018","TC_EC_019","TC_EC_020","TC_EC_021","TC_EC_023","TC_EC_024","TC_EC_025","TC_EC_027","TC_EC_028","TC_EC_031","TC_EC_032"})) -> 14 | H32: =SUMPRODUCT(COUNTIFS('Test Cases'!$A$2:$A$1513,{"TC_EC_014","TC_EC_015","TC_EC_017","TC_EC_018","TC_EC_019","TC_EC_020","TC_EC_021","TC_EC_023","TC_EC_024","TC_EC_025","TC_EC_027","TC_EC_028","TC_EC_031","TC_EC_032"},'Test Cases'!$J$2:$J$1513,"Pass")) -> 0 | I32: =SUMPRODUCT(COUNTIFS('Test Cases'!$A$2:$A$1513,{"TC_EC_014","TC_EC_015","TC_EC_017","TC_EC_018","TC_EC_019","TC_EC_020","TC_EC_021","TC_EC_023","TC_EC_024","TC_EC_025","TC_EC_027","TC_EC_028","TC_EC_031","TC_EC_032"},'Test Cases'!$J$2:$J$1513,"Fail")) -> 14 | J32: =SUMPRODUCT(COUNTIFS('Test Cases'!$A$2:$A$1513,{"TC_EC_014","TC_EC_015","TC_EC_017","TC_EC_018","TC_EC_019","TC_EC_020","TC_EC_021","TC_EC_023","TC_EC_024","TC_EC_025","TC_EC_027","TC_EC_028","TC_EC_031","TC_EC_032"},'Test Cases'!$J$2:$J$1513,"Blocked")) -> 0 | K32: =IF(G32=0,"Not covered",IF(I32>0,"Fail",IF(J32>0,"Blocked",IF(H32=G32,"Pass","Partially executed")))) -> Fail | L32: BUG_014, BUG_015, BUG_016, BUG_017, BUG_018
A33: DC1 | B33: 3.3.4 | C33: Delete Customer | D33: Customer ID must not be blank | E33: E15 | F33: TC_DC_006 | G33: =SUMPRODUCT(COUNTIF('Test Cases'!$A$2:$A$1513,{"TC_DC_006"})) -> 1 | H33: =SUMPRODUCT(COUNTIFS('Test Cases'!$A$2:$A$1513,{"TC_DC_006"},'Test Cases'!$J$2:$J$1513,"Pass")) -> 1 | I33: =SUMPRODUCT(COUNTIFS('Test Cases'!$A$2:$A$1513,{"TC_DC_006"},'Test Cases'!$J$2:$J$1513,"Fail")) -> 0 | J33: =SUMPRODUCT(COUNTIFS('Test Cases'!$A$2:$A$1513,{"TC_DC_006"},'Test Cases'!$J$2:$J$1513,"Blocked")) -> 0 | K33: =IF(G33=0,"Not covered",IF(I33>0,"Fail",IF(J33>0,"Blocked",IF(H33=G33,"Pass","Partially executed")))) -> Pass | L33: -
A34: DC2 | B34: 3.3.4 | C34: Delete Customer | D34: Customer ID must be numeric | E34: E16 | F34: TC_DC_007 | G34: =SUMPRODUCT(COUNTIF('Test Cases'!$A$2:$A$1513,{"TC_DC_007"})) -> 1 | H34: =SUMPRODUCT(COUNTIFS('Test Cases'!$A$2:$A$1513,{"TC_DC_007"},'Test Cases'!$J$2:$J$1513,"Pass")) -> 1 | I34: =SUMPRODUCT(COUNTIFS('Test Cases'!$A$2:$A$1513,{"TC_DC_007"},'Test Cases'!$J$2:$J$1513,"Fail")) -> 0 | J34: =SUMPRODUCT(COUNTIFS('Test Cases'!$A$2:$A$1513,{"TC_DC_007"},'Test Cases'!$J$2:$J$1513,"Blocked")) -> 0 | K34: =IF(G34=0,"Not covered",IF(I34>0,"Fail",IF(J34>0,"Blocked",IF(H34=G34,"Pass","Partially executed")))) -> Pass | L34: -
A35: DC3 | B35: 3.3.4 | C35: Delete Customer | D35: Customer ID must exist in database | E35: Custom error | F35: TC_DC_005, TC_DC_009 | G35: =SUMPRODUCT(COUNTIF('Test Cases'!$A$2:$A$1513,{"TC_DC_005","TC_DC_009"})) -> 2 | H35: =SUMPRODUCT(COUNTIFS('Test Cases'!$A$2:$A$1513,{"TC_DC_005","TC_DC_009"},'Test Cases'!$J$2:$J$1513,"Pass")) -> 2 | I35: =SUMPRODUCT(COUNTIFS('Test Cases'!$A$2:$A$1513,{"TC_DC_005","TC_DC_009"},'Test Cases'!$J$2:$J$1513,"Fail")) -> 0 | J35: =SUMPRODUCT(COUNTIFS('Test Cases'!$A$2:$A$1513,{"TC_DC_005","TC_DC_009"},'Test Cases'!$J$2:$J$1513,"Blocked")) -> 0 | K35: =IF(G35=0,"Not covered",IF(I35>0,"Fail",IF(J35>0,"Blocked",IF(H35=G35,"Pass","Partially executed")))) -> Pass | L35: -
A36: DC4 | B36: 3.3.4 | C36: Delete Customer | D36: Customer must not have any active accounts | E36: Custom error | F36: TC_DC_010 | G36: =SUMPRODUCT(COUNTIF('Test Cases'!$A$2:$A$1513,{"TC_DC_010"})) -> 1 | H36: =SUMPRODUCT(COUNTIFS('Test Cases'!$A$2:$A$1513,{"TC_DC_010"},'Test Cases'!$J$2:$J$1513,"Pass")) -> 1 | I36: =SUMPRODUCT(COUNTIFS('Test Cases'!$A$2:$A$1513,{"TC_DC_010"},'Test Cases'!$J$2:$J$1513,"Fail")) -> 0 | J36: =SUMPRODUCT(COUNTIFS('Test Cases'!$A$2:$A$1513,{"TC_DC_010"},'Test Cases'!$J$2:$J$1513,"Blocked")) -> 0 | K36: =IF(G36=0,"Not covered",IF(I36>0,"Fail",IF(J36>0,"Blocked",IF(H36=G36,"Pass","Partially executed")))) -> Pass | L36: -
A37: DC5 | B37: 3.3.4 | C37: Delete Customer | D37: Customer must be associated with current manager | E37: E44 | F37: TC_DC_011 | G37: =SUMPRODUCT(COUNTIF('Test Cases'!$A$2:$A$1513,{"TC_DC_011"})) -> 1 | H37: =SUMPRODUCT(COUNTIFS('Test Cases'!$A$2:$A$1513,{"TC_DC_011"},'Test Cases'!$J$2:$J$1513,"Pass")) -> 1 | I37: =SUMPRODUCT(COUNTIFS('Test Cases'!$A$2:$A$1513,{"TC_DC_011"},'Test Cases'!$J$2:$J$1513,"Fail")) -> 0 | J37: =SUMPRODUCT(COUNTIFS('Test Cases'!$A$2:$A$1513,{"TC_DC_011"},'Test Cases'!$J$2:$J$1513,"Blocked")) -> 0 | K37: =IF(G37=0,"Not covered",IF(I37>0,"Fail",IF(J37>0,"Blocked",IF(H37=G37,"Pass","Partially executed")))) -> Pass | L37: -
A38: NA1 | B38: 3.3.5 | C38: New Account | D38: Customer ID: Must not be blank | E38: E15 | F38: TC_NA_008 | G38: =SUMPRODUCT(COUNTIF('Test Cases'!$A$2:$A$1513,{"TC_NA_008"})) -> 1 | H38: =SUMPRODUCT(COUNTIFS('Test Cases'!$A$2:$A$1513,{"TC_NA_008"},'Test Cases'!$J$2:$J$1513,"Pass")) -> 1 | I38: =SUMPRODUCT(COUNTIFS('Test Cases'!$A$2:$A$1513,{"TC_NA_008"},'Test Cases'!$J$2:$J$1513,"Fail")) -> 0 | J38: =SUMPRODUCT(COUNTIFS('Test Cases'!$A$2:$A$1513,{"TC_NA_008"},'Test Cases'!$J$2:$J$1513,"Blocked")) -> 0 | K38: =IF(G38=0,"Not covered",IF(I38>0,"Fail",IF(J38>0,"Blocked",IF(H38=G38,"Pass","Partially executed")))) -> Pass | L38: -
A39: NA2 | B39: 3.3.5 | C39: New Account | D39: Customer ID: Must be numeric | E39: E16 | F39: TC_NA_009 | G39: =SUMPRODUCT(COUNTIF('Test Cases'!$A$2:$A$1513,{"TC_NA_009"})) -> 1 | H39: =SUMPRODUCT(COUNTIFS('Test Cases'!$A$2:$A$1513,{"TC_NA_009"},'Test Cases'!$J$2:$J$1513,"Pass")) -> 1 | I39: =SUMPRODUCT(COUNTIFS('Test Cases'!$A$2:$A$1513,{"TC_NA_009"},'Test Cases'!$J$2:$J$1513,"Fail")) -> 0 | J39: =SUMPRODUCT(COUNTIFS('Test Cases'!$A$2:$A$1513,{"TC_NA_009"},'Test Cases'!$J$2:$J$1513,"Blocked")) -> 0 | K39: =IF(G39=0,"Not covered",IF(I39>0,"Fail",IF(J39>0,"Blocked",IF(H39=G39,"Pass","Partially executed")))) -> Pass | L39: -
A40: NA3 | B40: 3.3.5 | C40: New Account | D40: Customer ID: Must exist in database | E40: Custom error | F40: TC_NA_011 | G40: =SUMPRODUCT(COUNTIF('Test Cases'!$A$2:$A$1513,{"TC_NA_011"})) -> 1 | H40: =SUMPRODUCT(COUNTIFS('Test Cases'!$A$2:$A$1513,{"TC_NA_011"},'Test Cases'!$J$2:$J$1513,"Pass")) -> 1 | I40: =SUMPRODUCT(COUNTIFS('Test Cases'!$A$2:$A$1513,{"TC_NA_011"},'Test Cases'!$J$2:$J$1513,"Fail")) -> 0 | J40: =SUMPRODUCT(COUNTIFS('Test Cases'!$A$2:$A$1513,{"TC_NA_011"},'Test Cases'!$J$2:$J$1513,"Blocked")) -> 0 | K40: =IF(G40=0,"Not covered",IF(I40>0,"Fail",IF(J40>0,"Blocked",IF(H40=G40,"Pass","Partially executed")))) -> Pass | L40: -
A41: NA4 | B41: 3.3.5 | C41: New Account | D41: Customer ID: Must be associated with manager | E41: E44 | F41: TC_NA_012 | G41: =SUMPRODUCT(COUNTIF('Test Cases'!$A$2:$A$1513,{"TC_NA_012"})) -> 1 | H41: =SUMPRODUCT(COUNTIFS('Test Cases'!$A$2:$A$1513,{"TC_NA_012"},'Test Cases'!$J$2:$J$1513,"Pass")) -> 0 | I41: =SUMPRODUCT(COUNTIFS('Test Cases'!$A$2:$A$1513,{"TC_NA_012"},'Test Cases'!$J$2:$J$1513,"Fail")) -> 0 | J41: =SUMPRODUCT(COUNTIFS('Test Cases'!$A$2:$A$1513,{"TC_NA_012"},'Test Cases'!$J$2:$J$1513,"Blocked")) -> 1 | K41: =IF(G41=0,"Not covered",IF(I41>0,"Fail",IF(J41>0,"Blocked",IF(H41=G41,"Pass","Partially executed")))) -> Blocked | L41: -
A42: NA5 | B42: 3.3.5 | C42: New Account | D42: Account Type: Must be selected | E42: E17 | F42: TC_NA_014 | G42: =SUMPRODUCT(COUNTIF('Test Cases'!$A$2:$A$1513,{"TC_NA_014"})) -> 1 | H42: =SUMPRODUCT(COUNTIFS('Test Cases'!$A$2:$A$1513,{"TC_NA_014"},'Test Cases'!$J$2:$J$1513,"Pass")) -> 0 | I42: =SUMPRODUCT(COUNTIFS('Test Cases'!$A$2:$A$1513,{"TC_NA_014"},'Test Cases'!$J$2:$J$1513,"Fail")) -> 0 | J42: =SUMPRODUCT(COUNTIFS('Test Cases'!$A$2:$A$1513,{"TC_NA_014"},'Test Cases'!$J$2:$J$1513,"Blocked")) -> 1 | K42: =IF(G42=0,"Not covered",IF(I42>0,"Fail",IF(J42>0,"Blocked",IF(H42=G42,"Pass","Partially executed")))) -> Blocked | L42: -
A43: NA6 | B43: 3.3.5 | C43: New Account | D43: Initial Deposit: Must not be blank | E43: E18 | F43: TC_NA_015 | G43: =SUMPRODUCT(COUNTIF('Test Cases'!$A$2:$A$1513,{"TC_NA_015"})) -> 1 | H43: =SUMPRODUCT(COUNTIFS('Test Cases'!$A$2:$A$1513,{"TC_NA_015"},'Test Cases'!$J$2:$J$1513,"Pass")) -> 1 | I43: =SUMPRODUCT(COUNTIFS('Test Cases'!$A$2:$A$1513,{"TC_NA_015"},'Test Cases'!$J$2:$J$1513,"Fail")) -> 0 | J43: =SUMPRODUCT(COUNTIFS('Test Cases'!$A$2:$A$1513,{"TC_NA_015"},'Test Cases'!$J$2:$J$1513,"Blocked")) -> 0 | K43: =IF(G43=0,"Not covered",IF(I43>0,"Fail",IF(J43>0,"Blocked",IF(H43=G43,"Pass","Partially executed")))) -> Pass | L43: -
A44: NA7 | B44: 3.3.5 | C44: New Account | D44: Initial Deposit: Must be numeric | E44: E19 | F44: TC_NA_016 | G44: =SUMPRODUCT(COUNTIF('Test Cases'!$A$2:$A$1513,{"TC_NA_016"})) -> 1 | H44: =SUMPRODUCT(COUNTIFS('Test Cases'!$A$2:$A$1513,{"TC_NA_016"},'Test Cases'!$J$2:$J$1513,"Pass")) -> 1 | I44: =SUMPRODUCT(COUNTIFS('Test Cases'!$A$2:$A$1513,{"TC_NA_016"},'Test Cases'!$J$2:$J$1513,"Fail")) -> 0 | J44: =SUMPRODUCT(COUNTIFS('Test Cases'!$A$2:$A$1513,{"TC_NA_016"},'Test Cases'!$J$2:$J$1513,"Blocked")) -> 0 | K44: =IF(G44=0,"Not covered",IF(I44>0,"Fail",IF(J44>0,"Blocked",IF(H44=G44,"Pass","Partially executed")))) -> Pass | L44: -
A45: NA8 | B45: 3.3.5 | C45: New Account | D45: Initial Deposit: Must be >= 500 | E45: E20 | F45: TC_NA_018 | G45: =SUMPRODUCT(COUNTIF('Test Cases'!$A$2:$A$1513,{"TC_NA_018"})) -> 1 | H45: =SUMPRODUCT(COUNTIFS('Test Cases'!$A$2:$A$1513,{"TC_NA_018"},'Test Cases'!$J$2:$J$1513,"Pass")) -> 1 | I45: =SUMPRODUCT(COUNTIFS('Test Cases'!$A$2:$A$1513,{"TC_NA_018"},'Test Cases'!$J$2:$J$1513,"Fail")) -> 0 | J45: =SUMPRODUCT(COUNTIFS('Test Cases'!$A$2:$A$1513,{"TC_NA_018"},'Test Cases'!$J$2:$J$1513,"Blocked")) -> 0 | K45: =IF(G45=0,"Not covered",IF(I45>0,"Fail",IF(J45>0,"Blocked",IF(H45=G45,"Pass","Partially executed")))) -> Pass | L45: -
A46: EA1 | B46: 3.3.6 | C46: Edit Account | D46: Account Number must not be blank | E46: E21 | F46: TC_EA_009 | G46: =SUMPRODUCT(COUNTIF('Test Cases'!$A$2:$A$1513,{"TC_EA_009"})) -> 1 | H46: =SUMPRODUCT(COUNTIFS('Test Cases'!$A$2:$A$1513,{"TC_EA_009"},'Test Cases'!$J$2:$J$1513,"Pass")) -> 1 | I46: =SUMPRODUCT(COUNTIFS('Test Cases'!$A$2:$A$1513,{"TC_EA_009"},'Test Cases'!$J$2:$J$1513,"Fail")) -> 0 | J46: =SUMPRODUCT(COUNTIFS('Test Cases'!$A$2:$A$1513,{"TC_EA_009"},'Test Cases'!$J$2:$J$1513,"Blocked")) -> 0 | K46: =IF(G46=0,"Not covered",IF(I46>0,"Fail",IF(J46>0,"Blocked",IF(H46=G46,"Pass","Partially executed")))) -> Pass | L46: -
A47: EA2 | B47: 3.3.6 | C47: Edit Account | D47: Account Number must be numeric | E47: E22 | F47: TC_EA_010 | G47: =SUMPRODUCT(COUNTIF('Test Cases'!$A$2:$A$1513,{"TC_EA_010"})) -> 1 | H47: =SUMPRODUCT(COUNTIFS('Test Cases'!$A$2:$A$1513,{"TC_EA_010"},'Test Cases'!$J$2:$J$1513,"Pass")) -> 0 | I47: =SUMPRODUCT(COUNTIFS('Test Cases'!$A$2:$A$1513,{"TC_EA_010"},'Test Cases'!$J$2:$J$1513,"Fail")) -> 0 | J47: =SUMPRODUCT(COUNTIFS('Test Cases'!$A$2:$A$1513,{"TC_EA_010"},'Test Cases'!$J$2:$J$1513,"Blocked")) -> 1 | K47: =IF(G47=0,"Not covered",IF(I47>0,"Fail",IF(J47>0,"Blocked",IF(H47=G47,"Pass","Partially executed")))) -> Blocked | L47: BUG_026
A48: EA3 | B48: 3.3.6 | C48: Edit Account | D48: Account Number must exist in database | E48: E24 | F48: TC_EA_012 | G48: =SUMPRODUCT(COUNTIF('Test Cases'!$A$2:$A$1513,{"TC_EA_012"})) -> 1 | H48: =SUMPRODUCT(COUNTIFS('Test Cases'!$A$2:$A$1513,{"TC_EA_012"},'Test Cases'!$J$2:$J$1513,"Pass")) -> 0 | I48: =SUMPRODUCT(COUNTIFS('Test Cases'!$A$2:$A$1513,{"TC_EA_012"},'Test Cases'!$J$2:$J$1513,"Fail")) -> 0 | J48: =SUMPRODUCT(COUNTIFS('Test Cases'!$A$2:$A$1513,{"TC_EA_012"},'Test Cases'!$J$2:$J$1513,"Blocked")) -> 1 | K48: =IF(G48=0,"Not covered",IF(I48>0,"Fail",IF(J48>0,"Blocked",IF(H48=G48,"Pass","Partially executed")))) -> Blocked | L48: BUG_026
A49: EA4 | B49: 3.3.6 | C49: Edit Account | D49: Account must be associated with manager | E49: E44 | F49: TC_EA_013 | G49: =SUMPRODUCT(COUNTIF('Test Cases'!$A$2:$A$1513,{"TC_EA_013"})) -> 1 | H49: =SUMPRODUCT(COUNTIFS('Test Cases'!$A$2:$A$1513,{"TC_EA_013"},'Test Cases'!$J$2:$J$1513,"Pass")) -> 0 | I49: =SUMPRODUCT(COUNTIFS('Test Cases'!$A$2:$A$1513,{"TC_EA_013"},'Test Cases'!$J$2:$J$1513,"Fail")) -> 0 | J49: =SUMPRODUCT(COUNTIFS('Test Cases'!$A$2:$A$1513,{"TC_EA_013"},'Test Cases'!$J$2:$J$1513,"Blocked")) -> 1 | K49: =IF(G49=0,"Not covered",IF(I49>0,"Fail",IF(J49>0,"Blocked",IF(H49=G49,"Pass","Partially executed")))) -> Blocked | L49: BUG_026
A50: EA5 | B50: 3.3.6 | C50: Edit Account | D50: Account Type must be selected | E50: E17 | F50: TC_EA_008 | G50: =SUMPRODUCT(COUNTIF('Test Cases'!$A$2:$A$1513,{"TC_EA_008"})) -> 1 | H50: =SUMPRODUCT(COUNTIFS('Test Cases'!$A$2:$A$1513,{"TC_EA_008"},'Test Cases'!$J$2:$J$1513,"Pass")) -> 0 | I50: =SUMPRODUCT(COUNTIFS('Test Cases'!$A$2:$A$1513,{"TC_EA_008"},'Test Cases'!$J$2:$J$1513,"Fail")) -> 0 | J50: =SUMPRODUCT(COUNTIFS('Test Cases'!$A$2:$A$1513,{"TC_EA_008"},'Test Cases'!$J$2:$J$1513,"Blocked")) -> 1 | K50: =IF(G50=0,"Not covered",IF(I50>0,"Fail",IF(J50>0,"Blocked",IF(H50=G50,"Pass","Partially executed")))) -> Blocked | L50: BUG_026
A51: DA1 | B51: 3.3.7 | C51: Delete Account | D51: Account Number must not be blank | E51: E21 | F51: TC_DA_006 | G51: =SUMPRODUCT(COUNTIF('Test Cases'!$A$2:$A$1513,{"TC_DA_006"})) -> 1 | H51: =SUMPRODUCT(COUNTIFS('Test Cases'!$A$2:$A$1513,{"TC_DA_006"},'Test Cases'!$J$2:$J$1513,"Pass")) -> 1 | I51: =SUMPRODUCT(COUNTIFS('Test Cases'!$A$2:$A$1513,{"TC_DA_006"},'Test Cases'!$J$2:$J$1513,"Fail")) -> 0 | J51: =SUMPRODUCT(COUNTIFS('Test Cases'!$A$2:$A$1513,{"TC_DA_006"},'Test Cases'!$J$2:$J$1513,"Blocked")) -> 0 | K51: =IF(G51=0,"Not covered",IF(I51>0,"Fail",IF(J51>0,"Blocked",IF(H51=G51,"Pass","Partially executed")))) -> Pass | L51: -
A52: DA2 | B52: 3.3.7 | C52: Delete Account | D52: Account Number must be numeric | E52: E22 | F52: TC_DA_007 | G52: =SUMPRODUCT(COUNTIF('Test Cases'!$A$2:$A$1513,{"TC_DA_007"})) -> 1 | H52: =SUMPRODUCT(COUNTIFS('Test Cases'!$A$2:$A$1513,{"TC_DA_007"},'Test Cases'!$J$2:$J$1513,"Pass")) -> 1 | I52: =SUMPRODUCT(COUNTIFS('Test Cases'!$A$2:$A$1513,{"TC_DA_007"},'Test Cases'!$J$2:$J$1513,"Fail")) -> 0 | J52: =SUMPRODUCT(COUNTIFS('Test Cases'!$A$2:$A$1513,{"TC_DA_007"},'Test Cases'!$J$2:$J$1513,"Blocked")) -> 0 | K52: =IF(G52=0,"Not covered",IF(I52>0,"Fail",IF(J52>0,"Blocked",IF(H52=G52,"Pass","Partially executed")))) -> Pass | L52: -
A53: DA3 | B53: 3.3.7 | C53: Delete Account | D53: Account Number must exist in database | E53: E24 | F53: TC_DA_009 | G53: =SUMPRODUCT(COUNTIF('Test Cases'!$A$2:$A$1513,{"TC_DA_009"})) -> 1 | H53: =SUMPRODUCT(COUNTIFS('Test Cases'!$A$2:$A$1513,{"TC_DA_009"},'Test Cases'!$J$2:$J$1513,"Pass")) -> 1 | I53: =SUMPRODUCT(COUNTIFS('Test Cases'!$A$2:$A$1513,{"TC_DA_009"},'Test Cases'!$J$2:$J$1513,"Fail")) -> 0 | J53: =SUMPRODUCT(COUNTIFS('Test Cases'!$A$2:$A$1513,{"TC_DA_009"},'Test Cases'!$J$2:$J$1513,"Blocked")) -> 0 | K53: =IF(G53=0,"Not covered",IF(I53>0,"Fail",IF(J53>0,"Blocked",IF(H53=G53,"Pass","Partially executed")))) -> Pass | L53: -
A54: DA4 | B54: 3.3.7 | C54: Delete Account | D54: Account must be associated with manager | E54: E44 | F54: TC_DA_010 | G54: =SUMPRODUCT(COUNTIF('Test Cases'!$A$2:$A$1513,{"TC_DA_010"})) -> 1 | H54: =SUMPRODUCT(COUNTIFS('Test Cases'!$A$2:$A$1513,{"TC_DA_010"},'Test Cases'!$J$2:$J$1513,"Pass")) -> 0 | I54: =SUMPRODUCT(COUNTIFS('Test Cases'!$A$2:$A$1513,{"TC_DA_010"},'Test Cases'!$J$2:$J$1513,"Fail")) -> 1 | J54: =SUMPRODUCT(COUNTIFS('Test Cases'!$A$2:$A$1513,{"TC_DA_010"},'Test Cases'!$J$2:$J$1513,"Blocked")) -> 0 | K54: =IF(G54=0,"Not covered",IF(I54>0,"Fail",IF(J54>0,"Blocked",IF(H54=G54,"Pass","Partially executed")))) -> Fail | L54: BUG_027
A55: DA5 | B55: 3.3.7 | C55: Delete Account | D55: Account balance must be zero | E55: Custom error | F55: TC_DA_011, TC_DA_013 | G55: =SUMPRODUCT(COUNTIF('Test Cases'!$A$2:$A$1513,{"TC_DA_011","TC_DA_013"})) -> 2 | H55: =SUMPRODUCT(COUNTIFS('Test Cases'!$A$2:$A$1513,{"TC_DA_011","TC_DA_013"},'Test Cases'!$J$2:$J$1513,"Pass")) -> 0 | I55: =SUMPRODUCT(COUNTIFS('Test Cases'!$A$2:$A$1513,{"TC_DA_011","TC_DA_013"},'Test Cases'!$J$2:$J$1513,"Fail")) -> 1 | J55: =SUMPRODUCT(COUNTIFS('Test Cases'!$A$2:$A$1513,{"TC_DA_011","TC_DA_013"},'Test Cases'!$J$2:$J$1513,"Blocked")) -> 1 | K55: =IF(G55=0,"Not covered",IF(I55>0,"Fail",IF(J55>0,"Blocked",IF(H55=G55,"Pass","Partially executed")))) -> Fail | L55: BUG_027
A56: DP1 | B56: 3.3.8 | C56: Deposit | D56: Account Number: Must not be blank | E56: E21 | F56: TC_DP_006 | G56: =SUMPRODUCT(COUNTIF('Test Cases'!$A$2:$A$1513,{"TC_DP_006"})) -> 1 | H56: =SUMPRODUCT(COUNTIFS('Test Cases'!$A$2:$A$1513,{"TC_DP_006"},'Test Cases'!$J$2:$J$1513,"Pass")) -> 1 | I56: =SUMPRODUCT(COUNTIFS('Test Cases'!$A$2:$A$1513,{"TC_DP_006"},'Test Cases'!$J$2:$J$1513,"Fail")) -> 0 | J56: =SUMPRODUCT(COUNTIFS('Test Cases'!$A$2:$A$1513,{"TC_DP_006"},'Test Cases'!$J$2:$J$1513,"Blocked")) -> 0 | K56: =IF(G56=0,"Not covered",IF(I56>0,"Fail",IF(J56>0,"Blocked",IF(H56=G56,"Pass","Partially executed")))) -> Pass | L56: -
A57: DP2 | B57: 3.3.8 | C57: Deposit | D57: Account Number: Must be numeric | E57: E22 | F57: TC_DP_007 | G57: =SUMPRODUCT(COUNTIF('Test Cases'!$A$2:$A$1513,{"TC_DP_007"})) -> 1 | H57: =SUMPRODUCT(COUNTIFS('Test Cases'!$A$2:$A$1513,{"TC_DP_007"},'Test Cases'!$J$2:$J$1513,"Pass")) -> 1 | I57: =SUMPRODUCT(COUNTIFS('Test Cases'!$A$2:$A$1513,{"TC_DP_007"},'Test Cases'!$J$2:$J$1513,"Fail")) -> 0 | J57: =SUMPRODUCT(COUNTIFS('Test Cases'!$A$2:$A$1513,{"TC_DP_007"},'Test Cases'!$J$2:$J$1513,"Blocked")) -> 0 | K57: =IF(G57=0,"Not covered",IF(I57>0,"Fail",IF(J57>0,"Blocked",IF(H57=G57,"Pass","Partially executed")))) -> Pass | L57: -
A58: DP3 | B58: 3.3.8 | C58: Deposit | D58: Account Number: Must exist in database | E58: E24 | F58: TC_DP_008 | G58: =SUMPRODUCT(COUNTIF('Test Cases'!$A$2:$A$1513,{"TC_DP_008"})) -> 1 | H58: =SUMPRODUCT(COUNTIFS('Test Cases'!$A$2:$A$1513,{"TC_DP_008"},'Test Cases'!$J$2:$J$1513,"Pass")) -> 0 | I58: =SUMPRODUCT(COUNTIFS('Test Cases'!$A$2:$A$1513,{"TC_DP_008"},'Test Cases'!$J$2:$J$1513,"Fail")) -> 0 | J58: =SUMPRODUCT(COUNTIFS('Test Cases'!$A$2:$A$1513,{"TC_DP_008"},'Test Cases'!$J$2:$J$1513,"Blocked")) -> 1 | K58: =IF(G58=0,"Not covered",IF(I58>0,"Fail",IF(J58>0,"Blocked",IF(H58=G58,"Pass","Partially executed")))) -> Blocked | L58: BUG_028
A59: DP4 | B59: 3.3.8 | C59: Deposit | D59: Account Number: Must be associated with manager | E59: E44 | F59: TC_DP_009 | G59: =SUMPRODUCT(COUNTIF('Test Cases'!$A$2:$A$1513,{"TC_DP_009"})) -> 1 | H59: =SUMPRODUCT(COUNTIFS('Test Cases'!$A$2:$A$1513,{"TC_DP_009"},'Test Cases'!$J$2:$J$1513,"Pass")) -> 0 | I59: =SUMPRODUCT(COUNTIFS('Test Cases'!$A$2:$A$1513,{"TC_DP_009"},'Test Cases'!$J$2:$J$1513,"Fail")) -> 0 | J59: =SUMPRODUCT(COUNTIFS('Test Cases'!$A$2:$A$1513,{"TC_DP_009"},'Test Cases'!$J$2:$J$1513,"Blocked")) -> 1 | K59: =IF(G59=0,"Not covered",IF(I59>0,"Fail",IF(J59>0,"Blocked",IF(H59=G59,"Pass","Partially executed")))) -> Blocked | L59: BUG_028
A60: DP5 | B60: 3.3.8 | C60: Deposit | D60: Amount: Must not be blank | E60: E39 | F60: TC_DP_010 | G60: =SUMPRODUCT(COUNTIF('Test Cases'!$A$2:$A$1513,{"TC_DP_010"})) -> 1 | H60: =SUMPRODUCT(COUNTIFS('Test Cases'!$A$2:$A$1513,{"TC_DP_010"},'Test Cases'!$J$2:$J$1513,"Pass")) -> 1 | I60: =SUMPRODUCT(COUNTIFS('Test Cases'!$A$2:$A$1513,{"TC_DP_010"},'Test Cases'!$J$2:$J$1513,"Fail")) -> 0 | J60: =SUMPRODUCT(COUNTIFS('Test Cases'!$A$2:$A$1513,{"TC_DP_010"},'Test Cases'!$J$2:$J$1513,"Blocked")) -> 0 | K60: =IF(G60=0,"Not covered",IF(I60>0,"Fail",IF(J60>0,"Blocked",IF(H60=G60,"Pass","Partially executed")))) -> Pass | L60: -
A61: DP6 | B61: 3.3.8 | C61: Deposit | D61: Amount: Must be numeric | E61: E40 | F61: TC_DP_011 | G61: =SUMPRODUCT(COUNTIF('Test Cases'!$A$2:$A$1513,{"TC_DP_011"})) -> 1 | H61: =SUMPRODUCT(COUNTIFS('Test Cases'!$A$2:$A$1513,{"TC_DP_011"},'Test Cases'!$J$2:$J$1513,"Pass")) -> 1 | I61: =SUMPRODUCT(COUNTIFS('Test Cases'!$A$2:$A$1513,{"TC_DP_011"},'Test Cases'!$J$2:$J$1513,"Fail")) -> 0 | J61: =SUMPRODUCT(COUNTIFS('Test Cases'!$A$2:$A$1513,{"TC_DP_011"},'Test Cases'!$J$2:$J$1513,"Blocked")) -> 0 | K61: =IF(G61=0,"Not covered",IF(I61>0,"Fail",IF(J61>0,"Blocked",IF(H61=G61,"Pass","Partially executed")))) -> Pass | L61: -
A62: DP7 | B62: 3.3.8 | C62: Deposit | D62: Amount: Must be greater than 0 | E62: Custom error | F62: TC_DP_012 | G62: =SUMPRODUCT(COUNTIF('Test Cases'!$A$2:$A$1513,{"TC_DP_012"})) -> 1 | H62: =SUMPRODUCT(COUNTIFS('Test Cases'!$A$2:$A$1513,{"TC_DP_012"},'Test Cases'!$J$2:$J$1513,"Pass")) -> 0 | I62: =SUMPRODUCT(COUNTIFS('Test Cases'!$A$2:$A$1513,{"TC_DP_012"},'Test Cases'!$J$2:$J$1513,"Fail")) -> 0 | J62: =SUMPRODUCT(COUNTIFS('Test Cases'!$A$2:$A$1513,{"TC_DP_012"},'Test Cases'!$J$2:$J$1513,"Blocked")) -> 1 | K62: =IF(G62=0,"Not covered",IF(I62>0,"Fail",IF(J62>0,"Blocked",IF(H62=G62,"Pass","Partially executed")))) -> Blocked | L62: BUG_028
A63: DP8 | B63: 3.3.8 | C63: Deposit | D63: Description: Must not be blank | E63: E41 | F63: TC_DP_018 | G63: =SUMPRODUCT(COUNTIF('Test Cases'!$A$2:$A$1513,{"TC_DP_018"})) -> 1 | H63: =SUMPRODUCT(COUNTIFS('Test Cases'!$A$2:$A$1513,{"TC_DP_018"},'Test Cases'!$J$2:$J$1513,"Pass")) -> 1 | I63: =SUMPRODUCT(COUNTIFS('Test Cases'!$A$2:$A$1513,{"TC_DP_018"},'Test Cases'!$J$2:$J$1513,"Fail")) -> 0 | J63: =SUMPRODUCT(COUNTIFS('Test Cases'!$A$2:$A$1513,{"TC_DP_018"},'Test Cases'!$J$2:$J$1513,"Blocked")) -> 0 | K63: =IF(G63=0,"Not covered",IF(I63>0,"Fail",IF(J63>0,"Blocked",IF(H63=G63,"Pass","Partially executed")))) -> Pass | L63: -
A64: WD1 | B64: 3.3.9 | C64: Withdrawal | D64: Account Number: Must not be blank | E64: E21 | F64: TC_WD_012 | G64: =SUMPRODUCT(COUNTIF('Test Cases'!$A$2:$A$1513,{"TC_WD_012"})) -> 1 | H64: =SUMPRODUCT(COUNTIFS('Test Cases'!$A$2:$A$1513,{"TC_WD_012"},'Test Cases'!$J$2:$J$1513,"Pass")) -> 1 | I64: =SUMPRODUCT(COUNTIFS('Test Cases'!$A$2:$A$1513,{"TC_WD_012"},'Test Cases'!$J$2:$J$1513,"Fail")) -> 0 | J64: =SUMPRODUCT(COUNTIFS('Test Cases'!$A$2:$A$1513,{"TC_WD_012"},'Test Cases'!$J$2:$J$1513,"Blocked")) -> 0 | K64: =IF(G64=0,"Not covered",IF(I64>0,"Fail",IF(J64>0,"Blocked",IF(H64=G64,"Pass","Partially executed")))) -> Pass | L64: -
A65: WD2 | B65: 3.3.9 | C65: Withdrawal | D65: Account Number: Must be numeric | E65: E22 | F65: TC_WD_013 | G65: =SUMPRODUCT(COUNTIF('Test Cases'!$A$2:$A$1513,{"TC_WD_013"})) -> 1 | H65: =SUMPRODUCT(COUNTIFS('Test Cases'!$A$2:$A$1513,{"TC_WD_013"},'Test Cases'!$J$2:$J$1513,"Pass")) -> 1 | I65: =SUMPRODUCT(COUNTIFS('Test Cases'!$A$2:$A$1513,{"TC_WD_013"},'Test Cases'!$J$2:$J$1513,"Fail")) -> 0 | J65: =SUMPRODUCT(COUNTIFS('Test Cases'!$A$2:$A$1513,{"TC_WD_013"},'Test Cases'!$J$2:$J$1513,"Blocked")) -> 0 | K65: =IF(G65=0,"Not covered",IF(I65>0,"Fail",IF(J65>0,"Blocked",IF(H65=G65,"Pass","Partially executed")))) -> Pass | L65: -
A66: WD3 | B66: 3.3.9 | C66: Withdrawal | D66: Account Number: Must exist in database | E66: E24 | F66: TC_WD_014 | G66: =SUMPRODUCT(COUNTIF('Test Cases'!$A$2:$A$1513,{"TC_WD_014"})) -> 1 | H66: =SUMPRODUCT(COUNTIFS('Test Cases'!$A$2:$A$1513,{"TC_WD_014"},'Test Cases'!$J$2:$J$1513,"Pass")) -> 1 | I66: =SUMPRODUCT(COUNTIFS('Test Cases'!$A$2:$A$1513,{"TC_WD_014"},'Test Cases'!$J$2:$J$1513,"Fail")) -> 0 | J66: =SUMPRODUCT(COUNTIFS('Test Cases'!$A$2:$A$1513,{"TC_WD_014"},'Test Cases'!$J$2:$J$1513,"Blocked")) -> 0 | K66: =IF(G66=0,"Not covered",IF(I66>0,"Fail",IF(J66>0,"Blocked",IF(H66=G66,"Pass","Partially executed")))) -> Pass | L66: -
A67: WD4 | B67: 3.3.9 | C67: Withdrawal | D67: Account Number: Must be associated with manager | E67: E44 | F67: TC_WD_015 | G67: =SUMPRODUCT(COUNTIF('Test Cases'!$A$2:$A$1513,{"TC_WD_015"})) -> 1 | H67: =SUMPRODUCT(COUNTIFS('Test Cases'!$A$2:$A$1513,{"TC_WD_015"},'Test Cases'!$J$2:$J$1513,"Pass")) -> 1 | I67: =SUMPRODUCT(COUNTIFS('Test Cases'!$A$2:$A$1513,{"TC_WD_015"},'Test Cases'!$J$2:$J$1513,"Fail")) -> 0 | J67: =SUMPRODUCT(COUNTIFS('Test Cases'!$A$2:$A$1513,{"TC_WD_015"},'Test Cases'!$J$2:$J$1513,"Blocked")) -> 0 | K67: =IF(G67=0,"Not covered",IF(I67>0,"Fail",IF(J67>0,"Blocked",IF(H67=G67,"Pass","Partially executed")))) -> Pass | L67: -
A68: WD5 | B68: 3.3.9 | C68: Withdrawal | D68: Amount: Must not be blank | E68: E39 | F68: TC_WD_016 | G68: =SUMPRODUCT(COUNTIF('Test Cases'!$A$2:$A$1513,{"TC_WD_016"})) -> 1 | H68: =SUMPRODUCT(COUNTIFS('Test Cases'!$A$2:$A$1513,{"TC_WD_016"},'Test Cases'!$J$2:$J$1513,"Pass")) -> 1 | I68: =SUMPRODUCT(COUNTIFS('Test Cases'!$A$2:$A$1513,{"TC_WD_016"},'Test Cases'!$J$2:$J$1513,"Fail")) -> 0 | J68: =SUMPRODUCT(COUNTIFS('Test Cases'!$A$2:$A$1513,{"TC_WD_016"},'Test Cases'!$J$2:$J$1513,"Blocked")) -> 0 | K68: =IF(G68=0,"Not covered",IF(I68>0,"Fail",IF(J68>0,"Blocked",IF(H68=G68,"Pass","Partially executed")))) -> Pass | L68: -
A69: WD6 | B69: 3.3.9 | C69: Withdrawal | D69: Amount: Must be numeric | E69: E40 | F69: TC_WD_017 | G69: =SUMPRODUCT(COUNTIF('Test Cases'!$A$2:$A$1513,{"TC_WD_017"})) -> 1 | H69: =SUMPRODUCT(COUNTIFS('Test Cases'!$A$2:$A$1513,{"TC_WD_017"},'Test Cases'!$J$2:$J$1513,"Pass")) -> 1 | I69: =SUMPRODUCT(COUNTIFS('Test Cases'!$A$2:$A$1513,{"TC_WD_017"},'Test Cases'!$J$2:$J$1513,"Fail")) -> 0 | J69: =SUMPRODUCT(COUNTIFS('Test Cases'!$A$2:$A$1513,{"TC_WD_017"},'Test Cases'!$J$2:$J$1513,"Blocked")) -> 0 | K69: =IF(G69=0,"Not covered",IF(I69>0,"Fail",IF(J69>0,"Blocked",IF(H69=G69,"Pass","Partially executed")))) -> Pass | L69: -
A70: WD7 | B70: 3.3.9 | C70: Withdrawal | D70: Amount: Must be greater than 0 | E70: Custom error | F70: TC_WD_018 | G70: =SUMPRODUCT(COUNTIF('Test Cases'!$A$2:$A$1513,{"TC_WD_018"})) -> 1 | H70: =SUMPRODUCT(COUNTIFS('Test Cases'!$A$2:$A$1513,{"TC_WD_018"},'Test Cases'!$J$2:$J$1513,"Pass")) -> 0 | I70: =SUMPRODUCT(COUNTIFS('Test Cases'!$A$2:$A$1513,{"TC_WD_018"},'Test Cases'!$J$2:$J$1513,"Fail")) -> 1 | J70: =SUMPRODUCT(COUNTIFS('Test Cases'!$A$2:$A$1513,{"TC_WD_018"},'Test Cases'!$J$2:$J$1513,"Blocked")) -> 0 | K70: =IF(G70=0,"Not covered",IF(I70>0,"Fail",IF(J70>0,"Blocked",IF(H70=G70,"Pass","Partially executed")))) -> Fail | L70: BUG_030
A71: WD8 | B71: 3.3.9 | C71: Withdrawal | D71: Amount: Must not exceed account balance | E71: E42 | F71: TC_WD_008 | G71: =SUMPRODUCT(COUNTIF('Test Cases'!$A$2:$A$1513,{"TC_WD_008"})) -> 1 | H71: =SUMPRODUCT(COUNTIFS('Test Cases'!$A$2:$A$1513,{"TC_WD_008"},'Test Cases'!$J$2:$J$1513,"Pass")) -> 0 | I71: =SUMPRODUCT(COUNTIFS('Test Cases'!$A$2:$A$1513,{"TC_WD_008"},'Test Cases'!$J$2:$J$1513,"Fail")) -> 1 | J71: =SUMPRODUCT(COUNTIFS('Test Cases'!$A$2:$A$1513,{"TC_WD_008"},'Test Cases'!$J$2:$J$1513,"Blocked")) -> 0 | K71: =IF(G71=0,"Not covered",IF(I71>0,"Fail",IF(J71>0,"Blocked",IF(H71=G71,"Pass","Partially executed")))) -> Fail | L71: BUG_030
A72: WD9 | B72: 3.3.9 | C72: Withdrawal | D72: Description: Must not be blank | E72: E41 | F72: TC_WD_023 | G72: =SUMPRODUCT(COUNTIF('Test Cases'!$A$2:$A$1513,{"TC_WD_023"})) -> 1 | H72: =SUMPRODUCT(COUNTIFS('Test Cases'!$A$2:$A$1513,{"TC_WD_023"},'Test Cases'!$J$2:$J$1513,"Pass")) -> 1 | I72: =SUMPRODUCT(COUNTIFS('Test Cases'!$A$2:$A$1513,{"TC_WD_023"},'Test Cases'!$J$2:$J$1513,"Fail")) -> 0 | J72: =SUMPRODUCT(COUNTIFS('Test Cases'!$A$2:$A$1513,{"TC_WD_023"},'Test Cases'!$J$2:$J$1513,"Blocked")) -> 0 | K72: =IF(G72=0,"Not covered",IF(I72>0,"Fail",IF(J72>0,"Blocked",IF(H72=G72,"Pass","Partially executed")))) -> Pass | L72: -
A73: FT1 | B73: 3.3.10 | C73: Fund Transfer | D73: Payer Account: Must not be blank | E73: E37 | F73: TC_FT_008 | G73: =SUMPRODUCT(COUNTIF('Test Cases'!$A$2:$A$1513,{"TC_FT_008"})) -> 1 | H73: =SUMPRODUCT(COUNTIFS('Test Cases'!$A$2:$A$1513,{"TC_FT_008"},'Test Cases'!$J$2:$J$1513,"Pass")) -> 1 | I73: =SUMPRODUCT(COUNTIFS('Test Cases'!$A$2:$A$1513,{"TC_FT_008"},'Test Cases'!$J$2:$J$1513,"Fail")) -> 0 | J73: =SUMPRODUCT(COUNTIFS('Test Cases'!$A$2:$A$1513,{"TC_FT_008"},'Test Cases'!$J$2:$J$1513,"Blocked")) -> 0 | K73: =IF(G73=0,"Not covered",IF(I73>0,"Fail",IF(J73>0,"Blocked",IF(H73=G73,"Pass","Partially executed")))) -> Pass | L73: -
A74: FT2 | B74: 3.3.10 | C74: Fund Transfer | D74: Payer Account: Must be numeric | E74: E22 | F74: TC_FT_011 | G74: =SUMPRODUCT(COUNTIF('Test Cases'!$A$2:$A$1513,{"TC_FT_011"})) -> 1 | H74: =SUMPRODUCT(COUNTIFS('Test Cases'!$A$2:$A$1513,{"TC_FT_011"},'Test Cases'!$J$2:$J$1513,"Pass")) -> 1 | I74: =SUMPRODUCT(COUNTIFS('Test Cases'!$A$2:$A$1513,{"TC_FT_011"},'Test Cases'!$J$2:$J$1513,"Fail")) -> 0 | J74: =SUMPRODUCT(COUNTIFS('Test Cases'!$A$2:$A$1513,{"TC_FT_011"},'Test Cases'!$J$2:$J$1513,"Blocked")) -> 0 | K74: =IF(G74=0,"Not covered",IF(I74>0,"Fail",IF(J74>0,"Blocked",IF(H74=G74,"Pass","Partially executed")))) -> Pass | L74: -
A75: FT3 | B75: 3.3.10 | C75: Fund Transfer | D75: Payer Account: Must exist in database | E75: E24 | F75: TC_FT_013 | G75: =SUMPRODUCT(COUNTIF('Test Cases'!$A$2:$A$1513,{"TC_FT_013"})) -> 1 | H75: =SUMPRODUCT(COUNTIFS('Test Cases'!$A$2:$A$1513,{"TC_FT_013"},'Test Cases'!$J$2:$J$1513,"Pass")) -> 1 | I75: =SUMPRODUCT(COUNTIFS('Test Cases'!$A$2:$A$1513,{"TC_FT_013"},'Test Cases'!$J$2:$J$1513,"Fail")) -> 0 | J75: =SUMPRODUCT(COUNTIFS('Test Cases'!$A$2:$A$1513,{"TC_FT_013"},'Test Cases'!$J$2:$J$1513,"Blocked")) -> 0 | K75: =IF(G75=0,"Not covered",IF(I75>0,"Fail",IF(J75>0,"Blocked",IF(H75=G75,"Pass","Partially executed")))) -> Pass | L75: -
A76: FT4 | B76: 3.3.10 | C76: Fund Transfer | D76: Payee Account: Must not be blank | E76: E38 | F76: TC_FT_009 | G76: =SUMPRODUCT(COUNTIF('Test Cases'!$A$2:$A$1513,{"TC_FT_009"})) -> 1 | H76: =SUMPRODUCT(COUNTIFS('Test Cases'!$A$2:$A$1513,{"TC_FT_009"},'Test Cases'!$J$2:$J$1513,"Pass")) -> 1 | I76: =SUMPRODUCT(COUNTIFS('Test Cases'!$A$2:$A$1513,{"TC_FT_009"},'Test Cases'!$J$2:$J$1513,"Fail")) -> 0 | J76: =SUMPRODUCT(COUNTIFS('Test Cases'!$A$2:$A$1513,{"TC_FT_009"},'Test Cases'!$J$2:$J$1513,"Blocked")) -> 0 | K76: =IF(G76=0,"Not covered",IF(I76>0,"Fail",IF(J76>0,"Blocked",IF(H76=G76,"Pass","Partially executed")))) -> Pass | L76: -
A77: FT5 | B77: 3.3.10 | C77: Fund Transfer | D77: Payee Account: Must be numeric | E77: E22 | F77: TC_FT_012 | G77: =SUMPRODUCT(COUNTIF('Test Cases'!$A$2:$A$1513,{"TC_FT_012"})) -> 1 | H77: =SUMPRODUCT(COUNTIFS('Test Cases'!$A$2:$A$1513,{"TC_FT_012"},'Test Cases'!$J$2:$J$1513,"Pass")) -> 1 | I77: =SUMPRODUCT(COUNTIFS('Test Cases'!$A$2:$A$1513,{"TC_FT_012"},'Test Cases'!$J$2:$J$1513,"Fail")) -> 0 | J77: =SUMPRODUCT(COUNTIFS('Test Cases'!$A$2:$A$1513,{"TC_FT_012"},'Test Cases'!$J$2:$J$1513,"Blocked")) -> 0 | K77: =IF(G77=0,"Not covered",IF(I77>0,"Fail",IF(J77>0,"Blocked",IF(H77=G77,"Pass","Partially executed")))) -> Pass | L77: -
A78: FT6 | B78: 3.3.10 | C78: Fund Transfer | D78: Payee Account: Must exist in database | E78: E24 | F78: TC_FT_014 | G78: =SUMPRODUCT(COUNTIF('Test Cases'!$A$2:$A$1513,{"TC_FT_014"})) -> 1 | H78: =SUMPRODUCT(COUNTIFS('Test Cases'!$A$2:$A$1513,{"TC_FT_014"},'Test Cases'!$J$2:$J$1513,"Pass")) -> 1 | I78: =SUMPRODUCT(COUNTIFS('Test Cases'!$A$2:$A$1513,{"TC_FT_014"},'Test Cases'!$J$2:$J$1513,"Fail")) -> 0 | J78: =SUMPRODUCT(COUNTIFS('Test Cases'!$A$2:$A$1513,{"TC_FT_014"},'Test Cases'!$J$2:$J$1513,"Blocked")) -> 0 | K78: =IF(G78=0,"Not covered",IF(I78>0,"Fail",IF(J78>0,"Blocked",IF(H78=G78,"Pass","Partially executed")))) -> Pass | L78: -
A79: FT7 | B79: 3.3.10 | C79: Fund Transfer | D79: Both Accounts: Must not be the same | E79: E43 | F79: TC_FT_007 | G79: =SUMPRODUCT(COUNTIF('Test Cases'!$A$2:$A$1513,{"TC_FT_007"})) -> 1 | H79: =SUMPRODUCT(COUNTIFS('Test Cases'!$A$2:$A$1513,{"TC_FT_007"},'Test Cases'!$J$2:$J$1513,"Pass")) -> 1 | I79: =SUMPRODUCT(COUNTIFS('Test Cases'!$A$2:$A$1513,{"TC_FT_007"},'Test Cases'!$J$2:$J$1513,"Fail")) -> 0 | J79: =SUMPRODUCT(COUNTIFS('Test Cases'!$A$2:$A$1513,{"TC_FT_007"},'Test Cases'!$J$2:$J$1513,"Blocked")) -> 0 | K79: =IF(G79=0,"Not covered",IF(I79>0,"Fail",IF(J79>0,"Blocked",IF(H79=G79,"Pass","Partially executed")))) -> Pass | L79: -
A80: FT8 | B80: 3.3.10 | C80: Fund Transfer | D80: Amount: Must not be blank | E80: E39 | F80: TC_FT_015 | G80: =SUMPRODUCT(COUNTIF('Test Cases'!$A$2:$A$1513,{"TC_FT_015"})) -> 1 | H80: =SUMPRODUCT(COUNTIFS('Test Cases'!$A$2:$A$1513,{"TC_FT_015"},'Test Cases'!$J$2:$J$1513,"Pass")) -> 1 | I80: =SUMPRODUCT(COUNTIFS('Test Cases'!$A$2:$A$1513,{"TC_FT_015"},'Test Cases'!$J$2:$J$1513,"Fail")) -> 0 | J80: =SUMPRODUCT(COUNTIFS('Test Cases'!$A$2:$A$1513,{"TC_FT_015"},'Test Cases'!$J$2:$J$1513,"Blocked")) -> 0 | K80: =IF(G80=0,"Not covered",IF(I80>0,"Fail",IF(J80>0,"Blocked",IF(H80=G80,"Pass","Partially executed")))) -> Pass | L80: -
A81: FT9 | B81: 3.3.10 | C81: Fund Transfer | D81: Amount: Must be numeric | E81: E40 | F81: TC_FT_016 | G81: =SUMPRODUCT(COUNTIF('Test Cases'!$A$2:$A$1513,{"TC_FT_016"})) -> 1 | H81: =SUMPRODUCT(COUNTIFS('Test Cases'!$A$2:$A$1513,{"TC_FT_016"},'Test Cases'!$J$2:$J$1513,"Pass")) -> 1 | I81: =SUMPRODUCT(COUNTIFS('Test Cases'!$A$2:$A$1513,{"TC_FT_016"},'Test Cases'!$J$2:$J$1513,"Fail")) -> 0 | J81: =SUMPRODUCT(COUNTIFS('Test Cases'!$A$2:$A$1513,{"TC_FT_016"},'Test Cases'!$J$2:$J$1513,"Blocked")) -> 0 | K81: =IF(G81=0,"Not covered",IF(I81>0,"Fail",IF(J81>0,"Blocked",IF(H81=G81,"Pass","Partially executed")))) -> Pass | L81: -
A82: FT10 | B82: 3.3.10 | C82: Fund Transfer | D82: Amount: Must not exceed payer balance | E82: E42 | F82: TC_FT_006 | G82: =SUMPRODUCT(COUNTIF('Test Cases'!$A$2:$A$1513,{"TC_FT_006"})) -> 1 | H82: =SUMPRODUCT(COUNTIFS('Test Cases'!$A$2:$A$1513,{"TC_FT_006"},'Test Cases'!$J$2:$J$1513,"Pass")) -> 0 | I82: =SUMPRODUCT(COUNTIFS('Test Cases'!$A$2:$A$1513,{"TC_FT_006"},'Test Cases'!$J$2:$J$1513,"Fail")) -> 1 | J82: =SUMPRODUCT(COUNTIFS('Test Cases'!$A$2:$A$1513,{"TC_FT_006"},'Test Cases'!$J$2:$J$1513,"Blocked")) -> 0 | K82: =IF(G82=0,"Not covered",IF(I82>0,"Fail",IF(J82>0,"Blocked",IF(H82=G82,"Pass","Partially executed")))) -> Fail | L82: BUG_032
A83: FT11 | B83: 3.3.10 | C83: Fund Transfer | D83: Description: Must not be blank | E83: E41 | F83: TC_FT_021 | G83: =SUMPRODUCT(COUNTIF('Test Cases'!$A$2:$A$1513,{"TC_FT_021"})) -> 1 | H83: =SUMPRODUCT(COUNTIFS('Test Cases'!$A$2:$A$1513,{"TC_FT_021"},'Test Cases'!$J$2:$J$1513,"Pass")) -> 1 | I83: =SUMPRODUCT(COUNTIFS('Test Cases'!$A$2:$A$1513,{"TC_FT_021"},'Test Cases'!$J$2:$J$1513,"Fail")) -> 0 | J83: =SUMPRODUCT(COUNTIFS('Test Cases'!$A$2:$A$1513,{"TC_FT_021"},'Test Cases'!$J$2:$J$1513,"Blocked")) -> 0 | K83: =IF(G83=0,"Not covered",IF(I83>0,"Fail",IF(J83>0,"Blocked",IF(H83=G83,"Pass","Partially executed")))) -> Pass | L83: -
A84: FT12 | B84: 3.3.10 | C84: Fund Transfer | D84: Payer Account: Must belong to user (Customer role) | E84: E44 | F84: - | G84: 0 | H84: 0 | I84: 0 | J84: 0 | K84: =IF(G84=0,"Not covered",IF(I84>0,"Fail",IF(J84>0,"Blocked",IF(H84=G84,"Pass","Partially executed")))) -> Not covered | L84: -
A85: FT13 | B85: 3.3.10 | C85: Fund Transfer | D85: Payer Account: Must be associated with manager (Manager role) | E85: E44 | F85: TC_FT_023 | G85: =SUMPRODUCT(COUNTIF('Test Cases'!$A$2:$A$1513,{"TC_FT_023"})) -> 1 | H85: =SUMPRODUCT(COUNTIFS('Test Cases'!$A$2:$A$1513,{"TC_FT_023"},'Test Cases'!$J$2:$J$1513,"Pass")) -> 1 | I85: =SUMPRODUCT(COUNTIFS('Test Cases'!$A$2:$A$1513,{"TC_FT_023"},'Test Cases'!$J$2:$J$1513,"Fail")) -> 0 | J85: =SUMPRODUCT(COUNTIFS('Test Cases'!$A$2:$A$1513,{"TC_FT_023"},'Test Cases'!$J$2:$J$1513,"Blocked")) -> 0 | K85: =IF(G85=0,"Not covered",IF(I85>0,"Fail",IF(J85>0,"Blocked",IF(H85=G85,"Pass","Partially executed")))) -> Pass | L85: -
A86: BE1 | B86: 3.3.11 | C86: Balance Enquiry | D86: Account Number must not be blank | E86: E21 | F86: TC_BE_008 | G86: =SUMPRODUCT(COUNTIF('Test Cases'!$A$2:$A$1513,{"TC_BE_008"})) -> 1 | H86: =SUMPRODUCT(COUNTIFS('Test Cases'!$A$2:$A$1513,{"TC_BE_008"},'Test Cases'!$J$2:$J$1513,"Pass")) -> 1 | I86: =SUMPRODUCT(COUNTIFS('Test Cases'!$A$2:$A$1513,{"TC_BE_008"},'Test Cases'!$J$2:$J$1513,"Fail")) -> 0 | J86: =SUMPRODUCT(COUNTIFS('Test Cases'!$A$2:$A$1513,{"TC_BE_008"},'Test Cases'!$J$2:$J$1513,"Blocked")) -> 0 | K86: =IF(G86=0,"Not covered",IF(I86>0,"Fail",IF(J86>0,"Blocked",IF(H86=G86,"Pass","Partially executed")))) -> Pass | L86: -
A87: BE2 | B87: 3.3.11 | C87: Balance Enquiry | D87: Account Number must be numeric | E87: E22 | F87: TC_BE_009 | G87: =SUMPRODUCT(COUNTIF('Test Cases'!$A$2:$A$1513,{"TC_BE_009"})) -> 1 | H87: =SUMPRODUCT(COUNTIFS('Test Cases'!$A$2:$A$1513,{"TC_BE_009"},'Test Cases'!$J$2:$J$1513,"Pass")) -> 1 | I87: =SUMPRODUCT(COUNTIFS('Test Cases'!$A$2:$A$1513,{"TC_BE_009"},'Test Cases'!$J$2:$J$1513,"Fail")) -> 0 | J87: =SUMPRODUCT(COUNTIFS('Test Cases'!$A$2:$A$1513,{"TC_BE_009"},'Test Cases'!$J$2:$J$1513,"Blocked")) -> 0 | K87: =IF(G87=0,"Not covered",IF(I87>0,"Fail",IF(J87>0,"Blocked",IF(H87=G87,"Pass","Partially executed")))) -> Pass | L87: -
A88: BE3 | B88: 3.3.11 | C88: Balance Enquiry | D88: Account Number must exist in database | E88: E24 | F88: TC_BE_011 | G88: =SUMPRODUCT(COUNTIF('Test Cases'!$A$2:$A$1513,{"TC_BE_011"})) -> 1 | H88: =SUMPRODUCT(COUNTIFS('Test Cases'!$A$2:$A$1513,{"TC_BE_011"},'Test Cases'!$J$2:$J$1513,"Pass")) -> 0 | I88: =SUMPRODUCT(COUNTIFS('Test Cases'!$A$2:$A$1513,{"TC_BE_011"},'Test Cases'!$J$2:$J$1513,"Fail")) -> 1 | J88: =SUMPRODUCT(COUNTIFS('Test Cases'!$A$2:$A$1513,{"TC_BE_011"},'Test Cases'!$J$2:$J$1513,"Blocked")) -> 0 | K88: =IF(G88=0,"Not covered",IF(I88>0,"Fail",IF(J88>0,"Blocked",IF(H88=G88,"Pass","Partially executed")))) -> Fail | L88: BUG_034
A89: BE4 | B89: 3.3.11 | C89: Balance Enquiry | D89: Account must belong to user (Customer role) | E89: E44 | F89: TC_BE_013 | G89: =SUMPRODUCT(COUNTIF('Test Cases'!$A$2:$A$1513,{"TC_BE_013"})) -> 1 | H89: =SUMPRODUCT(COUNTIFS('Test Cases'!$A$2:$A$1513,{"TC_BE_013"},'Test Cases'!$J$2:$J$1513,"Pass")) -> 1 | I89: =SUMPRODUCT(COUNTIFS('Test Cases'!$A$2:$A$1513,{"TC_BE_013"},'Test Cases'!$J$2:$J$1513,"Fail")) -> 0 | J89: =SUMPRODUCT(COUNTIFS('Test Cases'!$A$2:$A$1513,{"TC_BE_013"},'Test Cases'!$J$2:$J$1513,"Blocked")) -> 0 | K89: =IF(G89=0,"Not covered",IF(I89>0,"Fail",IF(J89>0,"Blocked",IF(H89=G89,"Pass","Partially executed")))) -> Pass | L89: -
A90: BE5 | B90: 3.3.11 | C90: Balance Enquiry | D90: Account must be associated with manager (Manager role) | E90: E44 | F90: TC_BE_012 | G90: =SUMPRODUCT(COUNTIF('Test Cases'!$A$2:$A$1513,{"TC_BE_012"})) -> 1 | H90: =SUMPRODUCT(COUNTIFS('Test Cases'!$A$2:$A$1513,{"TC_BE_012"},'Test Cases'!$J$2:$J$1513,"Pass")) -> 1 | I90: =SUMPRODUCT(COUNTIFS('Test Cases'!$A$2:$A$1513,{"TC_BE_012"},'Test Cases'!$J$2:$J$1513,"Fail")) -> 0 | J90: =SUMPRODUCT(COUNTIFS('Test Cases'!$A$2:$A$1513,{"TC_BE_012"},'Test Cases'!$J$2:$J$1513,"Blocked")) -> 0 | K90: =IF(G90=0,"Not covered",IF(I90>0,"Fail",IF(J90>0,"Blocked",IF(H90=G90,"Pass","Partially executed")))) -> Pass | L90: -
A91: MS1 | B91: 3.3.12 | C91: Mini Statement | D91: Account Number must not be blank | E91: E21 | F91: TC_MS_015 | G91: =SUMPRODUCT(COUNTIF('Test Cases'!$A$2:$A$1513,{"TC_MS_015"})) -> 1 | H91: =SUMPRODUCT(COUNTIFS('Test Cases'!$A$2:$A$1513,{"TC_MS_015"},'Test Cases'!$J$2:$J$1513,"Pass")) -> 1 | I91: =SUMPRODUCT(COUNTIFS('Test Cases'!$A$2:$A$1513,{"TC_MS_015"},'Test Cases'!$J$2:$J$1513,"Fail")) -> 0 | J91: =SUMPRODUCT(COUNTIFS('Test Cases'!$A$2:$A$1513,{"TC_MS_015"},'Test Cases'!$J$2:$J$1513,"Blocked")) -> 0 | K91: =IF(G91=0,"Not covered",IF(I91>0,"Fail",IF(J91>0,"Blocked",IF(H91=G91,"Pass","Partially executed")))) -> Pass | L91: -
A92: MS2 | B92: 3.3.12 | C92: Mini Statement | D92: Account Number must be numeric | E92: E22 | F92: TC_MS_016 | G92: =SUMPRODUCT(COUNTIF('Test Cases'!$A$2:$A$1513,{"TC_MS_016"})) -> 1 | H92: =SUMPRODUCT(COUNTIFS('Test Cases'!$A$2:$A$1513,{"TC_MS_016"},'Test Cases'!$J$2:$J$1513,"Pass")) -> 1 | I92: =SUMPRODUCT(COUNTIFS('Test Cases'!$A$2:$A$1513,{"TC_MS_016"},'Test Cases'!$J$2:$J$1513,"Fail")) -> 0 | J92: =SUMPRODUCT(COUNTIFS('Test Cases'!$A$2:$A$1513,{"TC_MS_016"},'Test Cases'!$J$2:$J$1513,"Blocked")) -> 0 | K92: =IF(G92=0,"Not covered",IF(I92>0,"Fail",IF(J92>0,"Blocked",IF(H92=G92,"Pass","Partially executed")))) -> Pass | L92: -
A93: MS3 | B93: 3.3.12 | C93: Mini Statement | D93: Account Number must exist in database | E93: E24 | F93: TC_MS_018 | G93: =SUMPRODUCT(COUNTIF('Test Cases'!$A$2:$A$1513,{"TC_MS_018"})) -> 1 | H93: =SUMPRODUCT(COUNTIFS('Test Cases'!$A$2:$A$1513,{"TC_MS_018"},'Test Cases'!$J$2:$J$1513,"Pass")) -> 1 | I93: =SUMPRODUCT(COUNTIFS('Test Cases'!$A$2:$A$1513,{"TC_MS_018"},'Test Cases'!$J$2:$J$1513,"Fail")) -> 0 | J93: =SUMPRODUCT(COUNTIFS('Test Cases'!$A$2:$A$1513,{"TC_MS_018"},'Test Cases'!$J$2:$J$1513,"Blocked")) -> 0 | K93: =IF(G93=0,"Not covered",IF(I93>0,"Fail",IF(J93>0,"Blocked",IF(H93=G93,"Pass","Partially executed")))) -> Pass | L93: -
A94: MS4 | B94: 3.3.12 | C94: Mini Statement | D94: Account must have transactions | E94: Custom error | F94: TC_MS_005 | G94: =SUMPRODUCT(COUNTIF('Test Cases'!$A$2:$A$1513,{"TC_MS_005"})) -> 1 | H94: =SUMPRODUCT(COUNTIFS('Test Cases'!$A$2:$A$1513,{"TC_MS_005"},'Test Cases'!$J$2:$J$1513,"Pass")) -> 0 | I94: =SUMPRODUCT(COUNTIFS('Test Cases'!$A$2:$A$1513,{"TC_MS_005"},'Test Cases'!$J$2:$J$1513,"Fail")) -> 1 | J94: =SUMPRODUCT(COUNTIFS('Test Cases'!$A$2:$A$1513,{"TC_MS_005"},'Test Cases'!$J$2:$J$1513,"Blocked")) -> 0 | K94: =IF(G94=0,"Not covered",IF(I94>0,"Fail",IF(J94>0,"Blocked",IF(H94=G94,"Pass","Partially executed")))) -> Fail | L94: BUG_035
A95: MS5 | B95: 3.3.12 | C95: Mini Statement | D95: Account must belong to user (Customer role) | E95: E44 | F95: - | G95: 0 | H95: 0 | I95: 0 | J95: 0 | K95: =IF(G95=0,"Not covered",IF(I95>0,"Fail",IF(J95>0,"Blocked",IF(H95=G95,"Pass","Partially executed")))) -> Not covered | L95: -
A96: MS6 | B96: 3.3.12 | C96: Mini Statement | D96: Account must be associated with manager (Manager role) | E96: E44 | F96: TC_MS_019 | G96: =SUMPRODUCT(COUNTIF('Test Cases'!$A$2:$A$1513,{"TC_MS_019"})) -> 1 | H96: =SUMPRODUCT(COUNTIFS('Test Cases'!$A$2:$A$1513,{"TC_MS_019"},'Test Cases'!$J$2:$J$1513,"Pass")) -> 1 | I96: =SUMPRODUCT(COUNTIFS('Test Cases'!$A$2:$A$1513,{"TC_MS_019"},'Test Cases'!$J$2:$J$1513,"Fail")) -> 0 | J96: =SUMPRODUCT(COUNTIFS('Test Cases'!$A$2:$A$1513,{"TC_MS_019"},'Test Cases'!$J$2:$J$1513,"Blocked")) -> 0 | K96: =IF(G96=0,"Not covered",IF(I96>0,"Fail",IF(J96>0,"Blocked",IF(H96=G96,"Pass","Partially executed")))) -> Pass | L96: -
A97: CS1 | B97: 3.3.13 | C97: Customized Statement | D97: Account Number: Must not be blank | E97: E21 | F97: TC_CS_021 | G97: =SUMPRODUCT(COUNTIF('Test Cases'!$A$2:$A$1513,{"TC_CS_021"})) -> 1 | H97: =SUMPRODUCT(COUNTIFS('Test Cases'!$A$2:$A$1513,{"TC_CS_021"},'Test Cases'!$J$2:$J$1513,"Pass")) -> 0 | I97: =SUMPRODUCT(COUNTIFS('Test Cases'!$A$2:$A$1513,{"TC_CS_021"},'Test Cases'!$J$2:$J$1513,"Fail")) -> 1 | J97: =SUMPRODUCT(COUNTIFS('Test Cases'!$A$2:$A$1513,{"TC_CS_021"},'Test Cases'!$J$2:$J$1513,"Blocked")) -> 0 | K97: =IF(G97=0,"Not covered",IF(I97>0,"Fail",IF(J97>0,"Blocked",IF(H97=G97,"Pass","Partially executed")))) -> Fail | L97: BUG_039
A98: CS2 | B98: 3.3.13 | C98: Customized Statement | D98: Account Number: Must be numeric | E98: E22 | F98: TC_CS_022 | G98: =SUMPRODUCT(COUNTIF('Test Cases'!$A$2:$A$1513,{"TC_CS_022"})) -> 1 | H98: =SUMPRODUCT(COUNTIFS('Test Cases'!$A$2:$A$1513,{"TC_CS_022"},'Test Cases'!$J$2:$J$1513,"Pass")) -> 0 | I98: =SUMPRODUCT(COUNTIFS('Test Cases'!$A$2:$A$1513,{"TC_CS_022"},'Test Cases'!$J$2:$J$1513,"Fail")) -> 1 | J98: =SUMPRODUCT(COUNTIFS('Test Cases'!$A$2:$A$1513,{"TC_CS_022"},'Test Cases'!$J$2:$J$1513,"Blocked")) -> 0 | K98: =IF(G98=0,"Not covered",IF(I98>0,"Fail",IF(J98>0,"Blocked",IF(H98=G98,"Pass","Partially executed")))) -> Fail | L98: BUG_039
A99: CS3 | B99: 3.3.13 | C99: Customized Statement | D99: Account Number: Must exist in database | E99: E24 | F99: TC_CS_023 | G99: =SUMPRODUCT(COUNTIF('Test Cases'!$A$2:$A$1513,{"TC_CS_023"})) -> 1 | H99: =SUMPRODUCT(COUNTIFS('Test Cases'!$A$2:$A$1513,{"TC_CS_023"},'Test Cases'!$J$2:$J$1513,"Pass")) -> 0 | I99: =SUMPRODUCT(COUNTIFS('Test Cases'!$A$2:$A$1513,{"TC_CS_023"},'Test Cases'!$J$2:$J$1513,"Fail")) -> 1 | J99: =SUMPRODUCT(COUNTIFS('Test Cases'!$A$2:$A$1513,{"TC_CS_023"},'Test Cases'!$J$2:$J$1513,"Blocked")) -> 0 | K99: =IF(G99=0,"Not covered",IF(I99>0,"Fail",IF(J99>0,"Blocked",IF(H99=G99,"Pass","Partially executed")))) -> Fail | L99: BUG_039
A100: CS4 | B100: 3.3.13 | C100: Customized Statement | D100: From Date: Must not be blank | E100: E30 | F100: TC_CS_006 | G100: =SUMPRODUCT(COUNTIF('Test Cases'!$A$2:$A$1513,{"TC_CS_006"})) -> 1 | H100: =SUMPRODUCT(COUNTIFS('Test Cases'!$A$2:$A$1513,{"TC_CS_006"},'Test Cases'!$J$2:$J$1513,"Pass")) -> 0 | I100: =SUMPRODUCT(COUNTIFS('Test Cases'!$A$2:$A$1513,{"TC_CS_006"},'Test Cases'!$J$2:$J$1513,"Fail")) -> 1 | J100: =SUMPRODUCT(COUNTIFS('Test Cases'!$A$2:$A$1513,{"TC_CS_006"},'Test Cases'!$J$2:$J$1513,"Blocked")) -> 0 | K100: =IF(G100=0,"Not covered",IF(I100>0,"Fail",IF(J100>0,"Blocked",IF(H100=G100,"Pass","Partially executed")))) -> Fail | L100: BUG_037
...

Sheet Bug Report
A1: ID | B1: Summary | C1: Description | D1: Pre-Condition | E1: Environment | F1: Steps | G1: Expected result | H1: Actual result | I1: Severity | J1: Priority | K1: Status | L1: Test data | M1: Created by | N1: Assigned to | O1: Test case ID | P1: Comment
A2: BUG_001 | B2: [Login] SQL injection input bypasses the login (authentication bypass) | C2: The login form accepts a SQL injection string as the User ID and logs the user in. Authentication can be bypassed, which exposes every Manager function. | D2: Login page is open | E2: Google Chrome; Guru99 Bank demo site (V2) - https://demo.guru99.com/V4/ | F2: 1. Open the Login page 2. Enter ' OR '1'='1 in User ID 3. Enter x in Password 4. Click Login | G2: The login is rejected (E3) and no access is granted. | H2: The system accepted the login and redirected the manager to the dashboard. | I2: Critical | J2: High | K2: Open | L2: User ID: ' OR '1'='1 Password: x | M2: Amjad | N2: Development Team | O2: TC_LG_014 (1 failed, 0 blocked)
A3: BUG_002 | B3: [Login] Protected pages can be opened directly without logging in | C3: A protected internal page opens when its URL is entered directly while the user is not logged in. Access control (SRS RBAC) is not enforced. | D3: User is not logged in; the URL of an internal page is known | E3: Google Chrome; Guru99 Bank demo site (V2) - https://demo.guru99.com/V4/ | F3: 1. Make sure no user is logged in 2. Enter the URL of an internal page directly in the browser | G3: The user is redirected to the Login page. | H3: The system opened the protected page directly without any authentication. | I3: Critical | J3: High | K3: Open | L3: Direct URL of an internal page | M3: Amjad | N3: Development Team | O3: TC_LG_018 (1 failed, 0 blocked)
A4: BUG_003 | B4: [Login] Account is not locked after 3 failed login attempts | C4: The SRS requires the account to be locked after 3 consecutive failed logins (L4, L5). The system never locks the account, so passwords can be guessed without limit. | D4: Manager account is active and not locked | E4: Google Chrome; Guru99 Bank demo site (V2) - https://demo.guru99.com/V4/ | F4: 1. Open the Login page 2. Enter a valid User ID and a wrong Password, click Login 3. Repeat step 2 two more times 4. Log in with the valid User ID and Password | G4: Attempts 1 and 2 show E3. After attempt 3 the account is locked and E55 is displayed; the valid login is rejected. | H4: The account was not locked after the 3 failed attempts and the lockout message (E55) was not displayed. | I4: High | J4: High | K4: Open | L4: User ID: mngr668217 Password: wrongpas (3 attempts), then rUqyzUv | M4: Amjad | N4: Development Team | O4: TC_LG_009 - TC_LG_010 (2 failed, 0 blocked) | P4: Test data of TC_LG_009 was corrected to use a wrong password. Please re-run TC_LG_009 and TC_LG_010 to confirm the result.
A5: BUG_004 | B5: [Login] Session is not terminated after Logout (Back button returns to the dashboard) | C5: After logging out, the browser Back button returns to the protected dashboard. The session stays usable after Logout. | D5: User is logged in | E5: Google Chrome; Guru99 Bank demo site (V2) - https://demo.guru99.com/V4/ | F5: 1. Log in as a Manager 2. Click Logout 3. Click the browser Back button | G5: The user cannot return to a protected page without logging in again. | H5: The session was not terminated: after pressing the Back button, the manager could return to the dashboard. | I5: High | J5: High | K5: Open | L5: User ID: mngr668217 | M5: Amjad | N5: Development Team | O5: TC_LG_017 (1 failed, 0 blocked)
A6: BUG_005 | B6: [Login] User ID and Password are not case-sensitive | C6: The login accepts the User ID in uppercase and the Password with different letter casing. The SRS requires case-sensitive credentials; this weakens password security. | D6: Manager account "mngr668217" exists with password "rUqyzUv" | E6: Google Chrome; Guru99 Bank demo site (V2) - https://demo.guru99.com/V4/ | F6: 1. Open the Login page 2. Enter the User ID MNGR668217 and the correct Password, click Login 3. Enter the correct User ID and the Password RUQYZUV, click Login | G6: E3 is displayed and the login is rejected in both cases. | H6: The system accepted both logins and redirected the manager to the dashboard. | I6: Medium | J6: Medium | K6: Open | L6: User ID: MNGR668217 / Password: rUqyzUv User ID: mngr668217 / Password: RUQYZUV | M6: Amjad | N6: Development Team | O6: TC_LG_007 - TC_LG_008 (2 failed, 0 blocked)
A7: BUG_006 | B7: [Login] Invalid login shows "User is not valid" instead of the SRS message E3 | C7: For an unknown User ID or a wrong Password the system shows an alert with different wording from the message defined in the SRS. | D7: Login page is open | E7: Google Chrome; Guru99 Bank demo site (V2) - https://demo.guru99.com/V4/ | F7: 1. Open the Login page 2. Enter an invalid User ID or a wrong Password 3. Click Login | G7: E3: "User ID and Password do not match" is displayed. | H7: The alert "User is not valid" was displayed and the login was rejected. | I7: Low | J7: Low | K7: Open | L7: User ID: ghost999 / Password: Pass@123 User ID: mngr668217 / Password: wrongpas | M7: Amjad | N7: Development Team | O7: TC_LG_005 - TC_LG_006 (2 failed, 0 blocked)
A8: BUG_007 | B8: [Login] Login field length limits differ from the SRS (User ID max 10, Password unlimited) | C8: The SRS defines a maximum of 30 characters for User ID and Password. The User ID field accepts only 10 characters and the Password field has no limit. | D8: Login page is open | E8: Google Chrome; Guru99 Bank demo site (V2) - https://demo.guru99.com/V4/ | F8: 1. Open the Login page 2. Type 30 characters in User ID and in Password 3. Type 31 characters in both fields | G8: 30 characters are accepted; the 31st character is rejected or truncated. | H8: The User ID field accepts a maximum of 10 characters and the Password field has no maximum length limit. | I8: Medium | J8: Low | K8: Open | L8: 30-character and 31-character strings | M8: Amjad | N8: Development Team | O8: TC_LG_013 (1 failed, 0 blocked)
A9: BUG_008 | B9: [New Customer] No age validation: customers under 18 and a future date of birth are accepted | C9: The SRS requires customers to be 18 or older (E58). The form creates customers aged 17, aged 10 and with a future date of birth without any error. | D9: Logged in as a Manager New Customer page is open | E9: Google Chrome; Guru99 Bank demo site (V2) - https://demo.guru99.com/V4/ | F9: 1. Open New Customer 2. Fill all fields with valid data and set the Date of Birth to a date that makes the customer under 18 (or a future date) 3. Click Submit | G9: E58 "Age must be 18 years or above" is displayed and no customer is created. | H9: Customers were created with Customer IDs 52817 (17 years old), 27595 (10 years old) and 69229 (future date of birth); no error message was displayed. | I9: High | J9: High | K9: Open | L9: Date of Birth: (Execution date - 18 years) + 1 day; Execution date - 10 years; tomorrow | M9: Amjad | N9: Development Team | O9: TC_NC_016 - TC_NC_018 (3 failed, 0 blocked)
A10: BUG_009 | B10: [New Customer] Mobile number length is not validated (9 and 11 digits are accepted) | C10: E59 requires a 10-digit mobile number, but customers are created with 9-digit and 11-digit numbers. | D10: Logged in as a Manager New Customer page is open | E10: Google Chrome; Guru99 Bank demo site (V2) - https://demo.guru99.com/V4/ | F10: 1. Open New Customer 2. Fill all fields with valid data and enter a 9-digit (or 11-digit) Mobile Number 3. Click Submit | G10: E59 "Mobile number must be 10 digits" is displayed and no customer is created. | H10: Customers were created with IDs 33471 (9 digits) and 78251 (11 digits); no error message was displayed. | I10: Medium | J10: Medium | K10: Open | L10: Mobile Number: 555123456; 55512345678 | M10: Amjad | N10: Development Team | O10: TC_NC_036 - TC_NC_037 (2 failed, 0 blocked)
A11: BUG_010 | B11: [New Customer] Password rules are not enforced (5-character and 31-character passwords accepted) | C11: The SRS defines a password of 6 to 30 characters. A 5-character password and a 31-character password are accepted. | D11: Logged in as a Manager New Customer page is open | E11: Google Chrome; Guru99 Bank demo site (V2) - https://demo.guru99.com/V4/ | F11: 1. Open New Customer 2. Fill all fields with valid data and enter a 5-character (or 31-character) Password 3. Click Submit | G11: The password is rejected with an error and no customer is created. | H11: A customer was created with a 5-character password (Customer ID 790); the 30-character and 31-character passwords were both accepted. | I11: Medium | J11: Medium | K11: Open | L11: Password: Ab@12; 31 characters | M11: Amjad | N11: Development Team | O11: TC_NC_044, TC_NC_046 (2 failed, 0 blocked)
A12: BUG_011 | B12: [New Customer] Gender cannot be left unselected (a default gender is selected) | C12: A gender is selected by default, so the mandatory-selection rule (NC20) cannot be tested and the user may submit a gender they did not choose. | D12: Logged in as a Manager New Customer page is open | E12: Google Chrome; Guru99 Bank demo site (V2) - https://demo.guru99.com/V4/ | F12: 1. Open New Customer 2. Check the Gender field | G12: No gender is selected by default and an error is displayed if none is chosen. | H12: A gender was selected by default, so the Gender field cannot be left unselected. | I12: Low | J12: Low | K12: Open | L12: Gender: (none selected) | M12: Amjad | N12: Development Team | O12: TC_NC_012 (1 failed, 0 blocked)
A13: BUG_012 | B13: [New Customer] Field maximum lengths are shorter than the SRS (Name 25, Address 50, City/State 25, Email 25) | C13: The fields stop accepting characters earlier than the lengths defined in the SRS (Name 50, Address 200, City 50, State 50, Email 50), so valid long values cannot be entered. | D13: Logged in as a Manager New Customer page is open | E13: Google Chrome; Guru99 Bank demo site (V2) - https://demo.guru99.com/V4/ | F13: 1. Open New Customer 2. Type the maximum length defined in the SRS in Name, Address, City, State and Email | G13: Name, City, State and Email accept 50 characters and Address accepts 200 characters. | H13: Customer Name accepts a maximum of 25 characters, Address 50, City and State 25 and Email 25. | I13: Medium | J13: Low | K13: Open | L13: 50-letter, 200-character and 51-letter strings | M13: Amjad | N13: Development Team | O13: TC_NC_011, TC_NC_023, TC_NC_029, TC_NC_042 (4 failed, 0 blocked)
A14: BUG_013 | B14: [Edit Customer] No confirmation after updating a customer; an empty white page is displayed | C14: After a customer is updated, the manager is redirected to an empty white page with no success or error message, so the result of the update is unclear. | D14: Logged in as a Manager Customer 4073 exists Edit Customer page is open | E14: Google Chrome; Guru99 Bank demo site (V2) - https://demo.guru99.com/V4/ | F14: 1. Open Edit Customer 2. Enter Customer ID 4073 and click Submit 3. Change one or more editable fields 4. Click Submit | G14: A confirmation message is displayed after a successful update. | H14: The customer data was updated, but no success message was displayed and the system redirected the manager to an empty white page. | I14: Medium | J14: Medium | K14: Open | L14: Customer ID: 4073 Address: 45 Park Avenue; City: Cairo; State: Cairo; PIN Code: 654321; Mobile Number: 5559876543; Email: john.edit10@test.com | M14: Amjad | N14: Development Team | O14: TC_EC_010, TC_EC_013, TC_EC_033, TC_EC_036 (4 failed, 0 blocked) | P14: TC_EC_012 (Pass) shows the same missing success message.
A15: BUG_014 | B15: [Edit Customer] Address is not validated on update (blank and special characters are saved) | C15: Edit Customer saves a blank address and an address made of special characters without any error. The same validations as New Customer are required (EC6). | D15: Logged in as a Manager Customer 4073 exists Edit Customer page is open | E15: Google Chrome; Guru99 Bank demo site (V2) - https://demo.guru99.com/V4/ | F15: 1. Open Edit Customer and load customer 4073 2. Clear the Address (or enter @#$%^&) 3. Click Submit | G15: E5 is displayed for a blank address and special characters are rejected; the address is not changed. | H15: The address was changed to blank and to "@#$%^&" and no error message was displayed. | I15: Medium | J15: Medium | K15: Open | L15: Address: (empty); @#$%^& | M15: Amjad | N15: Development Team | O15: TC_EC_014 - TC_EC_015 (2 failed, 0 blocked)
A16: BUG_015 | B16: [Edit Customer] City and State are not validated on update (blank, numbers and special characters are saved) | C16: Edit Customer saves a blank City or State and values containing numbers or special characters without any error. | D16: Logged in as a Manager Customer 4073 exists Edit Customer page is open | E16: Google Chrome; Guru99 Bank demo site (V2) - https://demo.guru99.com/V4/ | F16: 1. Open Edit Customer and load customer 4073 2. Enter a blank, numeric or special-character value in City or State 3. Click Submit | G16: E6 / E7 are displayed for blank values and E48 for numbers; special characters are rejected; nothing is saved. | H16: City and State were changed to blank, "Cairo123", "Cairo@#" and "Giza12"; no error message was displayed and the system redirected the manager to an empty white page. | I16: Medium | J16: Medium | K16: Open | L16: City: (empty); Cairo123; Cairo@# State: (empty); Giza12 | M16: Amjad | N16: Development Team | O16: TC_EC_017 - TC_EC_021 (5 failed, 0 blocked)
A17: BUG_016 | B17: [Edit Customer] PIN Code is not validated on update (blank, non-numeric and 5-digit values are saved) | C17: Edit Customer saves a blank PIN, a non-numeric PIN and a PIN shorter than 6 digits. A 7-digit PIN is silently cut to 6 digits. | D17: Logged in as a Manager Customer 4073 exists Edit Customer page is open | E17: Google Chrome; Guru99 Bank demo site (V2) - https://demo.guru99.com/V4/ | F17: 1. Open Edit Customer and load customer 4073 2. Enter a blank, non-numeric, 5-digit or 7-digit PIN Code 3. Click Submit | G17: E8, E9 and E10 are displayed and the PIN is not changed. | H17: The PIN was changed to blank, "12@#56" and "12345"; the 7-digit value was saved as "123456". No error message was displayed and the system redirected the manager to an empty white page. | I17: Medium | J17: Medium | K17: Open | L17: PIN Code: (empty); 12AB56; 12@#56; 12345; 1234567 | M17: Amjad | N17: Development Team | O17: TC_EC_023 - TC_EC_026 (4 failed, 0 blocked)
A18: BUG_017 | B18: [Edit Customer] Mobile Number is not validated on update (blank, non-numeric, 9 and 11 digits are saved) | C18: Edit Customer saves a blank, non-numeric, 9-digit and 11-digit mobile number without any error. | D18: Logged in as a Manager Customer 4073 exists Edit Customer page is open | E18: Google Chrome; Guru99 Bank demo site (V2) - https://demo.guru99.com/V4/ | F18: 1. Open Edit Customer and load customer 4073 2. Enter a blank, non-numeric, 9-digit or 11-digit Mobile Number 3. Click Submit | G18: E11, E12 and E59 are displayed and the mobile number is not changed. | H18: The mobile number was changed to blank, "555123@#90", "555123456" and "55512345678"; no error message was displayed and the system redirected the manager to an empty white page. | I18: Medium | J18: Medium | K18: Open | L18: Mobile Number: (empty); 55512ABC90; 555123@#90; 555123456; 55512345678 | M18: Amjad | N18: Development Team | O18: TC_EC_027 - TC_EC_030 (4 failed, 0 blocked)
A19: BUG_018 | B19: [Edit Customer] Email is not validated on update (blank and invalid formats are saved) | C19: Edit Customer saves a blank email and invalid email formats without any error. | D19: Logged in as a Manager Customer 4073 exists Edit Customer page is open | E19: Google Chrome; Guru99 Bank demo site (V2) - https://demo.guru99.com/V4/ | F19: 1. Open Edit Customer and load customer 4073 2. Enter a blank or invalid Email (for example john.smith or john@) 3. Click Submit | G19: E13 is displayed for a blank email and E14 for an invalid format; the email is not changed. | H19: The email was changed to blank and to the last invalid value; no error message was displayed and the system redirected the manager to an empty white page. | I19: Medium | J19: Medium | K19: Open | L19: Email: (empty); john.smith; john@; @test.com; john@test; john smith@test.com | M19: Amjad | N19: Development Team | O19: TC_EC_031 - TC_EC_032 (2 failed, 0 blocked)
A20: BUG_019 | B20: [Edit Customer] Duplicate email accepted on update (E49 is not enforced) | C20: A customer email can be changed to an email that already belongs to another customer, so email uniqueness (EC5) is not enforced. | D20: Logged in as a Manager Customer 4073 exists Another customer already uses the email a1a@gmail.com | E20: Google Chrome; Guru99 Bank demo site (V2) - https://demo.guru99.com/V4/ | F20: 1. Open Edit Customer and load customer 4073 2. Enter the email of another customer 3. Click Submit | G20: E49 "Customer with this email already exists" is displayed and the email is not changed. | H20: The email was changed to "a1a@gmail.com" and to "JOHN.SMITH04B@TEST.COM" and the duplicate-email error (E49) was not displayed. | I20: High | J20: High | K20: Open | L20: Email: a1a@gmail.com; JOHN.SMITH04B@TEST.COM | M20: Amjad | N20: Development Team | O20: TC_EC_034 - TC_EC_035 (2 failed, 0 blocked) | P20: Please confirm which customer owns a1a@gmail.com (see the note on TC_EC_034).
A21: BUG_020 | B21: [Edit Customer] Invalid values are saved when several fields are invalid (rejected update still changes data) | C21: When invalid values are submitted together, they are all stored. A rejected update must not change the stored customer data. | D21: Logged in as a Manager Customer 4073 exists Edit Customer page is open | E21: Google Chrome; Guru99 Bank demo site (V2) - https://demo.guru99.com/V4/ | F21: 1. Open Edit Customer and load customer 4073 2. Enter invalid PIN, Mobile Number and Email 3. Click Submit 4. Reload the customer | G21: E10, E12 and E14 are displayed and the stored data is unchanged. | H21: The PIN, mobile number and email were changed to the invalid values; no error message was displayed and the system redirected the manager to an empty white page. | I21: High | J21: High | K21: Open | L21: PIN Code: 123 Mobile Number: abc Email: xyz | M21: Amjad | N21: Development Team | O21: TC_EC_038 - TC_EC_039 (2 failed, 0 blocked)
A22: BUG_021 | B22: [Edit Customer] Field maximum lengths are shorter than the SRS (Address 50, City/State 25, Email 30) | C22: The editable fields stop accepting characters earlier than the lengths defined in the SRS. | D22: Logged in as a Manager Customer 4073 exists Edit Customer page is open | E22: Google Chrome; Guru99 Bank demo site (V2) - https://demo.guru99.com/V4/ | F22: 1. Open Edit Customer and load customer 4073 2. Type the maximum length defined in the SRS in Address, City, State and Email | G22: Address accepts 200 characters; City, State and Email accept 50 characters. | H22: The Address field accepts a maximum of 50 characters, City and State 25 and Email 30. | I22: Low | J22: Low | K22: Open | L22: 200-character and 50-character strings | M22: Amjad | N22: Development Team | O22: TC_EC_016, TC_EC_022, TC_EC_037 (3 failed, 0 blocked)
A23: BUG_022 | B23: [Delete Customer] "This page isn't working" error page after deleting a customer; no confirmation message | C23: Deleting a customer ends on an error page with no success or error message, so the manager cannot tell whether the deletion worked. | D23: Logged in as a Manager Customer 4073 exists, has no accounts and is associated with the Manager | E23: Google Chrome; Guru99 Bank demo site (V2) - https://demo.guru99.com/V4/ | F23: 1. Open Delete Customer 2. Enter Customer ID 4073 3. Click Delete and confirm the dialog | G23: A success message is displayed after the customer is deleted. | H23: The customer was deleted, but the system redirected the manager to a "This page isn't working" error page; no success or error message was displayed. | I23: Medium | J23: Medium | K23: Open | L23: Customer ID: 4073 | M23: Amjad | N23: Development Team | O23: TC_DC_001, TC_DC_014 (2 failed, 0 blocked) | P23: TC_DC_002, TC_DC_004 and TC_DC_005 (marked Pass) show the same error page.
A24: BUG_023 | B24: [New Account] Customer ID field does not limit the input to 10 digits | C24: An 11-digit Customer ID can be typed and submitted; the SRS limits the field to 10 characters. | D24: Logged in as a Manager New Account page is open | E24: Google Chrome; Guru99 Bank demo site (V2) - https://demo.guru99.com/V4/ | F24: 1. Open New Account 2. Enter an 11-digit Customer ID 3. Select Savings and enter 1000 4. Click Submit | G24: Only 10 digits can be entered. | H24: The system displayed E51 "Customer ID does not exist" for the 11-digit ID; the field did not limit the input to 10 digits. | I24: Low | J24: Low | K24: Open | L24: Customer ID: 12345678901 Account Type: Savings Initial Deposit: 1000 | M24: Amjad | N24: Development Team | O24: TC_NA_013 (1 failed, 0 blocked)
A25: BUG_024 | B25: [New Account] Decimal Initial Deposit is rejected with a misleading "must be numeric" message | C25: The value 500.50 is numeric but is rejected with E19 "Initial Deposit must be numeric". The SRS does not define decimals, so the behavior and message should be clarified. | D25: Logged in as a Manager Customer 38892 exists New Account page is open | E25: Google Chrome; Guru99 Bank demo site (V2) - https://demo.guru99.com/V4/ | F25: 1. Open New Account 2. Enter Customer ID 38892 and select Savings 3. Enter 500.50 as Initial Deposit 4. Click Submit | G25: The account is created with balance 500.50, or a clear error explains why decimals are not allowed. | H25: E19 "Initial Deposit must be numeric" was displayed for the decimal value 500.50; no account was created. | I25: Low | J25: Low | K25: Open | L25: Customer ID: 38892 Account Type: Savings Initial Deposit: 500.50 | M25: Amjad | N25: Development Team | O25: TC_NA_022 (1 failed, 0 blocked)
A26: BUG_025 | B26: [New Account] Initial Deposit field accepts a maximum of 8 digits | C26: The Initial Deposit field stops accepting digits after 8, so the very-large-value case cannot be tested and the length differs from the SRS (20). | D26: Logged in as a Manager New Account page is open | E26: Google Chrome; Guru99 Bank demo site (V2) - https://demo.guru99.com/V4/ | F26: 1. Open New Account 2. Type a 20-digit value in Initial Deposit | G26: The field accepts up to 20 characters, or a clear error is displayed for a value that is too large. | H26: The Initial Deposit field accepts a maximum of 8 digits. | I26: Low | J26: Low | K26: Open | L26: Initial Deposit: 99999999999999999999 (20 digits) | M26: Amjad | N26: Development Team | O26: TC_NA_025 (1 failed, 0 blocked)
A27: BUG_026 | B27: [Edit Account] "This page isn't working" error page after submitting an Account Number in Edit Account | C27: Edit Account cannot be used: a valid Account Number leads to an error page, so account details can never be loaded or edited. All dependent tests are blocked. | D27: Logged in as a Manager Account 185657 (Savings) exists | E27: Google Chrome; Guru99 Bank demo site (V2) - https://demo.guru99.com/V4/ | F27: 1. Open Edit Account 2. Enter Account Number 185657 3. Click Submit | G27: The account details are displayed in an editable form. | H27: After submitting the Account Number, the system redirected the manager to a "This page isn't working" error page. | I27: High | J27: High | K27: Open | L27: Account Number: 185657 | M27: Amjad | N27: Development Team | O27: TC_EA_001 - TC_EA_008, TC_EA_010 - TC_EA_015 (1 failed, 13 blocked)
A28: BUG_027 | B28: [Delete Account] "This page isn't working" error page after submitting an Account Number in Delete Account | C28: Delete Account ends on an error page for valid account numbers, so deletion and its business rules (E53) cannot be verified. | D28: Logged in as a Manager Account 185657 (balance 1000.00) exists | E28: Google Chrome; Guru99 Bank demo site (V2) - https://demo.guru99.com/V4/ | F28: 1. Open Delete Account 2. Enter Account Number 185657 3. Click Delete | G28: E53 "Account balance must be zero to delete" is displayed for an account with a positive balance. | H28: The system redirected the manager to a "This page isn't working" error page. | I28: High | J28: High | K28: Open | L28: Account Number: 185657 (balance 1000.00) | M28: Amjad | N28: Development Team | O28: TC_DA_004 - TC_DA_005, TC_DA_010 - TC_DA_013 (4 failed, 2 blocked)
A29: BUG_028 | B29: [Deposit] "This page isn't working" error page after submitting a deposit | C29: A valid deposit ends on an error page, so deposits cannot be confirmed and all deposit validations, balance checks and statements that depend on it cannot be tested. | D29: Logged in as a Manager Account 185657 exists | E29: Google Chrome; Guru99 Bank demo site (V2) - https://demo.guru99.com/V4/ | F29: 1. Open Deposit 2. Enter Account Number 185657, Amount 500 and Description "Salary deposit" 3. Click Submit | G29: The deposit succeeds; the updated balance and a Transaction ID are displayed. | H29: After clicking Submit, the system redirected the manager to a "This page isn't working" error page. | I29: Critical | J29: High | K29: Open | L29: Account Number: 185657 Amount: 500 Description: Salary deposit | M29: Amjad | N29: Development Team | O29: TC_DP_001 - TC_DP_003, TC_DP_008 - TC_DP_009, TC_DP_012 - TC_DP_017, TC_DP_020, TC_DP_022 - TC_DP_024, TC_DP_026 - TC_DP_027 (1 failed, 16 blocked)
A30: BUG_029 | B30: [Deposit] Description field accepts a maximum of 10 characters (SRS: 200) | C30: The Description field is far shorter than the 200 characters required by the SRS, so normal descriptions are cut and the XSS test could not be completed. | D30: Logged in as a Manager Deposit page is open | E30: Google Chrome; Guru99 Bank demo site (V2) - https://demo.guru99.com/V4/ | F30: 1. Open Deposit 2. Type a 200-character text (and a script tag) in Description | G30: Description accepts 200 characters. | H30: The Description field accepts a maximum of 10 characters. | I30: Medium | J30: Medium | K30: Open | L30: Description: 200-character and 201-character texts; <script>alert('x')</script> | M30: Amjad | N30: Development Team | O30: TC_DP_019, TC_DP_021 (2 failed, 0 blocked)
A31: BUG_030 | B31: [Withdrawal] No success or failure message after submitting a withdrawal | C31: After a withdrawal is submitted the system shows no result message, so the manager cannot know whether it succeeded. Amount boundaries, zero, negative and decimal values cannot be verified. | D31: Logged in as a Manager Account 185657 exists with a known balance B | E31: Google Chrome; Guru99 Bank demo site (V2) - https://demo.guru99.com/V4/ | F31: 1. Open Withdrawal 2. Enter Account Number 185657, an Amount and a Description 3. Click Submit | G31: A success message, or the relevant error (for example E42 for insufficient balance), is displayed. | H31: After clicking Submit, the system did not show whether the withdrawal succeeded or failed. | I31: High | J31: High | K31: Open | L31: Account Number: 185657 Amount: B; B - 1; B + 1; 1; 0.01; 0; -100; 100.50; 100.555 Description: ATM withdrawal | M31: Amjad | N31: Development Team | O31: TC_WD_006 - TC_WD_010, TC_WD_018 - TC_WD_021, TC_WD_026, TC_WD_028 (11 failed, 0 blocked)
A32: BUG_031 | B32: [Withdrawal] Description field accepts a maximum of 10 characters (SRS: 200) | C32: The Description field is far shorter than the 200 characters required by the SRS, so normal descriptions are cut and the XSS test could not be completed. | D32: Logged in as a Manager Withdrawal page is open | E32: Google Chrome; Guru99 Bank demo site (V2) - https://demo.guru99.com/V4/ | F32: 1. Open Withdrawal 2. Type a 200-character text (and a script tag) in Description | G32: Description accepts 200 characters. | H32: The Description field accepts a maximum of 10 characters. | I32: Medium | J32: Medium | K32: Open | L32: Description: 200-character and 201-character texts; <script>alert('x')</script> | M32: Amjad | N32: Development Team | O32: TC_WD_024 - TC_WD_025 (2 failed, 0 blocked)
A33: BUG_032 | B33: [Fund Transfer] Empty page showing only the "Fund transfer details" title after submitting a transfer | C33: A transfer request ends on an empty page with no success or error message. The result of every transfer is unknown, so balances, statements and boundary rules cannot be verified. | D33: Logged in as a Manager Payer account 185671 and payee account 185672 exist | E33: Google Chrome; Guru99 Bank demo site (V2) - https://demo.guru99.com/V4/ | F33: 1. Open Fund Transfer 2. Enter Payer 185671, Payee 185672, Amount 100 and Description "Rent payment" 3. Click Submit | G33: The transfer succeeds, the balances change and a confirmation is displayed. | H33: After clicking Submit, the system redirected the manager to an empty page showing only the "Fund transfer details" title; no success or error message was displayed. | I33: Critical | J33: High | K33: Open | L33: Payer Account: 185671 Payee Account: 185672 Amount: 100 Description: Rent payment | M33: Amjad | N33: Development Team | O33: TC_FT_001 - TC_FT_006, TC_FT_017 - TC_FT_020, TC_FT_024 - TC_FT_027, TC_FT_029, TC_FT_031 (16 failed, 0 blocked) | P33: TC_FT_027 (Reset) and TC_FT_031 (SQL injection) need their actual results to be confirmed (see the notes on those cells).
A34: BUG_033 | B34: [Fund Transfer] Description field accepts a maximum of 20 characters | C34: The Description field is too short for normal descriptions and the XSS test could not be completed. | D34: Logged in as a Manager Fund Transfer page is open | E34: Google Chrome; Guru99 Bank demo site (V2) - https://demo.guru99.com/V4/ | F34: 1. Open Fund Transfer 2. Type a long text (and a script tag) in Description | G34: Long descriptions are accepted (up to 200 characters). | H34: The Description field accepts a maximum of 20 characters. | I34: Medium | J34: Medium | K34: Open | L34: Description: long text; <script>alert('x')</script> | M34: Amjad | N34: Development Team | O34: TC_FT_022, TC_FT_030 (2 failed, 0 blocked)
A35: BUG_034 | B35: [Balance Enquiry] "This page isn't working" error page after submitting an Account Number in Balance Enquiry | C35: Balance Enquiry fails with an error page for valid and non-existent account numbers, so no balance can be checked. Every test that verifies a balance after another operation is affected. | D35: Logged in as a Manager Account 185674 exists | E35: Google Chrome; Guru99 Bank demo site (V2) - https://demo.guru99.com/V4/ | F35: 1. Open Balance Enquiry 2. Enter Account Number 185674 3. Click Submit | G35: The current balance and the account details are displayed. | H35: The system redirected the manager to a "This page isn't working" error page. | I35: Critical | J35: High | K35: Open | L35: Account Number: 185674 | M35: Amjad | N35: Development Team | O35: TC_BE_001 - TC_BE_007, TC_BE_011, TC_BE_014; TC_NA_007; TC_WD_002 (6 failed, 5 blocked) | P35: Also affects TC_NA_007 and TC_WD_002, which verify balances through this page.
A36: BUG_035 | B36: [Mini Statement] Empty white page after submitting an Account Number in Mini Statement | C36: Mini Statement shows an empty white page for valid accounts, so transactions cannot be viewed and all statement content rules cannot be tested. | D36: Logged in as a Manager Account 185674 has transactions | E36: Google Chrome; Guru99 Bank demo site (V2) - https://demo.guru99.com/V4/ | F36: 1. Open Mini Statement 2. Enter Account Number 185674 3. Click Submit | G36: The last 5 transactions of the account are displayed. | H36: The system redirected the manager to an empty white page; no success or error message was displayed. | I36: High | J36: High | K36: Open | L36: Account Number: 185674 | M36: Amjad | N36: Development Team | O36: TC_MS_001 - TC_MS_014; TC_WD_003, TC_WD_011 (11 failed, 5 blocked) | P36: Also affects TC_WD_003 and TC_WD_011, which verify transactions through this page.
A37: BUG_036 | B37: [Customized Statement] Empty white page after submitting valid statement criteria | C37: Customized Statement shows an empty white page for valid requests (date ranges, filters), so no statement can be produced. | D37: Logged in as a Manager Account 185674 has transactions | E37: Google Chrome; Guru99 Bank demo site (V2) - https://demo.guru99.com/V4/ | F37: 1. Open Customized Statement 2. Enter Account Number 185674 and a valid From Date and To Date 3. Click Submit | G37: The transactions of the account inside the date range are displayed. | H37: The system redirected the manager to an empty white page; no success or error message was displayed. | I37: High | J37: High | K37: Open | L37: Account Number: 185674 From Date: Execution date - 7 days To Date: Execution date | M37: Amjad | N37: Development Team | O37: TC_CS_001 - TC_CS_004, TC_CS_010 - TC_CS_014, TC_CS_017, TC_CS_025 (11 failed, 0 blocked)
A38: BUG_037 | B38: [Customized Statement] Date validations are missing (From Date later than To Date, blank dates and invalid dates are accepted) | C38: The SRS requires E30, E31, E32 and E57 for invalid dates. None of these errors is displayed. | D38: Logged in as a Manager Customized Statement page is open | E38: Google Chrome; Guru99 Bank demo site (V2) - https://demo.guru99.com/V4/ | F38: 1. Open Customized Statement 2. Enter Account Number 185674 3. Enter a From Date later than the To Date (or leave a date blank, or enter an invalid date) 4. Click Submit | G38: E32, E30, E31 or E57 is displayed. | H38: The system accepted the dates; the errors E30, E31, E32 and E57 were not displayed. | I38: Medium | J38: Medium | K38: Open | L38: From Date: Execution date; To Date: Execution date - 7 days From Date: (empty); To Date: (empty) From Date: 31/02/2025; abc | M38: Amjad | N38: Development Team | O38: TC_CS_005 - TC_CS_009 (5 failed, 0 blocked)
A39: BUG_038 | B39: [Customized Statement] Minimum Transaction Value and Number of Transactions accept zero, negative and decimal values without any message | C39: Zero, negative and decimal values are accepted and no error or explanation is displayed (the SRS does not define these cases). | D39: Logged in as a Manager Customized Statement page is open | E39: Google Chrome; Guru99 Bank demo site (V2) - https://demo.guru99.com/V4/ | F39: 1. Open Customized Statement 2. Enter valid account and dates 3. Enter 0, -100 or 100.50 as Min Transaction Value (or 0 / -3 as Number of Transactions) 4. Click Submit | G39: A clear error is displayed, or the values are handled consistently. | H39: No error message was displayed. | I39: Low | J39: Low | K39: Open | L39: Min Transaction Value: 0; -100; 100.50 Number of Transactions: 0; -3 | M39: Amjad | N39: Development Team | O39: TC_CS_018 - TC_CS_020 (3 failed, 0 blocked)
A40: BUG_039 | B40: [Customized Statement] Account Number validations (E21, E22, E24, E44) are not working | C40: Blank, non-numeric, non-existent and another Manager's account numbers do not produce the expected errors in Customized Statement. | D40: Logged in as a Manager Customized Statement page is open | E40: Google Chrome; Guru99 Bank demo site (V2) - https://demo.guru99.com/V4/ | F40: 1. Open Customized Statement 2. Enter a blank, non-numeric, non-existent or another Manager's Account Number with valid dates 3. Click Submit | G40: E21, E22, E24 or E44 is displayed. | H40: The expected error messages were not displayed (the actual results recorded for these tests equal the expected results; please confirm). | I40: Medium | J40: Medium | K40: Open | L40: Account Number: (empty); ABC123; 12@#45; 999999999999999; an account of a Manager 2 customer | M40: Amjad | N40: Development Team | O40: TC_CS_021 - TC_CS_024 (4 failed, 0 blocked) | P40: Actual results of these tests need to be confirmed (see the notes on those cells).
A41: BUG_040 | B41: [Change Password] Password length rules are not enforced (5-character and 31-character passwords accepted) | C41: Change Password accepts a 5-character password and a 31-character password, although the SRS requires at least 6 characters (CP4) and the login allows 30. | D41: Logged in as a Manager | E41: Google Chrome; Guru99 Bank demo site (V2) - https://demo.guru99.com/V4/ | F41: 1. Open Change Password 2. Enter the current password 3. Enter a 5-character (or 31-character) New Password and the same Confirm Password 4. Click Submit | G41: The 5-character and 31-character passwords are rejected with an error. | H41: The 5-character password was accepted, and both the 30-character and the 31-character passwords were accepted; the password was changed each time. | I41: Medium | J41: Medium | K41: Open | L41: New Password: Ab@12; 30 characters; 31 characters | M41: Amjad | N41: Development Team | O41: TC_CP_010, TC_CP_015 (2 failed, 0 blocked)
A42: BUG_041 | B42: [Change Password] Password containing spaces is accepted | C42: A new password containing spaces is accepted. The SRS does not define allowed characters; the behavior should be confirmed. | D42: Logged in as a Manager | E42: Google Chrome; Guru99 Bank demo site (V2) - https://demo.guru99.com/V4/ | F42: 1. Open Change Password 2. Enter the current password 3. Enter "P@ss word 1" as New Password and Confirm Password 4. Click Submit | G42: The behavior is consistent: the password is rejected, or it is accepted and works at the next login. | H42: The password containing spaces was accepted and the password was changed. | I42: Low | J42: Low | K42: Open | L42: New Password: P@ss word 1 | M42: Amjad | N42: Development Team | O42: TC_CP_017 (1 failed, 0 blocked)

Sheet Failed-Blocked Tests
A1: Test Case ID | B1: Module | C1: Title | D1: Priority | E1: Status | F1: Actual result | G1: Bug ID | H1: Bug summary / reason
A2: TC_LG_005 | B2: Login | C2: Non-existent User ID | D2: High | E2: Fail | F2: The alert "User is not valid" was displayed instead of the message required by the SRS (E3: "User ID and Password do not match"). The login was rejected. | G2: BUG_006 | H2: [Login] Invalid login shows "User is not valid" instead of the SRS message E3
A3: TC_LG_006 | B3: Login | C3: Incorrect Password | D3: High | E3: Fail | F3: The alert "User is not valid" was displayed instead of the message required by the SRS (E3: "User ID and Password do not match"). The login was rejected. | G3: BUG_006 | H3: [Login] Invalid login shows "User is not valid" instead of the SRS message E3
A4: TC_LG_007 | B4: Login | C4: Case sensitivity: User ID | D4: Medium | E4: Fail | F4: The system accepted the User ID in uppercase and redirected the manager to the dashboard (the User ID is not case-sensitive). | G4: BUG_005 | H4: [Login] User ID and Password are not case-sensitive
A5: TC_LG_008 | B5: Login | C5: Case sensitivity: Password | D5: Medium | E5: Fail | F5: The system accepted the Password with different letter casing and redirected the manager to the dashboard (the Password is not case-sensitive). | G5: BUG_005 | H5: [Login] User ID and Password are not case-sensitive
A6: TC_LG_009 | B6: Login | C6: Lockout after 3 failed attempts | D6: High | E6: Fail | F6: The account was not locked after the 3 failed attempts and no error message was displayed. | G6: BUG_003 | H6: [Login] Account is not locked after 3 failed login attempts
A7: TC_LG_010 | B7: Login | C7: Locked account with valid credentials | D7: High | E7: Fail | F7: The account was not locked, so the lockout message (E55) was not displayed. | G7: BUG_003 | H7: [Login] Account is not locked after 3 failed login attempts
A8: TC_LG_013 | B8: Login | C8: Maximum length of 30 characters | D8: Medium | E8: Fail | F8: The User ID field accepts a maximum of 10 characters and the Password field has no maximum length limit. | G8: BUG_007 | H8: [Login] Login field length limits differ from the SRS (User ID max 10, Password unlimited)
A9: TC_LG_014 | B9: Login | C9: Basic SQL injection | D9: High | E9: Fail | F9: The system accepted the login and redirected the manager to the dashboard. | G9: BUG_001 | H9: [Login] SQL injection input bypasses the login (authentication bypass)
A10: TC_LG_017 | B10: Login | C10: Browser Back button after Logout | D10: High | E10: Fail | F10: The session was not terminated: after pressing the Back button, the manager could return to the dashboard. | G10: BUG_004 | H10: [Login] Session is not terminated after Logout (Back button returns to the dashboard)
A11: TC_LG_018 | B11: Login | C11: Access without login | D11: High | E11: Fail | F11: The system opened the protected page directly without any authentication. | G11: BUG_002 | H11: [Login] Protected pages can be opened directly without logging in
A12: TC_NC_011 | B12: New Customer | C12: Name: max length 50 (BVA) | D12: Medium | E12: Fail | F12: The Customer Name field accepts a maximum of 25 characters. | G12: BUG_012 | H12: [New Customer] Field maximum lengths are shorter than the SRS (Name 25, Address 50, City/State 25, Email 25)
... A185: TC_CP_017 | B185: Change Password | C185: New Password: contains spaces | D185: Low | E185: Fail | F185: The password containing spaces was accepted and the password was changed. | G185: BUG_041 | H185: [Change Password] Password containing spaces is accepted

Sheet Test Summary Report
A1: Test Summary Report
A2: Guru99 Bank - Manual Functional Testing
A4: 1. Test overview
A5: Project name | B5: ='Test Plan'!B2 -> Guru99 Banking project
A6: SRS version | B6: ='Test Plan'!B4 -> 2
A7: Testing type | B7: ='Test Plan'!B5 -> Manual functional testing
A8: Objective | B8: ='Test Plan'!B6 -> Verify that Guru99 Bank meets the specified functional requirements
A9: Scope | B9: ='Test Plan'!B7 -> Functional testing and external interfaces
A10: Out of scope | B10: ='Test Plan'!B8 -> Automation testing and performance/stress testing
A11: User roles tested | B11: ='Test Plan'!B9 -> Manager and customer
A12: Application under test | B12: Guru99 Bank demo site (V4) - https://demo.guru99.com/V4/
A13: Test environment | B13: Google Chrome; Guru99 Bank demo site (V4)
A14: Tester | B14: Amjad Alrays
A15: Report date | B15: 13 Oct 2026
A17: 2. Overall results
A18: Total test cases | B18: =COUNTA('Test Cases'!$A$2:$A$1513) -> 353
A19: Passed | B19: =COUNTIF('Test Cases'!$J$2:$J$1513,"Pass") -> 169
A20: Failed | B20: =COUNTIF('Test Cases'!$J$2:$J$1513,"Fail") -> 137
A21: Blocked | B21: =COUNTIF('Test Cases'!$J$2:$J$1513,"Blocked") -> 47
A22: Not Applicable | B22: =COUNTIF('Test Cases'!$J$2:$J$1513,"Not Applicable") -> 0
A23: Not Executed | B23: =COUNTIF('Test Cases'!$J$2:$J$1513,"Not Executed") -> 0
A24: Executed (Pass + Fail) | B24: =B19+B20 -> 306
A25: Execution rate (Pass + Fail of total) | B25: =IF(B18=0,0,B24/B18) -> 0.86685552
A26: Pass rate (of executed) | B26: =IF(B24=0,0,B19/B24) -> 0.55228758
A27: Pass rate (of total) | B27: =IF(B18=0,0,B19/B18) -> 0.47875354
A29: 3. Results by module
A30: Module | B30: Name | C30: Total | D30: Pass | E30: Fail | F30: Blocked | G30: Not Applicable | H30: Not Executed | I30: Executed % | J30: Pass % (of executed) | K30: Pass % (of total)
A31: LG | B31: Login | C31: =COUNTIF('Test Cases'!$A$2:$A$1513,"TC_LG_*") -> 18 | D31: =COUNTIFS('Test Cases'!$A$2:$A$1513,"TC_LG_*",'Test Cases'!$J$2:$J$1513,"Pass") -> 8 | E31: =COUNTIFS('Test Cases'!$A$2:$A$1513,"TC_LG_*",'Test Cases'!$J$2:$J$1513,"Fail") -> 10 | F31: =COUNTIFS('Test Cases'!$A$2:$A$1513,"TC_LG_*",'Test Cases'!$J$2:$J$1513,"Blocked") -> 0 | G31: =COUNTIFS('Test Cases'!$A$2:$A$1513,"TC_LG_*",'Test Cases'!$J$2:$J$1513,"Not Applicable") -> 0 | H31: =COUNTIFS('Test Cases'!$A$2:$A$1513,"TC_LG_*",'Test Cases'!$J$2:$J$1513,"Not Executed") -> 0 | I31: =IF(C31=0,0,(D31+E31)/C31) -> 1 | J31: =IF((D31+E31)=0,0,D31/(D31+E31)) -> 0.44444444 | K31: =IF(C31=0,0,D31/C31) -> 0.44444444
A32: NC | B32: New Customer | C32: =COUNTIF('Test Cases'!$A$2:$A$1513,"TC_NC_*") -> 52 | D32: =COUNTIFS('Test Cases'!$A$2:$A$1513,"TC_NC_*",'Test Cases'!$J$2:$J$1513,"Pass") -> 39 | E32: =COUNTIFS('Test Cases'!$A$2:$A$1513,"TC_NC_*",'Test Cases'!$J$2:$J$1513,"Fail") -> 12 | F32: =COUNTIFS('Test Cases'!$A$2:$A$1513,"TC_NC_*",'Test Cases'!$J$2:$J$1513,"Blocked") -> 1 | G32: =COUNTIFS('Test Cases'!$A$2:$A$1513,"TC_NC_*",'Test Cases'!$J$2:$J$1513,"Not Applicable") -> 0 | H32: =COUNTIFS('Test Cases'!$A$2:$A$1513,"TC_NC_*",'Test Cases'!$J$2:$J$1513,"Not Executed") -> 0 | I32: =IF(C32=0,0,(D32+E32)/C32) -> 0.98076923 | J32: =IF((D32+E32)=0,0,D32/(D32+E32)) -> 0.76470588 | K32: =IF(C32=0,0,D32/C32) -> 0.75
A33: EC | B33: Edit Customer | C33: =COUNTIF('Test Cases'!$A$2:$A$1513,"TC_EC_*") -> 40 | D33: =COUNTIFS('Test Cases'!$A$2:$A$1513,"TC_EC_*",'Test Cases'!$J$2:$J$1513,"Pass") -> 12 | E33: =COUNTIFS('Test Cases'!$A$2:$A$1513,"TC_EC_*",'Test Cases'!$J$2:$J$1513,"Fail") -> 28 | F33: =COUNTIFS('Test Cases'!$A$2:$A$1513,"TC_EC_*",'Test Cases'!$J$2:$J$1513,"Blocked") -> 0 | G33: =COUNTIFS('Test Cases'!$A$2:$A$1513,"TC_EC_*",'Test Cases'!$J$2:$J$1513,"Not Applicable") -> 0 | H33: =COUNTIFS('Test Cases'!$A$2:$A$1513,"TC_EC_*",'Test Cases'!$J$2:$J$1513,"Not Executed") -> 0 | I33: =IF(C33=0,0,(D33+E33)/C33) -> 1 | J33: =IF((D33+E33)=0,0,D33/(D33+E33)) -> 0.3 | K33: =IF(C33=0,0,D33/C33) -> 0.3
A34: DC | B34: Delete Customer | C34: =COUNTIF('Test Cases'!$A$2:$A$1513,"TC_DC_*") -> 14 | D34: =COUNTIFS('Test Cases'!$A$2:$A$1513,"TC_DC_*",'Test Cases'!$J$2:$J$1513,"Pass") -> 12 | E34: =COUNTIFS('Test Cases'!$A$2:$A$1513,"TC_DC_*",'Test Cases'!$J$2:$J$1513,"Fail") -> 2 | F34: =COUNTIFS('Test Cases'!$A$2:$A$1513,"TC_DC_*",'Test Cases'!$J$2:$J$1513,"Blocked") -> 0 | G34: =COUNTIFS('Test Cases'!$A$2:$A$1513,"TC_DC_*",'Test Cases'!$J$2:$J$1513,"Not Applicable") -> 0 | H34: =COUNTIFS('Test Cases'!$A$2:$A$1513,"TC_DC_*",'Test Cases'!$J$2:$J$1513,"Not Executed") -> 0 | I34: =IF(C34=0,0,(D34+E34)/C34) -> 1 | J34: =IF((D34+E34)=0,0,D34/(D34+E34)) -> 0.85714286 | K34: =IF(C34=0,0,D34/C34) -> 0.85714286
A35: NA | B35: New Account | C35: =COUNTIF('Test Cases'!$A$2:$A$1513,"TC_NA_*") -> 29 | D35: =COUNTIFS('Test Cases'!$A$2:$A$1513,"TC_NA_*",'Test Cases'!$J$2:$J$1513,"Pass") -> 23 | E35: =COUNTIFS('Test Cases'!$A$2:$A$1513,"TC_NA_*",'Test Cases'!$J$2:$J$1513,"Fail") -> 4 | F35: =COUNTIFS('Test Cases'!$A$2:$A$1513,"TC_NA_*",'Test Cases'!$J$2:$J$1513,"Blocked") -> 2 | G35: =COUNTIFS('Test Cases'!$A$2:$A$1513,"TC_NA_*",'Test Cases'!$J$2:$J$1513,"Not Applicable") -> 0 | H35: =COUNTIFS('Test Cases'!$A$2:$A$1513,"TC_NA_*",'Test Cases'!$J$2:$J$1513,"Not Executed") -> 0 | I35: =IF(C35=0,0,(D35+E35)/C35) -> 0.93103448 | J35: =IF((D35+E35)=0,0,D35/(D35+E35)) -> 0.85185185 | K35: =IF(C35=0,0,D35/C35) -> 0.79310345
A36: EA | B36: Edit Account | C36: =COUNTIF('Test Cases'!$A$2:$A$1513,"TC_EA_*") -> 15 | D36: =COUNTIFS('Test Cases'!$A$2:$A$1513,"TC_EA_*",'Test Cases'!$J$2:$J$1513,"Pass") -> 1 | E36: =COUNTIFS('Test Cases'!$A$2:$A$1513,"TC_EA_*",'Test Cases'!$J$2:$J$1513,"Fail") -> 1 | F36: =COUNTIFS('Test Cases'!$A$2:$A$1513,"TC_EA_*",'Test Cases'!$J$2:$J$1513,"Blocked") -> 13 | G36: =COUNTIFS('Test Cases'!$A$2:$A$1513,"TC_EA_*",'Test Cases'!$J$2:$J$1513,"Not Applicable") -> 0 | H36: =COUNTIFS('Test Cases'!$A$2:$A$1513,"TC_EA_*",'Test Cases'!$J$2:$J$1513,"Not Executed") -> 0 | I36: =IF(C36=0,0,(D36+E36)/C36) -> 0.13333333 | J36: =IF((D36+E36)=0,0,D36/(D36+E36)) -> 0.5 | K36: =IF(C36=0,0,D36/C36) -> 0.066666667
A37: DA | B37: Delete Account | C37: =COUNTIF('Test Cases'!$A$2:$A$1513,"TC_DA_*") -> 13 | D37: =COUNTIFS('Test Cases'!$A$2:$A$1513,"TC_DA_*",'Test Cases'!$J$2:$J$1513,"Pass") -> 4 | E37: =COUNTIFS('Test Cases'!$A$2:$A$1513,"TC_DA_*",'Test Cases'!$J$2:$J$1513,"Fail") -> 4 | F37: =COUNTIFS('Test Cases'!$A$2:$A$1513,"TC_DA_*",'Test Cases'!$J$2:$J$1513,"Blocked") -> 5 | G37: =COUNTIFS('Test Cases'!$A$2:$A$1513,"TC_DA_*",'Test Cases'!$J$2:$J$1513,"Not Applicable") -> 0 | H37: =COUNTIFS('Test Cases'!$A$2:$A$1513,"TC_DA_*",'Test Cases'!$J$2:$J$1513,"Not Executed") -> 0 | I37: =IF(C37=0,0,(D37+E37)/C37) -> 0.61538462 | J37: =IF((D37+E37)=0,0,D37/(D37+E37)) -> 0.5 | K37: =IF(C37=0,0,D37/C37) -> 0.30769231
A38: DP | B38: Deposit | C38: =COUNTIF('Test Cases'!$A$2:$A$1513,"TC_DP_*") -> 27 | D38: =COUNTIFS('Test Cases'!$A$2:$A$1513,"TC_DP_*",'Test Cases'!$J$2:$J$1513,"Pass") -> 8 | E38: =COUNTIFS('Test Cases'!$A$2:$A$1513,"TC_DP_*",'Test Cases'!$J$2:$J$1513,"Fail") -> 3 | F38: =COUNTIFS('Test Cases'!$A$2:$A$1513,"TC_DP_*",'Test Cases'!$J$2:$J$1513,"Blocked") -> 16 | G38: =COUNTIFS('Test Cases'!$A$2:$A$1513,"TC_DP_*",'Test Cases'!$J$2:$J$1513,"Not Applicable") -> 0 | H38: =COUNTIFS('Test Cases'!$A$2:$A$1513,"TC_DP_*",'Test Cases'!$J$2:$J$1513,"Not Executed") -> 0 | I38: =IF(C38=0,0,(D38+E38)/C38) -> 0.40740741 | J38: =IF((D38+E38)=0,0,D38/(D38+E38)) -> 0.72727273 | K38: =IF(C38=0,0,D38/C38) -> 0.2962963
A39: WD | B39: Withdrawal | C39: =COUNTIF('Test Cases'!$A$2:$A$1513,"TC_WD_*") -> 29 | D39: =COUNTIFS('Test Cases'!$A$2:$A$1513,"TC_WD_*",'Test Cases'!$J$2:$J$1513,"Pass") -> 13 | E39: =COUNTIFS('Test Cases'!$A$2:$A$1513,"TC_WD_*",'Test Cases'!$J$2:$J$1513,"Fail") -> 16 | F39: =COUNTIFS('Test Cases'!$A$2:$A$1513,"TC_WD_*",'Test Cases'!$J$2:$J$1513,"Blocked") -> 0 | G39: =COUNTIFS('Test Cases'!$A$2:$A$1513,"TC_WD_*",'Test Cases'!$J$2:$J$1513,"Not Applicable") -> 0 | H39: =COUNTIFS('Test Cases'!$A$2:$A$1513,"TC_WD_*",'Test Cases'!$J$2:$J$1513,"Not Executed") -> 0 | I39: =IF(C39=0,0,(D39+E39)/C39) -> 1 | J39: =IF((D39+E39)=0,0,D39/(D39+E39)) -> 0.44827586 | K39: =IF(C39=0,0,D39/C39) -> 0.44827586
A40: FT | B40: Fund Transfer | C40: =COUNTIF('Test Cases'!$A$2:$A$1513,"TC_FT_*") -> 31 | D40: =COUNTIFS('Test Cases'!$A$2:$A$1513,"TC_FT_*",'Test Cases'!$J$2:$J$1513,"Pass") -> 13 | E40: =COUNTIFS('Test Cases'!$A$2:$A$1513,"TC_FT_*",'Test Cases'!$J$2:$J$1513,"Fail") -> 18 | F40: =COUNTIFS('Test Cases'!$A$2:$A$1513,"TC_FT_*",'Test Cases'!$J$2:$J$1513,"Blocked") -> 0 | G40: =COUNTIFS('Test Cases'!$A$2:$A$1513,"TC_FT_*",'Test Cases'!$J$2:$J$1513,"Not Applicable") -> 0 | H40: =COUNTIFS('Test Cases'!$A$2:$A$1513,"TC_FT_*",'Test Cases'!$J$2:$J$1513,"Not Executed") -> 0 | I40: =IF(C40=0,0,(D40+E40)/C40) -> 1 | J40: =IF((D40+E40)=0,0,D40/(D40+E40)) -> 0.41935484 | K40: =IF(C40=0,0,D40/C40) -> 0.41935484
A41: BE | B41: Balance Enquiry | C41: =COUNTIF('Test Cases'!$A$2:$A$1513,"TC_BE_*") -> 15 | D41: =COUNTIFS('Test Cases'!$A$2:$A$1513,"TC_BE_*",'Test Cases'!$J$2:$J$1513,"Pass") -> 6 | E41: =COUNTIFS('Test Cases'!$A$2:$A$1513,"TC_BE_*",'Test Cases'!$J$2:$J$1513,"Fail") -> 4 | F41: =COUNTIFS('Test Cases'!$A$2:$A$1513,"TC_BE_*",'Test Cases'!$J$2:$J$1513,"Blocked") -> 5 | G41: =COUNTIFS('Test Cases'!$A$2:$A$1513,"TC_BE_*",'Test Cases'!$J$2:$J$1513,"Not Applicable") -> 0 | H41: =COUNTIFS('Test Cases'!$A$2:$A$1513,"TC_BE_*",'Test Cases'!$J$2:$J$1513,"Not Executed") -> 0 | I41: =IF(C41=0,0,(D41+E41)/C41) -> 0.66666667 | J41: =IF((D41+E41)=0,0,D41/(D41+E41)) -> 0.6 | K41: =IF(C41=0,0,D41/C41) -> 0.4
A42: MS | B42: Mini Statement | C42: =COUNTIF('Test Cases'!$A$2:$A$1513,"TC_MS_*") -> 20 | D42: =COUNTIFS('Test Cases'!$A$2:$A$1513,"TC_MS_*",'Test Cases'!$J$2:$J$1513,"Pass") -> 6 | E42: =COUNTIFS('Test Cases'!$A$2:$A$1513,"TC_MS_*",'Test Cases'!$J$2:$J$1513,"Fail") -> 9 | F42: =COUNTIFS('Test Cases'!$A$2:$A$1513,"TC_MS_*",'Test Cases'!$J$2:$J$1513,"Blocked") -> 5 | G42: =COUNTIFS('Test Cases'!$A$2:$A$1513,"TC_MS_*",'Test Cases'!$J$2:$J$1513,"Not Applicable") -> 0 | H42: =COUNTIFS('Test Cases'!$A$2:$A$1513,"TC_MS_*",'Test Cases'!$J$2:$J$1513,"Not Executed") -> 0 | I42: =IF(C42=0,0,(D42+E42)/C42) -> 0.75 | J42: =IF((D42+E42)=0,0,D42/(D42+E42)) -> 0.4 | K42: =IF(C42=0,0,D42/C42) -> 0.3
A43: CS | B43: Customized Statement | C43: =COUNTIF('Test Cases'!$A$2:$A$1513,"TC_CS_*") -> 27 | D43: =COUNTIFS('Test Cases'!$A$2:$A$1513,"TC_CS_*",'Test Cases'!$J$2:$J$1513,"Pass") -> 4 | E43: =COUNTIFS('Test Cases'!$A$2:$A$1513,"TC_CS_*",'Test Cases'!$J$2:$J$1513,"Fail") -> 23 | F43: =COUNTIFS('Test Cases'!$A$2:$A$1513,"TC_CS_*",'Test Cases'!$J$2:$J$1513,"Blocked") -> 0 | G43: =COUNTIFS('Test Cases'!$A$2:$A$1513,"TC_CS_*",'Test Cases'!$J$2:$J$1513,"Not Applicable") -> 0 | H43: =COUNTIFS('Test Cases'!$A$2:$A$1513,"TC_CS_*",'Test Cases'!$J$2:$J$1513,"Not Executed") -> 0 | I43: =IF(C43=0,0,(D43+E43)/C43) -> 1 | J43: =IF((D43+E43)=0,0,D43/(D43+E43)) -> 0.14814815 | K43: =IF(C43=0,0,D43/C43) -> 0.14814815
A44: CP | B44: Change Password | C44: =COUNTIF('Test Cases'!$A$2:$A$1513,"TC_CP_*") -> 23 | D44: =COUNTIFS('Test Cases'!$A$2:$A$1513,"TC_CP_*",'Test Cases'!$J$2:$J$1513,"Pass") -> 20 | E44: =COUNTIFS('Test Cases'!$A$2:$A$1513,"TC_CP_*",'Test Cases'!$J$2:$J$1513,"Fail") -> 3 | F44: =COUNTIFS('Test Cases'!$A$2:$A$1513,"TC_CP_*",'Test Cases'!$J$2:$J$1513,"Blocked") -> 0 | G44: =COUNTIFS('Test Cases'!$A$2:$A$1513,"TC_CP_*",'Test Cases'!$J$2:$J$1513,"Not Applicable") -> 0 | H44: =COUNTIFS('Test Cases'!$A$2:$A$1513,"TC_CP_*",'Test Cases'!$J$2:$J$1513,"Not Executed") -> 0 | I44: =IF(C44=0,0,(D44+E44)/C44) -> 1 | J44: =IF((D44+E44)=0,0,D44/(D44+E44)) -> 0.86956522 | K44: =IF(C44=0,0,D44/C44) -> 0.86956522
A45: Total | C45: =SUM(C31:C44) -> 353 | D45: =SUM(D31:D44) -> 169 | E45: =SUM(E31:E44) -> 137 | F45: =SUM(F31:F44) -> 47 | G45: =SUM(G31:G44) -> 0 | H45: =SUM(H31:H44) -> 0 | I45: =IF(C45=0,0,(D45+E45)/C45) -> 0.86685552 | J45: =IF((D45+E45)=0,0,D45/(D45+E45)) -> 0.55228758 | K45: =IF(C45=0,0,D45/C45) -> 0.47875354
A47: 4. Results by priority
A48: Priority | C48: Total | D48: Pass | E48: Fail | F48: Blocked | G48: Not Applicable | H48: Not Executed
A49: High | C49: =COUNTIF('Test Cases'!$G$2:$G$1513,"High") -> 217 | D49: =COUNTIFS('Test Cases'!$G$2:$G$1513,"High",'Test Cases'!$J$2:$J$1513,"Pass") -> 114 | E49: =COUNTIFS('Test Cases'!$G$2:$G$1513,"High",'Test Cases'!$J$2:$J$1513,"Fail") -> 79 | F49: =COUNTIFS('Test Cases'!$G$2:$G$1513,"High",'Test Cases'!$J$2:$J$1513,"Blocked") -> 24 | G49: =COUNTIFS('Test Cases'!$G$2:$G$1513,"High",'Test Cases'!$J$2:$J$1513,"Not Applicable") -> 0 | H49: =COUNTIFS('Test Cases'!$G$2:$G$1513,"High",'Test Cases'!$J$2:$J$1513,"Not Executed") -> 0
A50: Medium | C50: =COUNTIF('Test Cases'!$G$2:$G$1513,"Medium") -> 92 | D50: =COUNTIFS('Test Cases'!$G$2:$G$1513,"Medium",'Test Cases'!$J$2:$J$1513,"Pass") -> 42 | E50: =COUNTIFS('Test Cases'!$G$2:$G$1513,"Medium",'Test Cases'!$J$2:$J$1513,"Fail") -> 34 | F50: =COUNTIFS('Test Cases'!$G$2:$G$1513,"Medium",'Test Cases'!$J$2:$J$1513,"Blocked") -> 16 | G50: =COUNTIFS('Test Cases'!$G$2:$G$1513,"Medium",'Test Cases'!$J$2:$J$1513,"Not Applicable") -> 0 | H50: =COUNTIFS('Test Cases'!$G$2:$G$1513,"Medium",'Test Cases'!$J$2:$J$1513,"Not Executed") -> 0
A51: Low | C51: =COUNTIF('Test Cases'!$G$2:$G$1513,"Low") -> 44 | D51: =COUNTIFS('Test Cases'!$G$2:$G$1513,"Low",'Test Cases'!$J$2:$J$1513,"Pass") -> 13 | E51: =COUNTIFS('Test Cases'!$G$2:$G$1513,"Low",'Test Cases'!$J$2:$J$1513,"Fail") -> 24 | F51: =COUNTIFS('Test Cases'!$G$2:$G$1513,"Low",'Test Cases'!$J$2:$J$1513,"Blocked") -> 7 | G51: =COUNTIFS('Test Cases'!$G$2:$G$1513,"Low",'Test Cases'!$J$2:$J$1513,"Not Applicable") -> 0 | H51: =COUNTIFS('Test Cases'!$G$2:$G$1513,"Low",'Test Cases'!$J$2:$J$1513,"Not Executed") -> 0
A53: 5. Requirements coverage (RTM)
A54: Coverage status | C54: Requirements
A55: Pass | C55: =COUNTIF('RTM'!$K$2:$K$500,"Pass") -> 78
A56: Fail | C56: =COUNTIF('RTM'!$K$2:$K$500,"Fail") -> 40
A57: Blocked | C57: =COUNTIF('RTM'!$K$2:$K$500,"Blocked") -> 9
A58: Partially executed | C58: =COUNTIF('RTM'!$K$2:$K$500,"Partially executed") -> 0
A59: Not covered | C59: =COUNTIF('RTM'!$K$2:$K$500,"Not covered") -> 4
A60: Total requirements | C60: =SUM(C55:C59) -> 131
A61: Covered by at least one test case | C61: =IF($C$60=0,0,($C$60-$C$59)/$C$60) -> 0.96946565
A63: 6. Defect summary
A64: Total defects logged | B64: =COUNTA('Bug Report'!$A$2:$A$500) -> 41
A65: Failed / blocked tests covered by a defect | B65: =COUNTIF('Failed-Blocked Tests'!$G$2:$G$500,"BUG_*")&" of "&COUNTA('Failed-Blocked Tests'!$A$2:$A$500) -> 178 of 184
A67: Severity | C67: Open | D67: In Progress | E67: Fixed | F67: Retest | G67: Closed | H67: Rejected | I67: Total
A68: Critical | C68: =COUNTIFS('Bug Report'!$I$2:$I$500,"Critical",'Bug Report'!$K$2:$K$500,"Open") -> 5 | D68: =COUNTIFS('Bug Report'!$I$2:$I$500,"Critical",'Bug Report'!$K$2:$K$500,"In Progress") -> 0 | E68: =COUNTIFS('Bug Report'!$I$2:$I$500,"Critical",'Bug Report'!$K$2:$K$500,"Fixed") -> 0 | F68: =COUNTIFS('Bug Report'!$I$2:$I$500,"Critical",'Bug Report'!$K$2:$K$500,"Retest") -> 0 | G68: =COUNTIFS('Bug Report'!$I$2:$I$500,"Critical",'Bug Report'!$K$2:$K$500,"Closed") -> 0 | H68: =COUNTIFS('Bug Report'!$I$2:$I$500,"Critical",'Bug Report'!$K$2:$K$500,"Rejected") -> 0 | I68: =SUM(C68:H68) -> 5
A69: High | C69: =COUNTIFS('Bug Report'!$I$2:$I$500,"High",'Bug Report'!$K$2:$K$500,"Open") -> 10 | D69: =COUNTIFS('Bug Report'!$I$2:$I$500,"High",'Bug Report'!$K$2:$K$500,"In Progress") -> 0 | E69: =COUNTIFS('Bug Report'!$I$2:$I$500,"High",'Bug Report'!$K$2:$K$500,"Fixed") -> 0 | F69: =COUNTIFS('Bug Report'!$I$2:$I$500,"High",'Bug Report'!$K$2:$K$500,"Retest") -> 0 | G69: =COUNTIFS('Bug Report'!$I$2:$I$500,"High",'Bug Report'!$K$2:$K$500,"Closed") -> 0 | H69: =COUNTIFS('Bug Report'!$I$2:$I$500,"High",'Bug Report'!$K$2:$K$500,"Rejected") -> 0 | I69: =SUM(C69:H69) -> 10
A70: Medium | C70: =COUNTIFS('Bug Report'!$I$2:$I$500,"Medium",'Bug Report'!$K$2:$K$500,"Open") -> 18 | D70: =COUNTIFS('Bug Report'!$I$2:$I$500,"Medium",'Bug Report'!$K$2:$K$500,"In Progress") -> 0 | E70: =COUNTIFS('Bug Report'!$I$2:$I$500,"Medium",'Bug Report'!$K$2:$K$500,"Fixed") -> 0 | F70: =COUNTIFS('Bug Report'!$I$2:$I$500,"Medium",'Bug Report'!$K$2:$K$500,"Retest") -> 0 | G70: =COUNTIFS('Bug Report'!$I$2:$I$500,"Medium",'Bug Report'!$K$2:$K$500,"Closed") -> 0 | H70: =COUNTIFS('Bug Report'!$I$2:$I$500,"Medium",'Bug Report'!$K$2:$K$500,"Rejected") -> 0 | I70: =SUM(C70:H70) -> 18
A71: Low | C71: =COUNTIFS('Bug Report'!$I$2:$I$500,"Low",'Bug Report'!$K$2:$K$500,"Open") -> 8 | D71: =COUNTIFS('Bug Report'!$I$2:$I$500,"Low",'Bug Report'!$K$2:$K$500,"In Progress") -> 0 | E71: =COUNTIFS('Bug Report'!$I$2:$I$500,"Low",'Bug Report'!$K$2:$K$500,"Fixed") -> 0 | F71: =COUNTIFS('Bug Report'!$I$2:$I$500,"Low",'Bug Report'!$K$2:$K$500,"Retest") -> 0 | G71: =COUNTIFS('Bug Report'!$I$2:$I$500,"Low",'Bug Report'!$K$2:$K$500,"Closed") -> 0 | H71: =COUNTIFS('Bug Report'!$I$2:$I$500,"Low",'Bug Report'!$K$2:$K$500,"Rejected") -> 0 | I71: =SUM(C71:H71) -> 8
A72: Total | C72: =SUM(C68:C71) -> 41 | D72: =SUM(D68:D71) -> 0 | E72: =SUM(E68:E71) -> 0 | F72: =SUM(F68:F71) -> 0 | G72: =SUM(G68:G71) -> 0 | H72: =SUM(H68:H71) -> 0 | I72: =SUM(I68:I71) -> 41
A74: Defects by module | C74: Defects
A75: Login | C75: =COUNTIF('Bug Report'!$B$2:$B$500,"[Login]*") -> 7
A76: New Customer | C76: =COUNTIF('Bug Report'!$B$2:$B$500,"[New Customer]*") -> 5
A77: Edit Customer | C77: =COUNTIF('Bug Report'!$B$2:$B$500,"[Edit Customer]*") -> 9
A78: Delete Customer | C78: =COUNTIF('Bug Report'!$B$2:$B$500,"[Delete Customer]*") -> 1
A79: New Account | C79: =COUNTIF('Bug Report'!$B$2:$B$500,"[New Account]*") -> 3
A80: Edit Account | C80: =COUNTIF('Bug Report'!$B$2:$B$500,"[Edit Account]*") -> 1
A81: Delete Account | C81: =COUNTIF('Bug Report'!$B$2:$B$500,"[Delete Account]*") -> 1
A82: Deposit | C82: =COUNTIF('Bug Report'!$B$2:$B$500,"[Deposit]*") -> 2
A83: Withdrawal | C83: =COUNTIF('Bug Report'!$B$2:$B$500,"[Withdrawal]*") -> 2
A84: Fund Transfer | C84: =COUNTIF('Bug Report'!$B$2:$B$500,"[Fund Transfer]*") -> 2
A85: Balance Enquiry | C85: =COUNTIF('Bug Report'!$B$2:$B$500,"[Balance Enquiry]*") -> 1
A86: Mini Statement | C86: =COUNTIF('Bug Report'!$B$2:$B$500,"[Mini Statement]*") -> 1
A87: Customized Statement | C87: =COUNTIF('Bug Report'!$B$2:$B$500,"[Customized Statement]*") -> 4
A88: Change Password | C88: =COUNTIF('Bug Report'!$B$2:$B$500,"[Change Password]*") -> 2
A89: Total | C89: =SUM(C75:C88) -> 41
A91: 7. Exit criteria
A92: Criterion (Test Plan) | C92: Result | E92: Evidence
A93: Planned test cases executed | C93: =IF($B$21+$B$23=0,"Met","Partially met") -> Partially met | E93: ="Executed (Pass + Fail): "&$B$24&" of "&$B$18&"; Blocked: "&$B$21&"; Not Executed: "&$B$23 -> Executed (Pass + Fail): 306 of 353; Blocked: 47; Not Executed: 0
A94: Defects documented | C94: =IF($B$64>0,"Met","Not met") -> Met | E94: =$B$64&" defects logged in the Bug Report; every failed or blocked test is listed in the Failed-Blocked Tests sheet" -> 41 defects logged in the Bug Report; every failed or blocked test is listed in the Failed-Blocked Tests sheet
A95: Every SRS requirement is covered by a test case | C95: =IF($C$59=0,"Met","Partially met") -> Partially met | E95: =$C$59&" of "&$C$60&" requirements have no test case (see the RTM sheet)" -> 4 of 131 requirements have no test case (see the RTM sheet)
A96: No open Critical defects (quality gate) | C96: =IF($C$68=0,"Met","Not met") -> Not met | E96: =$C$68&" Critical and "&$C$69&" High defects are open" -> 5 Critical and 10 High defects are open
A98: 8. Conclusion
A99: =IF($C$68>0,"Release is NOT recommended. "&$C$68&" Critical and "&$C$69&" High defects are open, and "&$B$21&" tests could not be completed because of them. The pass rate is "&TEXT($B$27,"0%")&" of all test cases.","The Critical defects are closed. Review the open High defects before release. The pass rate is "&TEXT($B$27,"0%")&" of all test cases.") -> Release is NOT recommended. 5 Critical and 10 High defects are open, and 47 tests could not be completed because of them. The pass rate is 48% of all test cases.
A101: 9. Key findings
A102: - Core banking operations could not be completed on the tested site: Deposit, Balance Enquiry and Fund Transfer end on an error page, a blank page or without any message, which blocked the dependent balance, statement and validation tests.
A103: - Mini Statement, Customized Statement, Edit Account and Delete Account also fail for valid input, and Withdrawal does not show whether a withdrawal succeeded.
A104: - Security: the login can be bypassed with SQL injection input, protected pages open without authentication, accounts are not locked after 3 failed attempts, the session survives Logout and credentials are not case-sensitive.
A105: - Validation: Edit Customer, Customized Statement and Change Password do not enforce the SRS rules (invalid, blank and duplicate values are saved); New Customer accepts customers under 18 and invalid mobile/password lengths.
A106: - Several input fields are shorter than the SRS lengths (Name 25, Address 50, City/State 25, Description 10-20, Initial Deposit 8 digits), and the Description limit prevented the XSS tests in Deposit, Withdrawal and Fund Transfer.
A107: - Basic input validations (blank and non-numeric values) pass in most modules, for example New Customer, New Account, Deposit, Withdrawal, Fund Transfer and Mini Statement.
A109: 10. Limitations and coverage gaps
A110: - Tests that needed a second Manager account, an account with a zero balance or data that depends on a broken page were Blocked or could not be completed (see the Failed-Blocked Tests sheet and Test Data Setup).
A111: - No test case covers a login as Customer, the 15-minute session timeout or the Customer-role rules FT12, MS5 and CS9 (see the RTM sheet), so the Customer role was not exercised.
A112: - Performance and stress testing, automation and non-functional checks are out of scope according to the Test Plan.
...

Sheet Test Data Setup
A1: Test Data Setup
A2: Data used by the test cases (taken from the Test Data and Actual result columns of the Test Cases sheet).
A4: 1. General
A5: Application | B5: Guru99 Bank demo site (V2): https://demo.guru99.com/V2/
A6: Browser | B6: Google Chrome
A7: Roles | B7: Manager and Customer
A8: Legend | B8: "◄" marks the field under test. "[Attempt n]" values are entered one after another. "B", "B1", "B2" are balances noted before the test. Dates are relative to the execution date.
A10: 2. Login accounts
A11: Account | B11: User ID | C11: Password | D11: Used in | E11: Notes
A12: Manager (main) | B12: mngr668217 | C12: rUqyzUv | D12: TC_LG_001 - TC_LG_018 and every module up to Change Password | E12: The password changes in the Change Password module (see the password chain below).
A13: Manager (first run) | B13: mngr667952 | C13: dYnAbAp | D13: TC_LG_001 - TC_LG_003 were first executed with this account | E13: Test data now uses the main Manager account so that all tests share the same login.
A14: Manager 2 | B14: not recorded | C14: not recorded | D14: Tests for accounts/customers of another Manager (E44) | E14: Its customers and accounts are not recorded in the tests.
A15: Customer | B15: not recorded | C15: not recorded | D15: Customer-role tests | E15: No customer credentials are recorded in the test data.
A16: Unknown user | B16: ghost999 | C16: Pass@123 | D16: TC_LG_005 | E16: User ID that does not exist.
A17: Wrong password | B17: mngr668217 | C17: wrongpas | D17: TC_LG_006, TC_LG_009 | E17: Valid User ID with an incorrect password.
A18: Case variants | B18: MNGR668217 / mngr668217 | C18: rUqyzUv / RUQYZUV | D18: TC_LG_007, TC_LG_008 | E18: Uppercase User ID; password with different casing.
A19: Special inputs | B19: ' OR '1'='1 / mngr 668217 | C19: x / rUqyzUv | D19: TC_LG_014, TC_LG_015 | E19: SQL injection string; User ID with a space inside.
A20: Password chain (Change Password) | D20: TC_CP_001 - TC_CP_023 | E20: rUqyzUv -> NewPass@456 (TC_CP_001) -> Ab@12 (TC_CP_010) -> Ab@123 (TC_CP_011) -> 30-character password -> 31-character password (TC_CP_015) -> P@$$w0rd!#% (TC_CP_016) -> P@ss word 1 (TC_CP_017). Each test uses the password set by the previous one.
A22: 3. Customers
A23: Customer ID | B23: Role in the tests | C23: Created in | D23: Key data | E23: Used in / notes
A24: 4073 | B24: Customer edited, then deleted | C24: TC_NC_001 | D24: John Smith, Male, 1990-05-15, 12 Main Street, Alexandria, Alexandria, PIN 123456, mobile 5551234567, password Pass@123, john.smith01@test.com | E24: Edited by TC_EC_010 - TC_EC_039 (its data changes) and deleted in TC_DC_001; ID 4073 is also used in TC_NC_005 and TC_DC_014.
A25: 4620 | B25: Customer A | C25: TC_NC_004 | D25: John Smith, Male, 1990-05-15, 12 Main Street, Alexandria, Alexandria, PIN 123456, mobile 5551234567, password Pass@123, john.smith04a@test.com | E25: Created together with customer B to check that Customer IDs are unique.
A26: 78692 | B26: Customer B | C26: TC_NC_004 | D26: John Smith, Male, 1990-05-15, 12 Main Street, Alexandria, Alexandria, PIN 123456, mobile 5551234567, password Pass@123, john.smith04b@test.com | E26: Email used as the "existing email" in TC_EC_035.
A27: 4273 | B27: Age boundary | C27: TC_NC_015 | D27: Date of birth = execution date - 18 years | E27: Valid customer.
A28: 52817 | B28: Age boundary | C28: TC_NC_016 | D28: Date of birth = (execution date - 18 years) + 1 day | E28: Created although under 18 (defect).
A29: 27595 | B29: Underage customer | C29: TC_NC_017 | D29: Date of birth = execution date - 10 years | E29: Created although under 18 (defect).
A30: 69229 | B30: Future date of birth | C30: TC_NC_018 | D30: Date of birth = tomorrow's date | E30: Created with a future date (defect).
A31: 63551 | B31: Alphanumeric address | C31: TC_NC_021 | D31: Address: 12 Main Street Apt 5 | E31: Valid customer.
A32: 33471 | B32: Short mobile number | C32: TC_NC_036 | D32: Mobile number: 555123456 (9 digits) | E32: Created with an invalid mobile length (defect).
A33: 78251 | B33: Long mobile number | C33: TC_NC_037 | D33: Mobile number: 55512345678 (11 digits) | E33: Created with an invalid mobile length (defect).
A34: 790 | B34: Short password | C34: TC_NC_044 | D34: Password: Ab@12 (5 characters) | E34: Created with an invalid password length (defect).
... A36: IDs not recorded | B36: Customers created by passed tests | C36: TC_NC_010, TC_NC_045, TC_NC_052 | D36: Mary Ann Lee; password Ab@123; double submission | E36: Customer IDs were not written in the Actual result.
A38: 4. Accounts
A39: Account number | B39: Customer | C39: Type / initial deposit | D39: Created in | E39: Used in / notes
A40: 185657 | B40: 38892 | C40: Savings / 1000 | D40: TC_NA_001 | E40: Main account for Deposit, Withdrawal, Edit Account, Delete Account (TC_DA_011) and the balance checks of TC_BE_004 / TC_BE_005.
A41: 185658 | B41: 38892 | C41: Current / 5000 | D41: TC_NA_002 | E41: Second account (TC_EA_005, Deposit and Withdrawal tests).
A42: 185659 | B42: 38892 | C42: Savings / 1500 | D42: TC_NA_006 | E42: Second Savings account of the same customer.
A43: 185660 | B43: 38892 | C43: Savings / 500 | D43: TC_NA_018 | E43: Minimum initial deposit (boundary).
A44: 185661 | B44: 38892 | C44: Savings / 501 | D44: TC_NA_019 | E44: Boundary + 1.
A45: 185662 | B45: 38892 | C45: Savings / 0500 (read as 500) | D45: TC_NA_024 | E45: Leading zeros.
A46: 185664 | B46: 38892 | C46: Savings / 1000 | D46: TC_NA_029 | E46: Double submission.
A47: 185671 | B47: not recorded | C47: not recorded | D47: not recorded | E47: Fund Transfer payer (TC_FT_001 and the other transfer tests); TC_BE_006; payee in TC_MS_012; TC_MS_013.
A48: 185672 | B48: not recorded | C48: not recorded | D48: not recorded | E48: Fund Transfer payee; also used as "account of another Manager" in TC_MS_019 (please confirm).
A49: 185674 | B49: not recorded | C49: not recorded | D49: not recorded | E49: Balance Enquiry (TC_BE_001), Mini Statement (TC_MS_*) and Customized Statement (TC_CS_*) tests.
A51: 5. Data used by module
A52: Module | B52: Data used
A53: Login | B53: Manager mngr668217 / rUqyzUv and the invalid logins listed above.
A54: New Customer | B54: Baseline customer (John Smith ...) with a unique email john.smithNN@test.com per test (NN = test number); boundary and invalid values of section 6.
A55: Edit Customer | B55: Customer 4073; email of customer 78692 (john.smith04b@test.com) and a1a@gmail.com as existing emails; new values: 45 Park Avenue, Cairo, 654321, 5559876543, john.edit10@test.com.
A56: Delete Customer | B56: Customer 4073 (no accounts) for deletion; customer 38892 (has accounts 185657 and 185658) for the active-accounts rule.
A57: New Account | B57: Customer 38892; Savings / Current; initial deposits 1000, 5000, 1500, 500, 501, 0500 and invalid values.
A58: Edit Account | B58: Accounts 185657 (Savings) and 185658 (Current).
A59: Delete Account | B59: Account 185657 (balance 1000.00). A zero-balance account is not available.
A60: Deposit | B60: Account 185657; amount 500; description "Salary deposit".
A61: Withdrawal | B61: Account 185657; amount 200; description "ATM withdrawal"; B = current balance.
A62: Fund Transfer | B62: Payer 185671, payee 185672; amount 100; description "Rent payment".
A63: Balance Enquiry | B63: Account 185674; accounts 185657, 185671 and 185672 for the balance checks after other operations.
... A66: Change Password | B66: Manager mngr668217 and the password chain of section 2.
A68: 6. Boundary and special values
A69: Field | B69: Values
A70: Customer Name | B70: 50 letters: AbcdefghijAbcdefghijAbcdefghijAbcdefghijAbcdefghij; 51 letters: the same + k; John123; John@#$; " John" (leading space); Mary Ann Lee
A71: Address | B71: 200 characters: "Main Street 12 " repeated and cut at 200; 201 characters: the same + A; @#$%^&; 12 Main Street Apt 5
A72: City / State | B72: 50 and 51 letters; Cairo123; Cairo@#; Giza12
A73: PIN Code | B73: 12345 (5 digits); 123456 (6 digits); 1234567 (7 digits); 12AB56; 12@#56
A74: Mobile Number | B74: 555123456 (9 digits); 5551234567 (10 digits); 55512345678 (11 digits); 55512ABC90; 555123@#90
A75: Email | B75: 50 characters: a x 41 + @test.com; 51 characters: a x 42 + @test.com; john.smith; john@; @test.com; john@test; john smith@test.com; JOHN.SMITH01@TEST.COM
A76: Password | B76: Ab@12 (5); Ab@123 (6); 30 characters: Ab@123 + 24 x; 31 characters: Ab@123 + 25 x; P@$$w0rd!#%; P@ss word 1
A77: IDs and account numbers | B77: ABC123; 12@#45; 0; -5; 12.5; 999999999 (customer that does not exist); 999999999999999 (account that does not exist); 12345678901 (11 digits)
A78: Amounts | B78: 0; 0.01; 100; 100.50; 100.555; -100; 499; 500; 501; B - 1; B; B + 1; 99999999999999999999 (20 digits); abc; 50@0; 5 00
A79: Description | B79: 200 and 201 characters ("Payment note 12 " repeated); Salary & bonus - Oct #2 (50%)
A80: Injection strings | B80: ' OR '1'='1 | 1 OR 1=1 | 500' OR '1'='1 | 100' OR '1'='1 | <script>alert('x')</script>
A82: 7. Data not available or to be confirmed
A83: - A zero-balance account cannot be created (minimum initial deposit is 500), so TC_DA_001 - TC_DA_003, TC_DA_012 and the zero-balance tests have no data.
A84: - The second Manager (Manager 2) and its customers/accounts are not recorded; the "another Manager" tests use a description instead of an ID.
A85: - Owner, type, initial deposit and balances of accounts 185671, 185672 and 185674 are not recorded.
A86: - Account 185672 is a payee in the Fund Transfer tests and also "another Manager's account" in TC_MS_019: please confirm.
A87: - Customer 38892: the test that created it is not recorded.
A88: - TC_MS_001, TC_MS_003 and TC_MS_004 use the same account (185674) for ">5", "exactly 5" and "1 to 4" transactions, which cannot all be true at the same time.
A89: - No customer login credentials are recorded, so no test was executed as a Customer.
